Workbook

Sheet Reading guide, SIGN of NPS
B1: How to interpret NPS scores
B3: NPS is a calculated score:
B4: • Calculated based on three subgroups (see visual)
B5: • Lower number of completes per group means more fluctuations
B6: • Significance testing needs to be on promoters and detractors, so
B7: differences on NPS from one to another quarter are hardly ever significant (see more info on sig. testing below)
B10: Manage fluctuations:
B11: • Increased sample sizes for more stability. Key objective of BAM is to measure brand performance among general population, so not all brands have an equal number of clients (base for NPS). Fewer clients causes higher error margin, especially for NPS.
B12: • 6-months average. Because it is too expensive to enlarge total sample for NPS purposes only, we report a average of six months to increase base size. Error margin remains quite large in countries where the market share of ING is limited (also applicable to competition).
B15: Ranking NPS performance:
B16: In markets with limited differentiation, slight change can create totally different rankings. In fact, this could be caused by the error margin of NPS and not due to actual change. The NPS rankings need to be interpreted with this in mind.
B19: Significance of NPS scores
... B27: Rough estimated delta required before NPS change is significant (95% confidence):
C30: Base size | D30: Delta required (assum. NPS=0) | E30: Delta required (assum. NPS=35) | F30: Delta required (assum. NPS=65)
C31: 50 | D31: 30.441649 | E31: 28.065814 | F31: 22.490453
C32: 100 | D32: 21.525497 | E32: 19.845527 | F32: 15.903152
C33: 150 | D33: 17.575494 | E33: 16.203805 | F33: 12.984869
C34: 200 | D34: 15.220825 | E34: 14.032907 | F34: 11.245226
C35: 300 | D35: 12.427751 | E35: 11.45782 | F35: 9.181689
C36: 400 | D36: 10.762748 | E36: 9.9227636 | F36: 7.9515759
C37: 500 | D37: 9.6264947 | E37: 8.8751896 | F37: 7.1121057
C38: 700 | D38: 8.1358729 | E38: 7.5009042 | F38: 6.0108264
C39: 1000 | D39: 6.8069597 | E39: 6.2757067 | F39: 5.0290182

Sheet Quarterly overview new
B2: Source: Global NPS tracking / Toluna | D2: Q4 - 2025
B4: Australia | D4: NPS | E4: Rank | F4: n
B5: ING | D5: ='Australia (quarter)'!C6 -> #REF! | E5: ='Australia (quarter)'!C49 -> #REF! | F5: ='Australia (quarter)'!C56 -> #REF!
B6: ANZ | D6: ='Australia (quarter)'!C14 -> #REF! | E6: ='Australia (quarter)'!C50 -> #REF! | F6: ='Australia (quarter)'!C57 -> #REF!
B7: Commonwealth Bank | D7: ='Australia (quarter)'!C21 -> #REF! | E7: ='Australia (quarter)'!C51 -> #REF! | F7: ='Australia (quarter)'!C58 -> #REF!
B8: NAB (National Australia Bank) | D8: ='Australia (quarter)'!C28 -> #REF! | E8: ='Australia (quarter)'!C52 -> #REF! | F8: ='Australia (quarter)'!C59 -> #REF!
B9: Westpac | D9: ='Australia (quarter)'!C35 -> #REF! | E9: ='Australia (quarter)'!C53 -> #REF! | F9: ='Australia (quarter)'!C60 -> #REF!
B11: Belgium | D11: NPS | E11: Rank | F11: n
B12: ING | D12: ='Belgium (quarter)'!C35 -> #REF! | E12: ='Belgium (quarter)'!C41 -> #REF! | F12: ='Belgium (quarter)'!C47 -> #REF!
B13: Belfius | D13: ='Belgium (quarter)'!C36 -> #REF! | E13: ='Belgium (quarter)'!C42 -> #REF! | F13: ='Belgium (quarter)'!C48 -> #REF!
B14: BNP Paribas Fortis | D14: ='Belgium (quarter)'!C37 -> #REF! | E14: ='Belgium (quarter)'!C43 -> #REF! | F14: ='Belgium (quarter)'!C49 -> #REF!
B15: KBC/CBC | D15: ='Belgium (quarter)'!C38 -> #REF! | E15: ='Belgium (quarter)'!C44 -> #REF! | F15: ='Belgium (quarter)'!C50 -> #REF!
B17: Germany | D17: NPS | E17: Rank | F17: n
B18: ING | D18: ='Germany (quarter)'!C6 -> #REF! | E18: ='Germany (quarter)'!C57 -> #REF! | F18: ='Germany (quarter)'!C65 -> #REF!
B19: Commerzbank | D19: ='Germany (quarter)'!C14 -> #REF! | E19: ='Germany (quarter)'!C58 -> #REF! | F19: ='Germany (quarter)'!C66 -> #REF!
B20: DKB | D20: ='Germany (quarter)'!C21 -> #REF! | E20: ='Germany (quarter)'!C59 -> #REF! | F20: ='Germany (quarter)'!C67 -> #REF!
B21: Postbank | D21: ='Germany (quarter)'!C28 -> #REF! | E21: ='Germany (quarter)'!C60 -> #REF! | F21: ='Germany (quarter)'!C68 -> #REF!
B22: Sparkasse | D22: ='Germany (quarter)'!C35 -> #REF! | E22: ='Germany (quarter)'!C61 -> #REF! | F22: ='Germany (quarter)'!C69 -> #REF!
B23: VR-Banken | D23: ='Germany (quarter)'!C42 -> #REF! | E23: ='Germany (quarter)'!C62 -> #REF! | F23: ='Germany (quarter)'!C70 -> #REF!
B25: Italy | D25: NPS | E25: Rank | F25: n
B26: ING | D26: ='Italy (quarter)'!C6 -> #REF! | E26: ='Italy (quarter)'!C57 -> #REF! | F26: ='Italy (quarter)'!C65 -> #REF!
B27: Banca Mediolanum | D27: ='Italy (quarter)'!C14 -> #REF! | E27: ='Italy (quarter)'!C58 -> #REF! | F27: ='Italy (quarter)'!C66 -> #REF!
B28: BancoPosta | D28: ='Italy (quarter)'!C21 -> #REF! | E28: ='Italy (quarter)'!C59 -> #REF! | F28: ='Italy (quarter)'!C67 -> #REF!
B29: Fineco | D29: ='Italy (quarter)'!C28 -> #REF! | E29: ='Italy (quarter)'!C60 -> #REF! | F29: ='Italy (quarter)'!C68 -> #REF!
B30: Intesa Sanpaolo | D30: ='Italy (quarter)'!C35 -> #REF! | E30: ='Italy (quarter)'!C61 -> #REF! | F30: ='Italy (quarter)'!C69 -> #REF!
B31: Unicredit | D31: ='Italy (quarter)'!C42 -> #REF! | E31: ='Italy (quarter)'!C62 -> #REF! | F31: ='Italy (quarter)'!C70 -> #REF!
B33: Luxembourg | D33: NPS | E33: Rank | F33: n
B34: ING | D34: =#REF! -> #REF! | E34: =#REF! -> #REF! | F34: =#REF! -> #REF!
B35: Banque et Caisse d’Epargne de l’Etat / Spuerkeess / BCEE | D35: =#REF! -> #REF! | E35: =#REF! -> #REF! | F35: =#REF! -> #REF!
B36: Banque International a Luxembourg | D36: =#REF! -> #REF! | E36: =#REF! -> #REF! | F36: =#REF! -> #REF!
B37: BGL BNP Paribas | D37: =#REF! -> #REF! | E37: =#REF! -> #REF! | F37: =#REF! -> #REF!
B38: Post | D38: =#REF! -> #REF! | E38: =#REF! -> #REF! | F38: =#REF! -> #REF!
B39: Raiffeisen | D39: =#REF! -> #REF! | E39: =#REF! -> #REF! | F39: =#REF! -> #REF!
B41: The Netherlands | D41: NPS | E41: Rank | F41: n
B42: ING | D42: ='Netherlands (quarter)'!C35 -> #REF! | E42: ='Netherlands (quarter)'!C41 -> #REF! | F42: ='Netherlands (quarter)'!C47 -> #REF!
B43: ABN AMRO | D43: ='Netherlands (quarter)'!C36 -> #REF! | E43: ='Netherlands (quarter)'!C42 -> #REF! | F43: ='Netherlands (quarter)'!C48 -> #REF!
B44: Rabobank | D44: ='Netherlands (quarter)'!C37 -> #REF! | E44: ='Netherlands (quarter)'!C43 -> #REF! | F44: ='Netherlands (quarter)'!C49 -> #REF!
B45: SNS bank | D45: ='Netherlands (quarter)'!#REF! -> #REF! | E45: ='Netherlands (quarter)'!#REF! -> #REF! | F45: ='Netherlands (quarter)'!#REF! -> #REF!
B46: ASN bank | D46: ='Netherlands (quarter)'!C38 -> #REF! | E46: ='Netherlands (quarter)'!C44 -> #REF! | F46: ='Netherlands (quarter)'!C50 -> #REF!
B48: Poland | D48: NPS | E48: Rank | F48: n
B49: ING | D49: ='Poland (quarter)'!C49 -> #REF! | E49: ='Poland (quarter)'!C57 -> #REF! | F49: ='Poland (quarter)'!C65 -> #REF!
B50: Velo bank (previously Getin Bank) | D50: ='Poland (quarter)'!C50 -> #REF! | E50: ='Poland (quarter)'!C58 -> #REF! | F50: ='Poland (quarter)'!C66 -> #REF!
B51: mBank | D51: ='Poland (quarter)'!C51 -> #REF! | E51: ='Poland (quarter)'!C59 -> #REF! | F51: ='Poland (quarter)'!C67 -> #REF!
B52: Pekao S.A. | D52: ='Poland (quarter)'!C52 -> #REF! | E52: ='Poland (quarter)'!C60 -> #REF! | F52: ='Poland (quarter)'!C68 -> #REF!
B53: PKO BP (Powszechna Kasa Oszczędności BP) | D53: ='Poland (quarter)'!C53 -> #REF! | E53: ='Poland (quarter)'!C61 -> #REF! | F53: ='Poland (quarter)'!C69 -> #REF!
B54: Santander | D54: ='Poland (quarter)'!C54 -> #REF! | E54: ='Poland (quarter)'!C62 -> #REF! | F54: ='Poland (quarter)'!C70 -> #REF!
B56: Romania | D56: NPS | E56: Rank | F56: n
B57: ING | D57: ='Romania (quarter)'!C42 -> #REF! | E57: ='Romania (quarter)'!C49 -> #REF! | F57: ='Romania (quarter)'!C56 -> #REF!
B58: Banca Transilvania | D58: ='Romania (quarter)'!C43 -> #REF! | E58: ='Romania (quarter)'!C50 -> #REF! | F58: ='Romania (quarter)'!C57 -> #REF!
B59: BCR | D59: ='Romania (quarter)'!C44 -> #REF! | E59: ='Romania (quarter)'!C51 -> #REF! | F59: ='Romania (quarter)'!C58 -> #REF!
B60: BRD | D60: ='Romania (quarter)'!C45 -> #REF! | E60: ='Romania (quarter)'!C52 -> #REF! | F60: ='Romania (quarter)'!C59 -> #REF!
B61: Raiffeisen Bank | D61: ='Romania (quarter)'!C46 -> #REF! | E61: ='Romania (quarter)'!C53 -> #REF! | F61: ='Romania (quarter)'!C60 -> #REF!
B63: Spain | D63: NPS | E63: Rank | F63: n
B64: ING | D64: ='Spain (quarter)'!C42 -> #REF! | E64: ='Spain (quarter)'!C49 -> #REF! | F64: ='Spain (quarter)'!C56 -> #REF!
B65: Banco Santander | D65: ='Spain (quarter)'!C43 -> #REF! | E65: ='Spain (quarter)'!C50 -> #REF! | F65: ='Spain (quarter)'!C57 -> #REF!
B66: BBVA | D66: ='Spain (quarter)'!C44 -> #REF! | E66: ='Spain (quarter)'!C51 -> #REF! | F66: ='Spain (quarter)'!C58 -> #REF!
B67: Caixabank | D67: ='Spain (quarter)'!C45 -> #REF! | E67: ='Spain (quarter)'!C52 -> #REF! | F67: ='Spain (quarter)'!C59 -> #REF!
B68: Openbank | D68: ='Spain (quarter)'!C46 -> #REF! | E68: ='Spain (quarter)'!C53 -> #REF! | F68: ='Spain (quarter)'!C60 -> #REF!
B70: Turkey | D70: NPS | E70: Rank | F70: n
B71: ING | D71: ='Turkey (quarter)'!C42 -> #REF! | E71: ='Turkey (quarter)'!C49 -> #REF! | F71: ='Turkey (quarter)'!C56 -> #REF!
B72: Akbank | D72: ='Turkey (quarter)'!C43 -> #REF! | E72: ='Turkey (quarter)'!C50 -> #REF! | F72: ='Turkey (quarter)'!C57 -> #REF!
B73: Garanti Bankası | D73: ='Turkey (quarter)'!C44 -> #REF! | E73: ='Turkey (quarter)'!C51 -> #REF! | F73: ='Turkey (quarter)'!C58 -> #REF!
B74: İş Bankası | D74: ='Turkey (quarter)'!C45 -> #REF! | E74: ='Turkey (quarter)'!C52 -> #REF! | F74: ='Turkey (quarter)'!C59 -> #REF!
B75: Yapı Kredi Bankası | D75: ='Turkey (quarter)'!C46 -> #REF! | E75: ='Turkey (quarter)'!C53 -> #REF! | F75: ='Turkey (quarter)'!C60 -> #REF!

Sheet Countries overview (monthly)
B2: Source: Global NPS tracking / Toluna | C2: January - 2026 | F2: February - 2026 | I2: March - 2026
B4: Australia | C4: NPS | D4: Rank | E4: n | F4: NPS | G4: Rank | H4: n | I4: NPS | J4: Rank | K4: n
B5: Commonwealth Bank | C5: ='Australia (Month)'!C42 -> 43.719344 | D5: =RANK(C5,$C$5:$C$22,0) -> 3 | E5: ='Australia (Month)'!C57 -> 331 | F5: ='Australia (Month)'!D42 -> 42.72414 | G5: =RANK(F5,$F$5:$F$22,0) -> 2 | H5: ='Australia (Month)'!D57 -> 401 | I5: ='Australia (Month)'!E42 -> 43.929886 | J5: =RANK(I5,$I$5:$I$22,0) -> 1 | K5: ='Australia (Month)'!E57 -> 391
B6: ANZ | C6: ='Australia (Month)'!C24 -> 44.621825 | D6: =RANK(C6,$C$5:$C$22,0) -> 2 | E6: ='Australia (Month)'!C39 -> 124 | F6: ='Australia (Month)'!D24 -> 42.488528 | G6: =RANK(F6,$F$5:$F$22,0) -> 3 | H6: ='Australia (Month)'!D39 -> 157 | I6: ='Australia (Month)'!E24 -> 38.373295 | J6: =RANK(I6,$I$5:$I$22,0) -> 2 | K6: ='Australia (Month)'!E39 -> 149
B7: Westpac | C7: ='Australia (Month)'!C78 -> 50.112199 | D7: =RANK(C7,$C$5:$C$22,0) -> 1 | E7: ='Australia (Month)'!C93 -> 113 | F7: ='Australia (Month)'!D78 -> 44.665324 | G7: =RANK(F7,$F$5:$F$22,0) -> 1 | H7: ='Australia (Month)'!D93 -> 141 | I7: ='Australia (Month)'!E78 -> 37.664561 | J7: =RANK(I7,$I$5:$I$22,0) -> 3 | K7: ='Australia (Month)'!E93 -> 137
B8: NAB (National Australia Bank) | C8: ='Australia (Month)'!C60 -> 31.411084 | D8: =RANK(C8,$C$5:$C$22,0) -> 4 | E8: ='Australia (Month)'!C75 -> 104 | F8: ='Australia (Month)'!D60 -> 29.606533 | G8: =RANK(F8,$F$5:$F$22,0) -> 4 | H8: ='Australia (Month)'!D75 -> 120 | I8: ='Australia (Month)'!E60 -> 29.562953 | J8: =RANK(I8,$I$5:$I$22,0) -> 4 | K8: ='Australia (Month)'!E75 -> 117
B9: ING | C9: ='Australia (Month)'!C6 -> 17.404865 | D9: =RANK(C9,$C$5:$C$22,0) -> 5 | E9: ='Australia (Month)'!C21 -> 42 | F9: ='Australia (Month)'!D6 -> 20.861557 | G9: =RANK(F9,$F$5:$F$22,0) -> 5 | H9: ='Australia (Month)'!D21 -> 53 | I9: ='Australia (Month)'!E6 -> 13.983207 | J9: =RANK(I9,$I$5:$I$22,0) -> 5 | K9: ='Australia (Month)'!E21 -> 48
B10: Bank of Australia | C10: ='Australia (Month)'!C96 -> Low N | D10: Low N | E10: ='Australia (Month)'!C111 -> 39 | F10: ='Australia (Month)'!D96 -> Low N | G10: Low N | H10: ='Australia (Month)'!D111 -> 53 | I10: ='Australia (Month)'!E96 -> Low N | J10: Low N | K10: ='Australia (Month)'!E111 -> 52
B11: Bankwest | C11: ='Australia (Month)'!C114 -> Low N | D11: Low N | E11: ='Australia (Month)'!C129 -> 19 | F11: ='Australia (Month)'!D114 -> Low N | G11: Low N | H11: ='Australia (Month)'!D129 -> 25 | I11: ='Australia (Month)'!E114 -> Low N | J11: Low N | K11: ='Australia (Month)'!E129 -> 25
B12: Bendigo Bank | C12: ='Australia (Month)'!C132 -> Low N | D12: Low N | E12: ='Australia (Month)'!C147 -> 25 | F12: ='Australia (Month)'!D132 -> Low N | G12: Low N | H12: ='Australia (Month)'!D147 -> 31 | I12: ='Australia (Month)'!E132 -> Low N | J12: Low N | K12: ='Australia (Month)'!E147 -> 26
B13: BoQ | C13: ='Australia (Month)'!C150 -> Low N | D13: Low N | E13: ='Australia (Month)'!C165 -> 13 | F13: ='Australia (Month)'!D150 -> Low N | G13: Low N | H13: ='Australia (Month)'!D165 -> 14 | I13: ='Australia (Month)'!E150 -> Low N | J13: Low N | K13: ='Australia (Month)'!E165 -> 13
B14: Citibank | C14: ='Australia (Month)'!C168 -> Low N | D14: Low N | E14: ='Australia (Month)'!C183 -> 34 | F14: ='Australia (Month)'!D168 -> Low N | G14: Low N | H14: ='Australia (Month)'!D183 -> 43 | I14: ='Australia (Month)'!E168 -> Low N | J14: Low N | K14: ='Australia (Month)'!E183 -> 40
B15: HSBC | C15: ='Australia (Month)'!C186 -> Low N | D15: Low N | E15: ='Australia (Month)'!C201 -> 53 | F15: ='Australia (Month)'!D186 -> Low N | G15: Low N | H15: ='Australia (Month)'!D201 -> 67 | I15: ='Australia (Month)'!E186 -> Low N | J15: Low N | K15: ='Australia (Month)'!E201 -> 49
B16: Macquarie Bank | C16: ='Australia (Month)'!C204 -> Low N | D16: Low N | E16: ='Australia (Month)'!C219 -> 55 | F16: ='Australia (Month)'!D204 -> Low N | G16: Low N | H16: ='Australia (Month)'!D219 -> 68 | I16: ='Australia (Month)'!E204 -> Low N | J16: Low N | K16: ='Australia (Month)'!E219 -> 65
B17: MEBank (Members Equity) | C17: ='Australia (Month)'!C222 -> Low N | D17: Low N | E17: ='Australia (Month)'!C237 -> 13 | F17: ='Australia (Month)'!D222 -> Low N | G17: Low N | H17: ='Australia (Month)'!D237 -> 16 | I17: ='Australia (Month)'!E222 -> Low N | J17: Low N | K17: ='Australia (Month)'!E237 -> 15
B18: St George | C18: ='Australia (Month)'!C240 -> Low N | D18: Low N | E18: ='Australia (Month)'!C255 -> 34 | F18: ='Australia (Month)'!D240 -> Low N | G18: Low N | H18: ='Australia (Month)'!D255 -> 39 | I18: ='Australia (Month)'!E240 -> Low N | J18: Low N | K18: ='Australia (Month)'!E255 -> 34
B19: Suncorp | C19: ='Australia (Month)'!C258 -> Low N | D19: Low N | E19: ='Australia (Month)'!C273 -> 32 | F19: ='Australia (Month)'!D258 -> Low N | G19: Low N | H19: ='Australia (Month)'!D273 -> 39 | I19: ='Australia (Month)'!E258 -> Low N | J19: Low N | K19: ='Australia (Month)'!E273 -> 33
B20: Ubank | C20: ='Australia (Month)'!C276 -> Low N | D20: Low N | E20: ='Australia (Month)'!C291 -> 14 | F20: ='Australia (Month)'!D276 -> Low N | G20: Low N | H20: ='Australia (Month)'!D291 -> 15 | I20: ='Australia (Month)'!E276 -> Low N | J20: Low N | K20: ='Australia (Month)'!E291 -> 19
B21: Revolut | C21: ='Australia (Month)'!C294 -> Low N | D21: Low N | E21: ='Australia (Month)'!C309 -> 30 | F21: ='Australia (Month)'!D294 -> Low N | G21: Low N | H21: ='Australia (Month)'!D309 -> 40 | I21: ='Australia (Month)'!E294 -> Low N | J21: Low N | K21: ='Australia (Month)'!E309 -> 42
B22: Up bank | C22: ='Australia (Month)'!C312 -> Low N | D22: Low N | E22: ='Australia (Month)'!C327 -> 13 | F22: ='Australia (Month)'!D312 -> Low N | G22: Low N | H22: ='Australia (Month)'!D327 -> 14 | I22: ='Australia (Month)'!E312 -> Low N | J22: Low N | K22: ='Australia (Month)'!E327 -> 14
B24: Belgium | C24: NPS | D24: Rank | E24: n | F24: NPS | G24: Rank | H24: n | I24: NPS | J24: Rank | K24: n
B25: Revolut | C25: ='Belgium (Month)'!C204 -> Low N | D25: Low N | E25: ='Belgium (Month)'!C219 -> 84 | F25: ='Belgium (Month)'!D204 -> 27.184115 | G25: =RANK(F25,$F$25:$F$40,0) -> 1 | H25: ='Belgium (Month)'!D219 -> 108 | I25: ='Belgium (Month)'!E204 -> 29.562701 | J25: =RANK(I25,$I$25:$I$40,0) -> 1 | K25: ='Belgium (Month)'!E219 -> 115
B26: Keytrade Bank | C26: ='Belgium (Month)'!C186 -> 19.826581 | D26: =RANK(C26,$C$25:$C$40,0) -> 1 | E26: ='Belgium (Month)'!C201 -> 131 | F26: ='Belgium (Month)'!D186 -> 20.382306 | G26: =RANK(F26,$F$25:$F$40,0) -> 2 | H26: ='Belgium (Month)'!D201 -> 152 | I26: ='Belgium (Month)'!E186 -> 25.261652 | J26: =RANK(I26,$I$25:$I$40,0) -> 2 | K26: ='Belgium (Month)'!E201 -> 148
B27: Argenta | C27: ='Belgium (Month)'!C78 -> 8.6148019 | D27: =RANK(C27,$C$25:$C$40,0) -> 7 | E27: ='Belgium (Month)'!C93 -> 315 | F27: ='Belgium (Month)'!D78 -> 10.919803 | G27: =RANK(F27,$F$25:$F$40,0) -> 5 | H27: ='Belgium (Month)'!D93 -> 378 | I27: ='Belgium (Month)'!E78 -> 16.834355 | J27: =RANK(I27,$I$25:$I$40,0) -> 3 | K27: ='Belgium (Month)'!E93 -> 366
B28: BNP Paribas Fortis | C28: ='Belgium (Month)'!C42 -> 13.642026 | D28: =RANK(C28,$C$25:$C$40,0) -> 4 | E28: ='Belgium (Month)'!C57 -> 455 | F28: ='Belgium (Month)'!D42 -> 10.35423 | G28: =RANK(F28,$F$25:$F$40,0) -> 7 | H28: ='Belgium (Month)'!D57 -> 546 | I28: ='Belgium (Month)'!E42 -> 14.946107 | J28: =RANK(I28,$I$25:$I$40,0) -> 4 | K28: ='Belgium (Month)'!E57 -> 532
B29: KBC/CBC | C29: ='Belgium (Month)'!C60 -> 13.918667 | D29: =RANK(C29,$C$25:$C$40,0) -> 3 | E29: ='Belgium (Month)'!C75 -> 420 | F29: ='Belgium (Month)'!D60 -> 14.392067 | G29: =RANK(F29,$F$25:$F$40,0) -> 3 | H29: ='Belgium (Month)'!D75 -> 508 | I29: ='Belgium (Month)'!E60 -> 13.328339 | J29: =RANK(I29,$I$25:$I$40,0) -> 5 | K29: ='Belgium (Month)'!E75 -> 496
B30: Belfius | C30: ='Belgium (Month)'!C24 -> 14.414706 | D30: =RANK(C30,$C$25:$C$40,0) -> 2 | E30: ='Belgium (Month)'!C39 -> 451 | F30: ='Belgium (Month)'!D24 -> 12.472744 | G30: =RANK(F30,$F$25:$F$40,0) -> 4 | H30: ='Belgium (Month)'!D39 -> 544 | I30: ='Belgium (Month)'!E24 -> 12.901733 | J30: =RANK(I30,$I$25:$I$40,0) -> 6 | K30: ='Belgium (Month)'!E39 -> 530
B31: Crelan | C31: ='Belgium (Month)'!C114 -> 9.2041353 | D31: =RANK(C31,$C$25:$C$40,0) -> 6 | E31: ='Belgium (Month)'!C129 -> 150 | F31: ='Belgium (Month)'!D114 -> 9.5530681 | G31: =RANK(F31,$F$25:$F$40,0) -> 8 | H31: ='Belgium (Month)'!D129 -> 180 | I31: ='Belgium (Month)'!E114 -> 8.8219655 | J31: =RANK(I31,$I$25:$I$40,0) -> 7 | K31: ='Belgium (Month)'!E129 -> 192
B32: ING | C32: ='Belgium (Month)'!C6 -> 11.545893 | D32: =RANK(C32,$C$25:$C$40,0) -> 5 | E32: ='Belgium (Month)'!C21 -> 219 | F32: ='Belgium (Month)'!D6 -> 10.763037 | G32: =RANK(F32,$F$25:$F$40,0) -> 6 | H32: ='Belgium (Month)'!D21 -> 268 | I32: ='Belgium (Month)'!E6 -> 8.5654767 | J32: =RANK(I32,$I$25:$I$40,0) -> 8 | K32: ='Belgium (Month)'!E21 -> 275
B33: DEGIRO | C33: ='Belgium (Month)'!C258 -> 2.4549292 | D33: =RANK(C33,$C$25:$C$40,0) -> 8 | E33: ='Belgium (Month)'!C273 -> 153 | F33: ='Belgium (Month)'!D258 -> 6.4150402 | G33: =RANK(F33,$F$25:$F$40,0) -> 9 | H33: ='Belgium (Month)'!D273 -> 196 | I33: ='Belgium (Month)'!E258 -> 7.9080325 | J33: =RANK(I33,$I$25:$I$40,0) -> 9 | K33: ='Belgium (Month)'!E273 -> 206
B34: Bolero | C34: ='Belgium (Month)'!C222 -> 1.3757745 | D34: =RANK(C34,$C$25:$C$40,0) -> 9 | E34: ='Belgium (Month)'!C237 -> 308 | F34: ='Belgium (Month)'!D222 -> 0.98354694 | G34: =RANK(F34,$F$25:$F$40,0) -> 10 | H34: ='Belgium (Month)'!D237 -> 402 | I34: ='Belgium (Month)'!E222 -> 2.0424661 | J34: =RANK(I34,$I$25:$I$40,0) -> 10 | K34: ='Belgium (Month)'!E237 -> 419
B35: Trade republic | C35: ='Belgium (Month)'!C276 -> 0.67753147 | D35: =RANK(C35,$C$25:$C$40,0) -> 10 | E35: ='Belgium (Month)'!C291 -> 162 | F35: ='Belgium (Month)'!D276 -> -2.2451811 | G35: =RANK(F35,$F$25:$F$40,0) -> 12 | H35: ='Belgium (Month)'!D291 -> 221 | I35: ='Belgium (Month)'!E276 -> 0.54808895 | J35: =RANK(I35,$I$25:$I$40,0) -> 11 | K35: ='Belgium (Month)'!E291 -> 233
B36: eToro | C36: ='Belgium (Month)'!C240 -> 0.0091775789 | D36: =RANK(C36,$C$25:$C$40,0) -> 11 | E36: ='Belgium (Month)'!C255 -> 148 | F36: ='Belgium (Month)'!D240 -> -1.0766291 | G36: =RANK(F36,$F$25:$F$40,0) -> 11 | H36: ='Belgium (Month)'!D255 -> 191 | I36: ='Belgium (Month)'!E240 -> -0.54086286 | J36: =RANK(I36,$I$25:$I$40,0) -> 12 | K36: ='Belgium (Month)'!E255 -> 196
B37: Beobank | C37: ='Belgium (Month)'!C96 -> Low N | D37: Low N | E37: ='Belgium (Month)'!C111 -> 55 | F37: ='Belgium (Month)'!D96 -> Low N | G37: Low N | H37: ='Belgium (Month)'!D111 -> 64 | I37: ='Belgium (Month)'!E96 -> Low N | J37: Low N | K37: ='Belgium (Month)'!E111 -> 67
B38: Deutsche Bank | C38: ='Belgium (Month)'!C132 -> Low N | D38: Low N | E38: ='Belgium (Month)'!C147 -> 64 | F38: ='Belgium (Month)'!D132 -> Low N | G38: Low N | H38: ='Belgium (Month)'!D147 -> 72 | I38: ='Belgium (Month)'!E132 -> Low N | J38: Low N | K38: ='Belgium (Month)'!E147 -> 68
B39: Fintro | C39: ='Belgium (Month)'!C150 -> Low N | D39: Low N | E39: ='Belgium (Month)'!C165 -> 47 | F39: ='Belgium (Month)'!D150 -> Low N | G39: Low N | H39: ='Belgium (Month)'!D165 -> 57 | I39: ='Belgium (Month)'!E150 -> Low N | J39: Low N | K39: ='Belgium (Month)'!E165 -> 53
B40: Hello Bank | C40: ='Belgium (Month)'!C168 -> Low N | D40: Low N | E40: ='Belgium (Month)'!C183 -> 26 | F40: ='Belgium (Month)'!D168 -> Low N | G40: Low N | H40: ='Belgium (Month)'!D183 -> 33 | I40: ='Belgium (Month)'!E168 -> Low N | J40: Low N | K40: ='Belgium (Month)'!E183 -> 36
B42: Germany | C42: NPS | D42: Rank | E42: n | F42: NPS | G42: Rank | H42: n | I42: NPS | J42: Rank | K42: n
B43: Revolut | C43: ='Germany (Month)'!C222 -> Low N | D43: Low N | E43: ='Germany (Month)'!C237 -> 92 | F43: ='Germany (Month)'!D222 -> 56.272619 | G43: =RANK(F43,$F$43:$F$58,0) -> 1 | H43: ='Germany (Month)'!D237 -> 116 | I43: ='Germany (Month)'!E222 -> 50.896528 | J43: =RANK(I43,$I$43:$I$58,0) -> 1 | K43: ='Germany (Month)'!E237 -> 106
B44: Trade Republic | C44: ='Germany (Month)'!C240 -> 46.022213 | D44: =RANK(C44,$C$43:$C$58,0) -> 1 | E44: ='Germany (Month)'!C255 -> 287 | F44: ='Germany (Month)'!D240 -> 46.07108 | G44: =RANK(F44,$F$43:$F$58,0) -> 2 | H44: ='Germany (Month)'!D255 -> 337 | I44: ='Germany (Month)'!E240 -> 46.852005 | J44: =RANK(I44,$I$43:$I$58,0) -> 2 | K44: ='Germany (Month)'!E255 -> 343
B45: ING | C45: ='Germany (Month)'!C6 -> 37.351547 | D45: =RANK(C45,$C$43:$C$58,0) -> 2 | E45: ='Germany (Month)'!C21 -> 210 | F45: ='Germany (Month)'!D6 -> 40.748368 | G45: =RANK(F45,$F$43:$F$58,0) -> 3 | H45: ='Germany (Month)'!D21 -> 255 | I45: ='Germany (Month)'!E6 -> 38.60839 | J45: =RANK(I45,$I$43:$I$58,0) -> 3 | K45: ='Germany (Month)'!E21 -> 256
B46: Sparkasse | C46: ='Germany (Month)'!C78 -> 32.435297 | D46: =RANK(C46,$C$43:$C$58,0) -> 3 | E46: ='Germany (Month)'!C93 -> 383 | F46: ='Germany (Month)'!D78 -> 32.793778 | G46: =RANK(F46,$F$43:$F$58,0) -> 4 | H46: ='Germany (Month)'!D93 -> 452 | I46: ='Germany (Month)'!E78 -> 36.593052 | J46: =RANK(I46,$I$43:$I$58,0) -> 4 | K46: ='Germany (Month)'!E93 -> 436
B47: Comdirect | C47: ='Germany (Month)'!C114 -> Low N | D47: Low N | E47: ='Germany (Month)'!C129 -> 87 | F47: ='Germany (Month)'!D114 -> Low N | G47: Low N | H47: ='Germany (Month)'!D129 -> 97 | I47: ='Germany (Month)'!E114 -> 25.442275 | J47: =RANK(I47,$I$43:$I$58,0) -> 5 | K47: ='Germany (Month)'!E129 -> 108
B48: Commerzbank | C48: ='Germany (Month)'!C24 -> Low N | D48: Low N | E48: ='Germany (Month)'!C39 -> 91 | F48: ='Germany (Month)'!D24 -> 27.770398 | G48: =RANK(F48,$F$43:$F$58,0) -> 5 | H48: ='Germany (Month)'!D39 -> 106 | I48: ='Germany (Month)'!E24 -> 25.112411 | J48: =RANK(I48,$I$43:$I$58,0) -> 6 | K48: ='Germany (Month)'!E39 -> 109
B49: Deutsche Bank | C49: ='Germany (Month)'!C150 -> 25.011006 | D49: =RANK(C49,$C$43:$C$58,0) -> 4 | E49: ='Germany (Month)'!C165 -> 136 | F49: ='Germany (Month)'!D150 -> 23.589 | G49: =RANK(F49,$F$43:$F$58,0) -> 6 | H49: ='Germany (Month)'!D165 -> 157 | I49: ='Germany (Month)'!E150 -> 23.172458 | J49: =RANK(I49,$I$43:$I$58,0) -> 7 | K49: ='Germany (Month)'!E165 -> 149
B50: VR-Banken | C50: ='Germany (Month)'!C96 -> 22.486678 | D50: =RANK(C50,$C$43:$C$58,0) -> 5 | E50: ='Germany (Month)'!C111 -> 177 | F50: ='Germany (Month)'!D96 -> 23.118379 | G50: =RANK(F50,$F$43:$F$58,0) -> 7 | H50: ='Germany (Month)'!D111 -> 215 | I50: ='Germany (Month)'!E96 -> 22.281993 | J50: =RANK(I50,$I$43:$I$58,0) -> 8 | K50: ='Germany (Month)'!E111 -> 217
B51: DKB | C51: ='Germany (Month)'!C42 -> Low N | D51: Low N | E51: ='Germany (Month)'!C57 -> 47 | F51: ='Germany (Month)'!D42 -> Low N | G51: Low N | H51: ='Germany (Month)'!D57 -> 52 | I51: ='Germany (Month)'!E42 -> Low N | J51: Low N | K51: ='Germany (Month)'!E57 -> 60
B52: Postbank | C52: ='Germany (Month)'!C60 -> Low N | D52: Low N | E52: ='Germany (Month)'!C75 -> 61 | F52: ='Germany (Month)'!D60 -> Low N | G52: Low N | H52: ='Germany (Month)'!D75 -> 70 | I52: ='Germany (Month)'!E60 -> Low N | J52: Low N | K52: ='Germany (Month)'!E75 -> 59
B53: Consors Bank | C53: ='Germany (Month)'!C132 -> Low N | D53: Low N | E53: ='Germany (Month)'!C147 -> 77 | F53: ='Germany (Month)'!D132 -> Low N | G53: Low N | H53: ='Germany (Month)'!D147 -> 96 | I53: ='Germany (Month)'!E132 -> Low N | J53: Low N | K53: ='Germany (Month)'!E147 -> 94
B54: N26 | C54: ='Germany (Month)'!C168 -> Low N | D54: Low N | E54: ='Germany (Month)'!C183 -> 40 | F54: ='Germany (Month)'!D168 -> Low N | G54: Low N | H54: ='Germany (Month)'!D183 -> 44 | I54: ='Germany (Month)'!E168 -> Low N | J54: Low N | K54: ='Germany (Month)'!E183 -> 41
B55: Sparda | C55: ='Germany (Month)'!C186 -> Low N | D55: Low N | E55: ='Germany (Month)'!C201 -> 24 | F55: ='Germany (Month)'!D186 -> Low N | G55: Low N | H55: ='Germany (Month)'!D201 -> 33 | I55: ='Germany (Month)'!E186 -> Low N | J55: Low N | K55: ='Germany (Month)'!E201 -> 36
B56: Targobank | C56: ='Germany (Month)'!C204 -> Low N | D56: Low N | E56: ='Germany (Month)'!C219 -> 48 | F56: ='Germany (Month)'!D204 -> Low N | G56: Low N | H56: ='Germany (Month)'!D219 -> 58 | I56: ='Germany (Month)'!E204 -> Low N | J56: Low N | K56: ='Germany (Month)'!E219 -> 58
B57: C24 | C57: ='Germany (Month)'!C258 -> Low N | D57: Low N | E57: ='Germany (Month)'!C273 -> 13 | F57: ='Germany (Month)'!D258 -> Low N | G57: Low N | H57: ='Germany (Month)'!D273 -> 19 | I57: ='Germany (Month)'!E258 -> Low N | J57: Low N | K57: ='Germany (Month)'!E273 -> 22
B58: Scalable Capital | C58: Currently running a test to check representativity
B60: Italy | C60: NPS | D60: Rank | E60: n | F60: NPS | G60: Rank | H60: n | I60: NPS | J60: Rank | K60: n
B61: Fineco | C61: ='Italy (Month)'!C42 -> 66.036846 | D61: =RANK(C61,$C$61:$C$81,0) -> 1 | E61: ='Italy (Month)'!C57 -> 149 | F61: ='Italy (Month)'!D42 -> 63.103222 | G61: =RANK(F61,$F$61:$F$81,0) -> 1 | H61: ='Italy (Month)'!D57 -> 176 | I61: ='Italy (Month)'!E42 -> 63.19128 | J61: =RANK(I61,$I$61:$I$81,0) -> 1 | K61: ='Italy (Month)'!E57 -> 180
B62: Revolut | C62: ='Italy (Month)'!C204 -> 52.946871 | D62: =RANK(C62,$C$61:$C$81,0) -> 2 | E62: ='Italy (Month)'!C219 -> 128 | F62: ='Italy (Month)'!D204 -> 55.465109 | G62: =RANK(F62,$F$61:$F$81,0) -> 2 | H62: ='Italy (Month)'!D219 -> 152 | I62: ='Italy (Month)'!E204 -> 53.249662 | J62: =RANK(I62,$I$61:$I$81,0) -> 2 | K62: ='Italy (Month)'!E219 -> 146
B63: Banca Mediolanum | C63: ='Italy (Month)'!C24 -> 40.753957 | D63: =RANK(C63,$C$61:$C$81,0) -> 4 | E63: ='Italy (Month)'!C39 -> 123 | F63: ='Italy (Month)'!D24 -> 43.349631 | G63: =RANK(F63,$F$61:$F$81,0) -> 3 | H63: ='Italy (Month)'!D39 -> 146 | I63: ='Italy (Month)'!E24 -> 43.023035 | J63: =RANK(I63,$I$61:$I$81,0) -> 3 | K63: ='Italy (Month)'!E39 -> 127
B64: Unicredit | C64: ='Italy (Month)'!C78 -> 39.055306 | D64: =RANK(C64,$C$61:$C$81,0) -> 5 | E64: ='Italy (Month)'!C93 -> 176 | F64: ='Italy (Month)'!D78 -> 37.424715 | G64: =RANK(F64,$F$61:$F$81,0) -> 5 | H64: ='Italy (Month)'!D93 -> 200 | I64: ='Italy (Month)'!E78 -> 39.030946 | J64: =RANK(I64,$I$61:$I$81,0) -> 4 | K64: ='Italy (Month)'!E93 -> 184
B65: ING | C65: ='Italy (Month)'!C6 -> 41.703194 | D65: =RANK(C65,$C$61:$C$81,0) -> 3 | E65: ='Italy (Month)'!C21 -> 90 | F65: ='Italy (Month)'!D6 -> 38.719898 | G65: =RANK(F65,$F$61:$F$81,0) -> 4 | H65: ='Italy (Month)'!D21 -> 108 | I65: ='Italy (Month)'!E6 -> 38.887289 | J65: =RANK(I65,$I$61:$I$81,0) -> 5 | K65: ='Italy (Month)'!E21 -> 104
B66: BancoPosta | C66: ='Italy (Month)'!C96 -> 34.563509 | D66: =RANK(C66,$C$61:$C$81,0) -> 6 | E66: ='Italy (Month)'!C111 -> 274 | F66: ='Italy (Month)'!D96 -> 34.87419 | G66: =RANK(F66,$F$61:$F$81,0) -> 6 | H66: ='Italy (Month)'!D111 -> 311 | I66: ='Italy (Month)'!E96 -> 30.505965 | J66: =RANK(I66,$I$61:$I$81,0) -> 6 | K66: ='Italy (Month)'!E111 -> 293
B67: Intesa Sanpaolo | C67: ='Italy (Month)'!C60 -> 29.89663 | D67: =RANK(C67,$C$61:$C$81,0) -> 7 | E67: ='Italy (Month)'!C75 -> 342 | F67: ='Italy (Month)'!D60 -> 29.271521 | G67: =RANK(F67,$F$61:$F$81,0) -> 7 | H67: ='Italy (Month)'!D75 -> 405 | I67: ='Italy (Month)'!E60 -> 26.860344 | J67: =RANK(I67,$I$61:$I$81,0) -> 7 | K67: ='Italy (Month)'!E75 -> 379
B68: Bper | C68: ='Italy (Month)'!C330 -> 4.5772764 | D68: =RANK(C68,$C$61:$C$81,0) -> 8 | E68: ='Italy (Month)'!C345 -> 307 | F68: ='Italy (Month)'!D330 -> 3.4245481 | G68: =RANK(F68,$F$61:$F$81,0) -> 9 | H68: ='Italy (Month)'!D345 -> 384 | I68: ='Italy (Month)'!E330 -> 4.0870436 | J68: =RANK(I68,$I$61:$I$81,0) -> 8 | K68: ='Italy (Month)'!E345 -> 404
B69: Credit agricole | C69: ='Italy (Month)'!C312 -> 0.61913312 | D69: =RANK(C69,$C$61:$C$81,0) -> 9 | E69: ='Italy (Month)'!C327 -> 277 | F69: ='Italy (Month)'!D312 -> 4.0682767 | G69: =RANK(F69,$F$61:$F$81,0) -> 8 | H69: ='Italy (Month)'!D327 -> 356 | I69: ='Italy (Month)'!E312 -> 3.874715 | J69: =RANK(I69,$I$61:$I$81,0) -> 9 | K69: ='Italy (Month)'!E327 -> 363
B70: Credem | C70: ='Italy (Month)'!C366 -> -3.8019076 | D70: =RANK(C70,$C$61:$C$81,0) -> 11 | E70: ='Italy (Month)'!C381 -> 240 | F70: ='Italy (Month)'!D366 -> 1.0052465 | G70: =RANK(F70,$F$61:$F$81,0) -> 10 | H70: ='Italy (Month)'!D381 -> 311 | I70: ='Italy (Month)'!E366 -> 1.6507144 | J70: =RANK(I70,$I$61:$I$81,0) -> 10 | K70: ='Italy (Month)'!E381 -> 316
B71: Banco BPM | C71: ='Italy (Month)'!C348 -> -2.0696338 | D71: =RANK(C71,$C$61:$C$81,0) -> 10 | E71: ='Italy (Month)'!C363 -> 259 | F71: ='Italy (Month)'!D348 -> 0.71753329 | G71: =RANK(F71,$F$61:$F$81,0) -> 11 | H71: ='Italy (Month)'!D363 -> 342 | I71: ='Italy (Month)'!E348 -> 1.6238331 | J71: =RANK(I71,$I$61:$I$81,0) -> 11 | K71: ='Italy (Month)'!E363 -> 354
B72: BNL | C72: ='Italy (Month)'!C114 -> Low N | D72: Low N | E72: ='Italy (Month)'!C129 -> 59 | F72: ='Italy (Month)'!D114 -> Low N | G72: Low N | H72: ='Italy (Month)'!D129 -> 65 | I72: ='Italy (Month)'!E114 -> Low N | J72: Low N | K72: ='Italy (Month)'!E129 -> 66
B73: Deutsche Bank | C73: ='Italy (Month)'!C132 -> Low N | D73: Low N | E73: ='Italy (Month)'!C147 -> 28 | F73: ='Italy (Month)'!D132 -> Low N | G73: Low N | H73: ='Italy (Month)'!D147 -> 31 | I73: ='Italy (Month)'!E132 -> Low N | J73: Low N | K73: ='Italy (Month)'!E147 -> 34
B74: Monte dei Paschi di Siena | C74: ='Italy (Month)'!C168 -> Low N | D74: Low N | E74: ='Italy (Month)'!C183 -> 66 | F74: ='Italy (Month)'!D168 -> Low N | G74: Low N | H74: ='Italy (Month)'!D183 -> 76 | I74: ='Italy (Month)'!E168 -> Low N | J74: Low N | K74: ='Italy (Month)'!E183 -> 73
B75: N26 | C75: ='Italy (Month)'!C186 -> Low N | D75: Low N | E75: ='Italy (Month)'!C201 -> 14 | F75: ='Italy (Month)'!D186 -> Low N | G75: Low N | H75: ='Italy (Month)'!D201 -> 17 | I75: ='Italy (Month)'!E186 -> Low N | J75: Low N | K75: ='Italy (Month)'!E201 -> 16
B76: Webank | C76: ='Italy (Month)'!C222 -> Low N | D76: Low N | E76: ='Italy (Month)'!C237 -> 21 | F76: ='Italy (Month)'!D222 -> Low N | G76: Low N | H76: ='Italy (Month)'!D237 -> 24 | I76: ='Italy (Month)'!E222 -> Low N | J76: Low N | K76: ='Italy (Month)'!E237 -> 21
B77: Widiba | C77: ='Italy (Month)'!C240 -> Low N | D77: Low N | E77: ='Italy (Month)'!C255 -> 18 | F77: ='Italy (Month)'!D240 -> Low N | G77: Low N | H77: ='Italy (Month)'!D255 -> 21 | I77: ='Italy (Month)'!E240 -> Low N | J77: Low N | K77: ='Italy (Month)'!E255 -> 19
B78: BBVA | C78: ='Italy (Month)'!C258 -> Low N | D78: Low N | E78: ='Italy (Month)'!C273 -> 28 | F78: ='Italy (Month)'!D258 -> Low N | G78: Low N | H78: ='Italy (Month)'!D273 -> 32 | I78: ='Italy (Month)'!E258 -> Low N | J78: Low N | K78: ='Italy (Month)'!E273 -> 33
B79: Isybank | C79: ='Italy (Month)'!C276 -> Low N | D79: Low N | E79: ='Italy (Month)'!C291 -> 29 | F79: ='Italy (Month)'!D276 -> Low N | G79: Low N | H79: ='Italy (Month)'!D291 -> 31 | I79: ='Italy (Month)'!E276 -> Low N | J79: Low N | K79: ='Italy (Month)'!E291 -> 25
B80: Mediobanca Premier (previously CheBanca!) | C80: ='Italy (Month)'!C294 -> Low N | D80: Low N | E80: ='Italy (Month)'!C309 -> 25 | F80: ='Italy (Month)'!D294 -> Low N | G80: Low N | H80: ='Italy (Month)'!D309 -> 32 | I80: ='Italy (Month)'!E294 -> Low N | J80: Low N | K80: ='Italy (Month)'!E309 -> 29
B81: IWBank | C81: Low N | D81: Low N | E81: ='Italy (Month)'!C165 -> 15 | F81: Low N | G81: Low N | H81: ='Italy (Month)'!D165 -> 17
B83: The Netherlands | C83: NPS | D83: Rank | E83: n | F83: NPS | G83: Rank | H83: n | I83: NPS | J83: Rank | K83: n
B84: ING | C84: ='Netherlands (Month)'!C6 -> 22.590758 | D84: =RANK(C84,$C$84:$C$98,0) -> 1 | E84: ='Netherlands (Month)'!C21 -> 260 | F84: ='Netherlands (Month)'!D6 -> 20.112431 | G84: =RANK(F84,$F$84:$F$98,0) -> 1 | H84: ='Netherlands (Month)'!D21 -> 296 | I84: ='Netherlands (Month)'!E6 -> 21.139988 | J84: =RANK(I84,$I$84:$I$98,0) -> 1 | K84: ='Netherlands (Month)'!E21 -> 272
B85: DeGIRO | C85: ='Netherlands (Month)'!C114 -> 16.585219 | D85: =RANK(C85,$C$84:$C$98,0) -> 2 | E85: ='Netherlands (Month)'!C129 -> 180 | F85: ='Netherlands (Month)'!D114 -> 16.356023 | G85: =RANK(F85,$F$84:$F$98,0) -> 2 | H85: ='Netherlands (Month)'!D129 -> 225 | I85: ='Netherlands (Month)'!E114 -> 18.039264 | J85: =RANK(I85,$I$84:$I$98,0) -> 2 | K85: ='Netherlands (Month)'!E129 -> 232
B86: ABN AMRO | C86: ='Netherlands (Month)'!C24 -> 13.164507 | D86: =RANK(C86,$C$84:$C$98,0) -> 3 | E86: ='Netherlands (Month)'!C39 -> 168 | F86: ='Netherlands (Month)'!D24 -> 15.574583 | G86: =RANK(F86,$F$84:$F$98,0) -> 3 | H86: ='Netherlands (Month)'!D39 -> 203 | I86: ='Netherlands (Month)'!E24 -> 13.836482 | J86: =RANK(I86,$I$84:$I$98,0) -> 3 | K86: ='Netherlands (Month)'!E39 -> 199
B87: Rabobank | C87: ='Netherlands (Month)'!C42 -> 10.872639 | D87: =RANK(C87,$C$84:$C$98,0) -> 4 | E87: ='Netherlands (Month)'!C57 -> 193 | F87: ='Netherlands (Month)'!D42 -> 9.9592566 | G87: =RANK(F87,$F$84:$F$98,0) -> 4 | H87: ='Netherlands (Month)'!D57 -> 223 | I87: ='Netherlands (Month)'!E42 -> 9.2983737 | J87: =RANK(I87,$I$84:$I$98,0) -> 4 | K87: ='Netherlands (Month)'!E57 -> 213
B88: Brand new day | C88: ='Netherlands (Month)'!C258 -> 3.7877831 | D88: =RANK(C88,$C$84:$C$98,0) -> 5 | E88: ='Netherlands (Month)'!C273 -> 214 | F88: ='Netherlands (Month)'!D258 -> 4.5481466 | G88: =RANK(F88,$F$84:$F$98,0) -> 6 | H88: ='Netherlands (Month)'!D273 -> 277 | I88: ='Netherlands (Month)'!E258 -> 8.474188 | J88: =RANK(I88,$I$84:$I$98,0) -> 5 | K88: ='Netherlands (Month)'!E273 -> 300
B89: EVI Van Lanschot | C89: ='Netherlands (Month)'!C186 -> 3.2997747 | D89: =RANK(C89,$C$84:$C$98,0) -> 6 | E89: ='Netherlands (Month)'!C201 -> 126 | F89: ='Netherlands (Month)'!D186 -> 6.6966299 | G89: =RANK(F89,$F$84:$F$98,0) -> 5 | H89: ='Netherlands (Month)'!D201 -> 164 | I89: ='Netherlands (Month)'!E186 -> 6.8145848 | J89: =RANK(I89,$I$84:$I$98,0) -> 6 | K89: ='Netherlands (Month)'!E201 -> 165
B90: Peaks | C90: ='Netherlands (Month)'!C222 -> -4.3981694 | D90: =RANK(C90,$C$84:$C$98,0) -> 7 | E90: ='Netherlands (Month)'!C237 -> 150 | F90: ='Netherlands (Month)'!D222 -> -4.0241252 | G90: =RANK(F90,$F$84:$F$98,0) -> 7 | H90: ='Netherlands (Month)'!D237 -> 191 | I90: ='Netherlands (Month)'!E222 -> 0.36489483 | J90: =RANK(I90,$I$84:$I$98,0) -> 7 | K90: ='Netherlands (Month)'!E237 -> 202
B91: Bux | C91: ='Netherlands (Month)'!C240 -> -8.0968655 | D91: =RANK(C91,$C$84:$C$98,0) -> 8 | E91: ='Netherlands (Month)'!C255 -> 223 | F91: ='Netherlands (Month)'!D240 -> -5.1834719 | G91: =RANK(F91,$F$84:$F$98,0) -> 8 | H91: ='Netherlands (Month)'!D255 -> 296 | I91: ='Netherlands (Month)'!E240 -> -3.9079571 | J91: =RANK(I91,$I$84:$I$98,0) -> 8 | K91: ='Netherlands (Month)'!E255 -> 300
B92: ASN bank | C92: ='Netherlands (Month)'!C60 -> Low N | D92: Low N | E92: ='Netherlands (Month)'!C75 -> 50 | F92: ='Netherlands (Month)'!D60 -> Low N | G92: Low N | H92: ='Netherlands (Month)'!D75 -> 66 | I92: ='Netherlands (Month)'!E60 -> Low N | J92: Low N | K92: ='Netherlands (Month)'!E75 -> 69
B93: Bunq | C93: ='Netherlands (Month)'!C96 -> Low N | D93: Low N | E93: ='Netherlands (Month)'!C111 -> 19 | F93: ='Netherlands (Month)'!D96 -> Low N | G93: Low N | H93: ='Netherlands (Month)'!D111 -> 26 | I93: ='Netherlands (Month)'!E96 -> Low N | J93: Low N | K93: ='Netherlands (Month)'!E111 -> 26
B94: KNAB | C94: ='Netherlands (Month)'!C132 -> Low N | D94: Low N | E94: ='Netherlands (Month)'!C147 -> 20 | F94: ='Netherlands (Month)'!D132 -> Low N | G94: Low N | H94: ='Netherlands (Month)'!D147 -> 25 | I94: ='Netherlands (Month)'!E132 -> Low N | J94: Low N | K94: ='Netherlands (Month)'!E147 -> 24
B95: Triodos Bank | C95: ='Netherlands (Month)'!C168 -> Low N | D95: Low N | E95: ='Netherlands (Month)'!C183 -> 21 | F95: ='Netherlands (Month)'!D168 -> Low N | G95: Low N | H95: ='Netherlands (Month)'!D183 -> 23 | I95: ='Netherlands (Month)'!E168 -> Low N | J95: Low N | K95: ='Netherlands (Month)'!E183 -> 25
B96: Revolut | C96: ='Netherlands (Month)'!C204 -> Low N | D96: Low N | E96: ='Netherlands (Month)'!C219 -> 76 | F96: ='Netherlands (Month)'!D204 -> Low N | G96: Low N | H96: ='Netherlands (Month)'!D219 -> 88 | I96: ='Netherlands (Month)'!E204 -> Low N | J96: Low N | K96: ='Netherlands (Month)'!E219 -> 96
B97: SNS bank | C97: ='Netherlands (Month)'!C78 -> Low N | D97: Low N | E97: ='Netherlands (Month)'!C93 -> 9 | F97: ='Netherlands (Month)'!D78 -> Low N | G97: Low N | H97: ='Netherlands (Month)'!D93 -> 9
B98: Regiobank | C98: ='Netherlands (Month)'!C150 -> Low N | D98: Low N | E98: ='Netherlands (Month)'!C165 -> 4 | F98: ='Netherlands (Month)'!D150 -> Low N | G98: Low N | H98: ='Netherlands (Month)'!D165 -> 4
B100: Poland | C100: NPS | D100: Rank | E100: n | F100: NPS | G100: Rank | H100: n | I100: NPS | J100: Rank | K100: n
B101: Revolut | C101: ='Poland (Month)'!C258 -> 59.226943 | D101: =RANK(C101,$C$101:$C$116,0) -> 1 | E101: ='Poland (Month)'!C273 -> 132 | F101: ='Poland (Month)'!D258 -> 56.509003 | G101: =RANK(F101,$F$101:$F$116,0) -> 1 | H101: ='Poland (Month)'!D273 -> 158 | I101: ='Poland (Month)'!E258 -> 51.510057 | J101: =RANK(I101,$I$101:$I$116,0) -> 1 | K101: ='Poland (Month)'!E273 -> 151
B102: mBank | C102: ='Poland (Month)'!C42 -> 31.873025 | D102: =RANK(C102,$C$101:$C$116,0) -> 3 | E102: ='Poland (Month)'!C57 -> 154 | F102: ='Poland (Month)'!D42 -> 36.279673 | G102: =RANK(F102,$F$101:$F$116,0) -> 2 | H102: ='Poland (Month)'!D57 -> 184 | I102: ='Poland (Month)'!E42 -> 34.732035 | J102: =RANK(I102,$I$101:$I$116,0) -> 2 | K102: ='Poland (Month)'!E57 -> 185
B103: Pekao S.A. | C103: ='Poland (Month)'!C60 -> Low N | D103: Low N | E103: ='Poland (Month)'!C75 -> 92 | F103: ='Poland (Month)'!D60 -> 27.6768 | G103: =RANK(F103,$F$101:$F$116,0) -> 5 | H103: ='Poland (Month)'!D75 -> 114 | I103: ='Poland (Month)'!E60 -> 34.717385 | J103: =RANK(I103,$I$101:$I$116,0) -> 3 | K103: ='Poland (Month)'!E75 -> 116
B104: ING | C104: ='Poland (Month)'!C6 -> 37.738385 | D104: =RANK(C104,$C$101:$C$116,0) -> 2 | E104: ='Poland (Month)'!C21 -> 133 | F104: ='Poland (Month)'!D6 -> 35.603056 | G104: =RANK(F104,$F$101:$F$116,0) -> 3 | H104: ='Poland (Month)'!D21 -> 160 | I104: ='Poland (Month)'!E6 -> 33.415363 | J104: =RANK(I104,$I$101:$I$116,0) -> 4 | K104: ='Poland (Month)'!E21 -> 163
B105: PKO BP (Powszechna Kasa Oszczędności BP) | C105: ='Poland (Month)'!C78 -> 31.170856 | D105: =RANK(C105,$C$101:$C$116,0) -> 4 | E105: ='Poland (Month)'!C93 -> 214 | F105: ='Poland (Month)'!D78 -> 33.037206 | G105: =RANK(F105,$F$101:$F$116,0) -> 4 | H105: ='Poland (Month)'!D93 -> 259 | I105: ='Poland (Month)'!E78 -> 30.393973 | J105: =RANK(I105,$I$101:$I$116,0) -> 5 | K105: ='Poland (Month)'!E93 -> 274
B106: Velo bank (previously Getin Bank) | C106: ='Poland (Month)'!C24 -> Low N | D106: Low N | E106: ='Poland (Month)'!C39 -> 15 | F106: ='Poland (Month)'!D24 -> Low N | G106: Low N | H106: ='Poland (Month)'!D39 -> 18 | I106: ='Poland (Month)'!E24 -> Low N | J106: Low N | K106: ='Poland (Month)'!E39 -> 20
B107: Santander | C107: ='Poland (Month)'!C96 -> Low N | D107: Low N | E107: ='Poland (Month)'!C111 -> 57 | F107: ='Poland (Month)'!D96 -> Low N | G107: Low N | H107: ='Poland (Month)'!D111 -> 75 | I107: ='Poland (Month)'!E96 -> Low N | J107: Low N | K107: ='Poland (Month)'!E111 -> 88
...

Sheet Australia (quarter)
B2: Source: Global NPS tracking / Toluna | C2: Q4 - 2025
B4: Rolling NPS Data - Total
B5: ING
B6: NPS - ING (%) | C6: ='Australia (Month)'!#REF! -> #REF!
B7: Rank - ING | C7: =C49 -> #REF!
B8: Promoter - ING (%) | C8: ='Australia (Month)'!#REF! -> #REF!
B9: Passive - ING (%) | C9: ='Australia (Month)'!#REF! -> #REF!
B10: Detractor - ING (%) | C10: ='Australia (Month)'!#REF! -> #REF!
B12: Key competitors
B13: ANZ
B14: NPS - ANZ (%) | C14: ='Australia (Month)'!#REF! -> #REF!
B15: Rank - ANZ | C15: =C50 -> #REF!
B16: Promoter - ANZ (%) | C16: ='Australia (Month)'!#REF! -> #REF!
B17: Passive - ANZ (%) | C17: ='Australia (Month)'!#REF! -> #REF!
B18: Detractor - ANZ (%) | C18: ='Australia (Month)'!#REF! -> #REF!
B20: Commonwealth Bank
B21: NPS - Commonwealth Bank (%) | C21: ='Australia (Month)'!#REF! -> #REF!
B22: Rank - Commonwealth Bank | C22: =C51 -> #REF!
B23: Promoter - Commonwealth Bank (%) | C23: ='Australia (Month)'!#REF! -> #REF!
B24: Passive - Commonwealth Bank (%) | C24: ='Australia (Month)'!#REF! -> #REF!
B25: Detractor - Commonwealth Bank (%) | C25: ='Australia (Month)'!#REF! -> #REF!
B27: NAB - National Australia Bank
B28: NPS - NAB (%) | C28: ='Australia (Month)'!#REF! -> #REF!
B29: Rank - NAB | C29: =C52 -> #REF!
B30: Promoter - NAB (%) | C30: ='Australia (Month)'!#REF! -> #REF!
B31: Passive - NAB (%) | C31: ='Australia (Month)'!#REF! -> #REF!
B32: Detractor - NAB (%) | C32: ='Australia (Month)'!#REF! -> #REF!
B34: Westpac
B35: NPS - Westpac (%) | C35: ='Australia (Month)'!#REF! -> #REF!
B36: Rank - Westpac | C36: =C53 -> #REF!
B37: Promoter - Westpac (%) | C37: ='Australia (Month)'!#REF! -> #REF!
B38: Passive - Westpac (%) | C38: ='Australia (Month)'!#REF! -> #REF!
B39: Detractor - Westpac (%) | C39: ='Australia (Month)'!#REF! -> #REF!
B41: NPS - ING & Key competitors (For ranking)
B42: ING | C42: =C6 -> #REF!
B43: ANZ | C43: =C14 -> #REF!
B44: Commonwealth Bank | C44: =C21 -> #REF!
B45: NAB (National Australia Bank) | C45: =C28 -> #REF!
B46: Westpac | C46: =C35 -> #REF!
B48: Ranking formule
B49: ING | C49: =RANK(C42,C$42:C$46,0) -> #REF!
B50: ANZ | C50: =RANK(C43,C$42:C$46,0) -> #REF!
B51: Commonwealth Bank | C51: =RANK(C44,C$42:C$46,0) -> #REF!
B52: NAB (National Australia Bank) | C52: =RANK(C45,C$42:C$46,0) -> #REF!
B53: Westpac | C53: =RANK(C46,C$42:C$46,0) -> #REF!
B55: Base Size - NPS
B56: ING | C56: ='Australia (Month)'!#REF! -> #REF!
B57: ANZ | C57: ='Australia (Month)'!#REF! -> #REF!
B58: Commonwealth Bank | C58: ='Australia (Month)'!#REF! -> #REF!
B59: NAB (National Australia Bank) | C59: ='Australia (Month)'!#REF! -> #REF!
B60: Westpac | C60: ='Australia (Month)'!#REF! -> #REF!

Sheet Australia (Month)
B2: Source: Global NPS tracking / Toluna | C2: January - 2026 (6 months rolling) | D2: February - 2026 (6 months rolling) | E2: March - 2026 (6 months rolling)
B4: NPS total
B5: ING | C5: NPS | D5: NPS | E5: NPS
C6: ='Australia Crunch Output'!G21 -> 17.404865 | D6: ='Australia Crunch Output'!H21 -> 20.861557 | E6: ='Australia Crunch Output'!I21 -> 13.983207
B7: Promoter | C7: ='Australia Crunch Output'!G7 -> 0.39838158 | D7: ='Australia Crunch Output'!H7 -> 0.39646689 | E7: ='Australia Crunch Output'!I7 -> 0.35230341
B8: Passive | C8: ='Australia Crunch Output'!G8 -> 0.37728548 | D8: ='Australia Crunch Output'!H8 -> 0.41568179 | E8: ='Australia Crunch Output'!I8 -> 0.43522525
B9: Detractor | C9: ='Australia Crunch Output'!G9 -> 0.22433293 | D9: ='Australia Crunch Output'!H9 -> 0.18785132 | E9: ='Australia Crunch Output'!I9 -> 0.21247134
B10: Extremely likely | C10: ='Australia Crunch Output'!G10 -> 0.25217444 | D10: ='Australia Crunch Output'!H10 -> 0.26119081 | E10: ='Australia Crunch Output'!I10 -> 0.21694215
B11: 9 | C11: ='Australia Crunch Output'!G11 -> 0.14620714 | D11: ='Australia Crunch Output'!H11 -> 0.13527608 | E11: ='Australia Crunch Output'!I11 -> 0.13536126
B12: 8 | C12: ='Australia Crunch Output'!G12 -> 0.26618879 | D12: ='Australia Crunch Output'!H12 -> 0.28948345 | E12: ='Australia Crunch Output'!I12 -> 0.29309967
B13: 7 | C13: ='Australia Crunch Output'!G13 -> 0.1110967 | D13: ='Australia Crunch Output'!H13 -> 0.12619834 | E13: ='Australia Crunch Output'!I13 -> 0.14212558
B14: 6 | C14: ='Australia Crunch Output'!G14 -> 0.17702314 | D14: ='Australia Crunch Output'!H14 -> 0.15027529 | E14: ='Australia Crunch Output'!I14 -> 0.17180229
B15: 5 | C15: ='Australia Crunch Output'!G15 -> 0.023547444 | D15: ='Australia Crunch Output'!H15 -> 0.01870267 | E15: ='Australia Crunch Output'!I15 -> 0.020242155
B16: 4 | C16: ='Australia Crunch Output'!G16 -> 0.023762355 | D16: ='Australia Crunch Output'!H16 -> 0.018873364 | E16: ='Australia Crunch Output'!I16 -> 0.0204269
B17: 3 | C17: ='Australia Crunch Output'!G17 -> 0 | D17: ='Australia Crunch Output'!H17 -> 0 | E17: ='Australia Crunch Output'!I17 -> 0
B18: 2 | C18: ='Australia Crunch Output'!G18 -> 0 | D18: ='Australia Crunch Output'!H18 -> 0 | E18: ='Australia Crunch Output'!I18 -> 0
B19: 1 | C19: ='Australia Crunch Output'!G19 -> 0 | D19: ='Australia Crunch Output'!H19 -> 0 | E19: ='Australia Crunch Output'!I19 -> 0
B20: Extremely Unlikely | C20: ='Australia Crunch Output'!G20 -> 0 | D20: ='Australia Crunch Output'!H20 -> 0 | E20: ='Australia Crunch Output'!I20 -> 0
B21: n | C21: ='Australia Crunch Output'!G6 -> 42 | D21: ='Australia Crunch Output'!H6 -> 53 | E21: ='Australia Crunch Output'!I6 -> 48
B23: ANZ | C23: NPS | D23: NPS | E23: NPS
C24: ='Australia Crunch Output'!G40 -> 44.621825 | D24: ='Australia Crunch Output'!H40 -> 42.488528 | E24: ='Australia Crunch Output'!I40 -> 38.373295
B25: Promoter | C25: ='Australia Crunch Output'!G26 -> 0.52486817 | D25: ='Australia Crunch Output'!H26 -> 0.52061667 | E25: ='Australia Crunch Output'!I26 -> 0.50065198
B26: Passive | C26: ='Australia Crunch Output'!G27 -> 0.3964819 | D26: ='Australia Crunch Output'!H27 -> 0.38365194 | E26: ='Australia Crunch Output'!I27 -> 0.38242899
B27: Detractor | C27: ='Australia Crunch Output'!G28 -> 0.078649925 | D27: ='Australia Crunch Output'!H28 -> 0.095731393 | E27: ='Australia Crunch Output'!I28 -> 0.11691903
B28: Extremely likely | C28: ='Australia Crunch Output'!G29 -> 0.2618003 | D28: ='Australia Crunch Output'!H29 -> 0.26383604 | E28: ='Australia Crunch Output'!I29 -> 0.25196124
B29: 9 | C29: ='Australia Crunch Output'!G30 -> 0.26306787 | D29: ='Australia Crunch Output'!H30 -> 0.25678063 | E29: ='Australia Crunch Output'!I30 -> 0.24869074
B30: 8 | C30: ='Australia Crunch Output'!G31 -> 0.27788914 | D30: ='Australia Crunch Output'!H31 -> 0.28287399 | E30: ='Australia Crunch Output'!I31 -> 0.27779568
B31: 7 | C31: ='Australia Crunch Output'!G32 -> 0.11859276 | D31: ='Australia Crunch Output'!H32 -> 0.10077795 | E31: ='Australia Crunch Output'!I32 -> 0.10463331
B32: 6 | C32: ='Australia Crunch Output'!G33 -> 0.041566955 | D32: ='Australia Crunch Output'!H33 -> 0.033017907 | E32: ='Australia Crunch Output'!I33 -> 0.043605856
B33: 5 | C33: ='Australia Crunch Output'!G34 -> 0.037082971 | D33: ='Australia Crunch Output'!H34 -> 0.056081123 | E33: ='Australia Crunch Output'!I34 -> 0.054296797
B34: 4 | C34: ='Australia Crunch Output'!G35 -> 0 | D34: ='Australia Crunch Output'!H35 -> 0 | E34: ='Australia Crunch Output'!I35 -> 0.0056585511
B35: 3 | C35: ='Australia Crunch Output'!G36 -> 0 | D35: ='Australia Crunch Output'!H36 -> 0 | E35: ='Australia Crunch Output'!I36 -> 0
B36: 2 | C36: ='Australia Crunch Output'!G37 -> 0 | D36: ='Australia Crunch Output'!H37 -> 0.0066323623 | E36: ='Australia Crunch Output'!I37 -> 0.0068913057
B37: 1 | C37: ='Australia Crunch Output'!G38 -> 0 | D37: ='Australia Crunch Output'!H38 -> 0 | E37: ='Australia Crunch Output'!I38 -> 0.0064665179
B38: Extremely Unlikely | C38: ='Australia Crunch Output'!G39 -> 0 | D38: ='Australia Crunch Output'!H39 -> 0 | E38: ='Australia Crunch Output'!I39 -> 0
B39: n | C39: ='Australia Crunch Output'!G25 -> 124 | D39: ='Australia Crunch Output'!H25 -> 157 | E39: ='Australia Crunch Output'!I25 -> 149
B41: Commonwealth Bank | C41: NPS | D41: NPS | E41: NPS
C42: ='Australia Crunch Output'!G59 -> 43.719344 | D42: ='Australia Crunch Output'!H59 -> 42.72414 | E42: ='Australia Crunch Output'!I59 -> 43.929886
B43: Promoter | C43: ='Australia Crunch Output'!G45 -> 0.5501922 | D43: ='Australia Crunch Output'!H45 -> 0.54792716 | E43: ='Australia Crunch Output'!I45 -> 0.55717797
B44: Passive | C44: ='Australia Crunch Output'!G46 -> 0.33680904 | D44: ='Australia Crunch Output'!H46 -> 0.33138707 | E44: ='Australia Crunch Output'!I46 -> 0.32494292
B45: Detractor | C45: ='Australia Crunch Output'!G47 -> 0.11299876 | D45: ='Australia Crunch Output'!H47 -> 0.12068576 | E45: ='Australia Crunch Output'!I47 -> 0.11787911
B46: Extremely likely | C46: ='Australia Crunch Output'!G48 -> 0.314311 | D46: ='Australia Crunch Output'!H48 -> 0.30747943 | E46: ='Australia Crunch Output'!I48 -> 0.31299308
B47: 9 | C47: ='Australia Crunch Output'!G49 -> 0.23588121 | D47: ='Australia Crunch Output'!H49 -> 0.24044774 | E47: ='Australia Crunch Output'!I49 -> 0.24418489
B48: 8 | C48: ='Australia Crunch Output'!G50 -> 0.24603948 | D48: ='Australia Crunch Output'!H50 -> 0.23794385 | E48: ='Australia Crunch Output'!I50 -> 0.23413662
B49: 7 | C49: ='Australia Crunch Output'!G51 -> 0.09076955 | D49: ='Australia Crunch Output'!H51 -> 0.093443224 | E49: ='Australia Crunch Output'!I51 -> 0.090806307
B50: 6 | C50: ='Australia Crunch Output'!G52 -> 0.053182737 | D50: ='Australia Crunch Output'!H52 -> 0.059227138 | E50: ='Australia Crunch Output'!I52 -> 0.056393855
B51: 5 | C51: ='Australia Crunch Output'!G53 -> 0.031595726 | D51: ='Australia Crunch Output'!H53 -> 0.028391748 | E51: ='Australia Crunch Output'!I53 -> 0.025148865
B52: 4 | C52: ='Australia Crunch Output'!G54 -> 0 | D52: ='Australia Crunch Output'!H54 -> 0.0050450563 | E52: ='Australia Crunch Output'!I54 -> 0.0051110603
B53: 3 | C53: ='Australia Crunch Output'!G55 -> 0.0088276817 | D53: ='Australia Crunch Output'!H55 -> 0.0072261484 | E53: ='Australia Crunch Output'!I55 -> 0.010895749
B54: 2 | C54: ='Australia Crunch Output'!G56 -> 0.0028574571 | D54: ='Australia Crunch Output'!H56 -> 0.0048539811 | E54: ='Australia Crunch Output'!I56 -> 0.01077052
B55: 1 | C55: ='Australia Crunch Output'!G57 -> 0.0017240514 | D55: ='Australia Crunch Output'!H57 -> 0.001411271 | E55: ='Australia Crunch Output'!I57 -> 0
B56: Extremely Unlikely | C56: ='Australia Crunch Output'!G58 -> 0.014811109 | D56: ='Australia Crunch Output'!H58 -> 0.014530421 | E56: ='Australia Crunch Output'!I58 -> 0.0095590605
B57: n | C57: ='Australia Crunch Output'!G44 -> 331 | D57: ='Australia Crunch Output'!H44 -> 401 | E57: ='Australia Crunch Output'!I44 -> 391
B59: NAB | C59: NPS | D59: NPS | E59: NPS
C60: ='Australia Crunch Output'!G78 -> 31.411084 | D60: ='Australia Crunch Output'!H78 -> 29.606533 | E60: ='Australia Crunch Output'!I78 -> 29.562953
B61: Promoter | C61: ='Australia Crunch Output'!G64 -> 0.43373682 | D61: ='Australia Crunch Output'!H64 -> 0.41842987 | E61: ='Australia Crunch Output'!I64 -> 0.43771645
B62: Passive | C62: ='Australia Crunch Output'!G65 -> 0.4466372 | D62: ='Australia Crunch Output'!H65 -> 0.45920558 | E62: ='Australia Crunch Output'!I65 -> 0.42019663
B63: Detractor | C63: ='Australia Crunch Output'!G66 -> 0.11962598 | D63: ='Australia Crunch Output'!H66 -> 0.12236455 | E63: ='Australia Crunch Output'!I66 -> 0.14208692
B64: Extremely likely | C64: ='Australia Crunch Output'!G67 -> 0.15801526 | D64: ='Australia Crunch Output'!H67 -> 0.15402963 | E64: ='Australia Crunch Output'!I67 -> 0.1648378
B65: 9 | C65: ='Australia Crunch Output'!G68 -> 0.27572156 | D65: ='Australia Crunch Output'!H68 -> 0.26440025 | E65: ='Australia Crunch Output'!I68 -> 0.27287865
B66: 8 | C66: ='Australia Crunch Output'!G69 -> 0.34520906 | D66: ='Australia Crunch Output'!H69 -> 0.33132869 | E66: ='Australia Crunch Output'!I69 -> 0.2725657
B67: 7 | C67: ='Australia Crunch Output'!G70 -> 0.10142813 | D67: ='Australia Crunch Output'!H70 -> 0.12787689 | E67: ='Australia Crunch Output'!I70 -> 0.14763093
B68: 6 | C68: ='Australia Crunch Output'!G71 -> 0.060030452 | D68: ='Australia Crunch Output'!H71 -> 0.071045055 | E68: ='Australia Crunch Output'!I71 -> 0.08910359
B69: 5 | C69: ='Australia Crunch Output'!G72 -> 0.047426508 | D69: ='Australia Crunch Output'!H72 -> 0.040840383 | E69: ='Australia Crunch Output'!I72 -> 0.042164475
B70: 4 | C70: ='Australia Crunch Output'!G73 -> 0.011612259 | D70: ='Australia Crunch Output'!H73 -> 0.0099996634 | E70: ='Australia Crunch Output'!I73 -> 0.010323864
B71: 3 | C71: ='Australia Crunch Output'!G74 -> 0 | D71: ='Australia Crunch Output'!H74 -> 0 | E71: ='Australia Crunch Output'!I74 -> 0
B72: 2 | C72: ='Australia Crunch Output'!G75 -> 0 | D72: ='Australia Crunch Output'!H75 -> 0 | E72: ='Australia Crunch Output'!I75 -> 0
B73: 1 | C73: ='Australia Crunch Output'!G76 -> 0 | D73: ='Australia Crunch Output'!H76 -> 0 | E73: ='Australia Crunch Output'!I76 -> 0
B74: Extremely Unlikely | C74: ='Australia Crunch Output'!G77 -> 0.00055676477 | D74: ='Australia Crunch Output'!H77 -> 0.00047944678 | E74: ='Australia Crunch Output'!I77 -> 0.00049499099
B75: n | C75: ='Australia Crunch Output'!G63 -> 104 | D75: ='Australia Crunch Output'!H63 -> 120 | E75: ='Australia Crunch Output'!I63 -> 117
B77: Westpac | C77: NPS | D77: NPS | E77: NPS
C78: ='Australia Crunch Output'!G97 -> 50.112199 | D78: ='Australia Crunch Output'!H97 -> 44.665324 | E78: ='Australia Crunch Output'!I97 -> 37.664561
B79: Promoter | C79: ='Australia Crunch Output'!G83 -> 0.5790449 | D79: ='Australia Crunch Output'!H83 -> 0.55601699 | E79: ='Australia Crunch Output'!I83 -> 0.52802704
B80: Passive | C80: ='Australia Crunch Output'!G84 -> 0.34303219 | D80: ='Australia Crunch Output'!H84 -> 0.33461926 | E80: ='Australia Crunch Output'!I84 -> 0.32059153
B81: Detractor | C81: ='Australia Crunch Output'!G85 -> 0.077922911 | D81: ='Australia Crunch Output'!H85 -> 0.10936375 | E81: ='Australia Crunch Output'!I85 -> 0.15138143
B82: Extremely likely | C82: ='Australia Crunch Output'!G86 -> 0.33157079 | D82: ='Australia Crunch Output'!H86 -> 0.3257811 | E82: ='Australia Crunch Output'!I86 -> 0.31703835
B83: 9 | C83: ='Australia Crunch Output'!G87 -> 0.24747411 | D83: ='Australia Crunch Output'!H87 -> 0.23023589 | E83: ='Australia Crunch Output'!I87 -> 0.21098869
B84: 8 | C84: ='Australia Crunch Output'!G88 -> 0.17376253 | D84: ='Australia Crunch Output'!H88 -> 0.16763445 | E84: ='Australia Crunch Output'!I88 -> 0.15589968
B85: 7 | C85: ='Australia Crunch Output'!G89 -> 0.16926967 | D85: ='Australia Crunch Output'!H89 -> 0.16698481 | E85: ='Australia Crunch Output'!I89 -> 0.16469184
B86: 6 | C86: ='Australia Crunch Output'!G90 -> 0.037756929 | D86: ='Australia Crunch Output'!H90 -> 0.04467341 | E86: ='Australia Crunch Output'!I90 -> 0.077402933
B87: 5 | C87: ='Australia Crunch Output'!G91 -> 0.040165981 | D87: ='Australia Crunch Output'!H91 -> 0.059483748 | E87: ='Australia Crunch Output'!I91 -> 0.061693572
B88: 4 | C88: ='Australia Crunch Output'!G92 -> 0 | D88: ='Australia Crunch Output'!H92 -> 0 | E88: ='Australia Crunch Output'!I92 -> 0
B89: 3 | C89: ='Australia Crunch Output'!G93 -> 0 | D89: ='Australia Crunch Output'!H93 -> 0 | E89: ='Australia Crunch Output'!I93 -> 0
B90: 2 | C90: ='Australia Crunch Output'!G94 -> 0 | D90: ='Australia Crunch Output'!H94 -> 0.0052065909 | E90: ='Australia Crunch Output'!I94 -> 0.012284927
B91: 1 | C91: ='Australia Crunch Output'!G95 -> 0 | D91: ='Australia Crunch Output'!H95 -> 0 | E91: ='Australia Crunch Output'!I95 -> 0
B92: Extremely Unlikely | C92: ='Australia Crunch Output'!G96 -> 0 | D92: ='Australia Crunch Output'!H96 -> 0 | E92: ='Australia Crunch Output'!I96 -> 0
B93: n | C93: ='Australia Crunch Output'!G82 -> 113 | D93: ='Australia Crunch Output'!H82 -> 141 | E93: ='Australia Crunch Output'!I82 -> 137
B95: Bank of Australia | C95: NPS | D95: NPS | E95: NPS
C96: Low N | D96: Low N | E96: Low N
B97: Promoter | C97: Low N | D97: Low N | E97: Low N
B98: Passive | C98: Low N | D98: Low N | E98: Low N
B99: Detractor | C99: Low N | D99: Low N | E99: Low N
B100: Extremely likely | C100: Low N | D100: Low N | E100: Low N
B101: 9 | C101: Low N | D101: Low N | E101: Low N
B102: 8 | C102: Low N | D102: Low N | E102: Low N
B103: 7 | C103: Low N | D103: Low N | E103: Low N
B104: 6 | C104: Low N | D104: Low N | E104: Low N
B105: 5 | C105: Low N | D105: Low N | E105: Low N
B106: 4 | C106: Low N | D106: Low N | E106: Low N
B107: 3 | C107: Low N | D107: Low N | E107: Low N
...

Sheet Australia Crunch  Output
A1: P97511: ING BAM: Australia
A2: Investment NPS
A3: Based on your knowledge and experience with the investment services offered by the brand(s) below, how likely is it that you would recommend their investment services to a friend, family member or colleague?
A5: Investment NPS: ING | B5: All | C5: Apr 2025 - Sep 2025 | D5: May 2025 - Oct 2025 | E5: June 2025 - Nov 2025 | F5: July 2025 - Dec 2025 | G5: August 2025 - Jan 2026 | H5: Sep 2025 - Feb 2026 | I5: Oct 2025 - Mar 2026
A6: Unweighted N | B6: 34 | C6: 12 | D6: 16 | E6: 26 | F6: 34 | G6: 42 | H6: 53 | I6: 48
A7: Promoter | B7: 0.43309219 | C7: 0.60029294 | D7: 0.5751047 | E7: 0.49578486 | F7: 0.43309219 | G7: 0.39838158 | H7: 0.39646689 | I7: 0.35230341
A8: Passive | B8: 0.34740457 | C8: 0.3133977 | D8: 0.2352106 | E8: 0.34543323 | F8: 0.34740457 | G8: 0.37728548 | H8: 0.41568179 | I8: 0.43522525
A9: Detractor | B9: 0.21950324 | C9: 0.086309354 | D9: 0.1896847 | E9: 0.1587819 | F9: 0.21950324 | G9: 0.22433293 | H9: 0.18785132 | I9: 0.21247134
A10: Extremely Likely | B10: 0.28166927 | C10: 0.47703713 | D10: 0.42845271 | E10: 0.28946752 | F10: 0.28166927 | G10: 0.25217444 | H10: 0.26119081 | I10: 0.21694215
A11: 9 | B11: 0.15142292 | C11: 0.12325582 | D11: 0.14665199 | E11: 0.20631734 | F11: 0.15142292 | G11: 0.14620714 | H11: 0.13527608 | I11: 0.13536126
A12: 8 | B12: 0.20872222 | C12: 0.17568308 | D12: 0.1318533 | E12: 0.20062037 | F12: 0.20872222 | G12: 0.26618879 | H12: 0.28948345 | I12: 0.29309967
A13: 7 | B13: 0.13868235 | C13: 0.13771462 | D13: 0.10335729 | E13: 0.14481286 | F13: 0.13868235 | G13: 0.1110967 | H13: 0.12619834 | I13: 0.14212558
A14: 6 | B14: 0.19010889 | C14: 0.086309354 | D14: 0.1896847 | E14: 0.1587819 | F14: 0.19010889 | G14: 0.17702314 | H14: 0.15027529 | I14: 0.17180229
A15: 5 | B15: 0.029394347 | C15: 0 | D15: 0 | E15: 0 | F15: 0.029394347 | G15: 0.023547444 | H15: 0.01870267 | I15: 0.020242155
A16: 4 | B16: 0 | C16: 0 | D16: 0 | E16: 0 | F16: 0 | G16: 0.023762355 | H16: 0.018873364 | I16: 0.0204269
A17: 3 | B17: 0 | C17: 0 | D17: 0 | E17: 0 | F17: 0 | G17: 0 | H17: 0 | I17: 0
... A20: Extremely Unlikely | B20: 0 | C20: 0 | D20: 0 | E20: 0 | F20: 0 | G20: 0 | H20: 0 | I20: 0
A21: Mean | B21: =(B7-B9)*100 -> 21.358895 | C21: =(C7-C9)*100 -> 51.398359 | D21: =(D7-D9)*100 -> 38.542 | E21: =(E7-E9)*100 -> 33.700296 | F21: =(F7-F9)*100 -> 21.358895 | G21: 17.404865 | H21: 20.861557 | I21: 13.983207
A24: Investment NPS: ANZ | B24: All | C24: Apr 2025 - Sep 2025 | D24: May 2025 - Oct 2025 | E24: June 2025 - Nov 2025 | F24: July 2025 - Dec 2025 | G24: August 2025 - Jan 2026 | H24: Sep 2025 - Feb 2026 | I24: Oct 2025 - Mar 2026
A25: Unweighted N | B25: 102 | C25: 27 | D25: 48 | E25: 76 | F25: 102 | G25: 124 | H25: 157 | I25: 149
A26: Promoter | B26: 0.51344409 | C26: 0.63005152 | D26: 0.59530687 | E26: 0.5431767 | F26: 0.51344409 | G26: 0.52486817 | H26: 0.52061667 | I26: 0.50065198
A27: Passive | B27: 0.4028706 | C27: 0.28389129 | D27: 0.28942979 | E27: 0.36181018 | F27: 0.4028706 | G27: 0.3964819 | H27: 0.38365194 | I27: 0.38242899
A28: Detractor | B28: 0.083685316 | C28: 0.086057184 | D28: 0.11526334 | E28: 0.095013117 | F28: 0.083685316 | G28: 0.078649925 | H28: 0.095731393 | I28: 0.11691903
A29: Extremely Likely | B29: 0.24659197 | C29: 0.33565522 | D29: 0.26720384 | E29: 0.25172552 | F29: 0.24659197 | G29: 0.2618003 | H29: 0.26383604 | I29: 0.25196124
A30: 9 | B30: 0.26685211 | C30: 0.29439631 | D30: 0.32810302 | E30: 0.29145119 | F30: 0.26685211 | G30: 0.26306787 | H30: 0.25678063 | I30: 0.24869074
A31: 8 | B31: 0.28684926 | C31: 0.24618135 | D31: 0.18336672 | E31: 0.22335578 | F31: 0.28684926 | G31: 0.27788914 | H31: 0.28287399 | I31: 0.27779568
A32: 7 | B32: 0.11602134 | C32: 0.037709941 | D32: 0.10606307 | E32: 0.1384544 | F32: 0.11602134 | G32: 0.11859276 | H32: 0.10077795 | I32: 0.10463331
A33: 6 | B33: 0.050271048 | C33: 0 | D33: 0.041565435 | E33: 0.04881453 | F33: 0.050271048 | G33: 0.041566955 | H33: 0.033017907 | I33: 0.043605856
A34: 5 | B34: 0.033414268 | C34: 0.086057184 | D34: 0.073697908 | E34: 0.046198587 | F34: 0.033414268 | G34: 0.037082971 | H34: 0.056081123 | I34: 0.054296797
A35: 4 | B35: 0 | C35: 0 | D35: 0 | E35: 0 | F35: 0 | G35: 0 | H35: 0 | I35: 0.0056585511
A36: 3 | B36: 0 | C36: 0 | D36: 0 | E36: 0 | F36: 0 | G36: 0 | H36: 0 | I36: 0
... A39: Extremely Unlikely | B39: 0 | C39: 0 | D39: 0 | E39: 0 | F39: 0 | G39: 0 | H39: 0 | I39: 0
A40: Mean | B40: =(B26-B28)*100 -> 42.975877 | C40: =(C26-C28)*100 -> 54.399434 | D40: =(D26-D28)*100 -> 48.004353 | E40: =(E26-E28)*100 -> 44.816359 | F40: =(F26-F28)*100 -> 42.975877 | G40: 44.621825 | H40: 42.488528 | I40: 38.373295
A43: Investment NPS: Commonwealth Bank | B43: All | C43: Apr 2025 - Sep 2025 | D43: May 2025 - Oct 2025 | E43: June 2025 - Nov 2025 | F43: July 2025 - Dec 2025 | G43: August 2025 - Jan 2026 | H43: Sep 2025 - Feb 2026 | I43: Oct 2025 - Mar 2026
A44: Unweighted N | B44: 268 | C44: 66 | D44: 135 | E44: 199 | F44: 268 | G44: 331 | H44: 401 | I44: 391
A45: Promoter | B45: 0.53682547 | C45: 0.50680944 | D45: 0.54133151 | E45: 0.55748607 | F45: 0.53682547 | G45: 0.5501922 | H45: 0.54792716 | I45: 0.55717797
A46: Passive | B46: 0.33359332 | C46: 0.33747057 | D46: 0.35295168 | E46: 0.32056232 | F46: 0.33359332 | G46: 0.33680904 | H46: 0.33138707 | I46: 0.32494292
A47: Detractor | B47: 0.12958121 | C47: 0.15571999 | D47: 0.10571682 | E47: 0.12195161 | F47: 0.12958121 | G47: 0.11299876 | H47: 0.12068576 | I47: 0.11787911
A48: Extremely Likely | B48: 0.29650351 | C48: 0.31053977 | D48: 0.31320032 | E48: 0.30909499 | F48: 0.29650351 | G48: 0.314311 | H48: 0.30747943 | I48: 0.31299308
A49: 9 | B49: 0.24032196 | C49: 0.19626967 | D49: 0.22813118 | E49: 0.24839107 | F49: 0.24032196 | G49: 0.23588121 | H49: 0.24044774 | I49: 0.24418489
A50: 8 | B50: 0.24635942 | C50: 0.25164715 | D50: 0.27553002 | E50: 0.24116305 | F50: 0.24635942 | G50: 0.24603948 | H50: 0.23794385 | I50: 0.23413662
A51: 7 | B51: 0.087233895 | C51: 0.085823425 | D51: 0.077421659 | E51: 0.079399276 | F51: 0.087233895 | G51: 0.09076955 | H51: 0.093443224 | I51: 0.090806307
A52: 6 | B52: 0.062067517 | C52: 0.065415741 | D52: 0.031824057 | E52: 0.051588668 | F52: 0.062067517 | G52: 0.053182737 | H52: 0.059227138 | I52: 0.056393855
A53: 5 | B53: 0.034658081 | C53: 0.049026643 | D53: 0.045847435 | E53: 0.040666687 | F53: 0.034658081 | G53: 0.031595726 | H53: 0.028391748 | I53: 0.025148865
A54: 4 | B54: 0 | C54: 0 | D54: 0 | E54: 0 | F54: 0 | G54: 0 | H54: 0.0050450563 | I54: 0.0051110603
A55: 3 | B55: 0.0088547767 | C55: 0 | D55: 0 | E55: 0.0046942288 | F55: 0.0088547767 | G55: 0.0088276817 | H55: 0.0072261484 | I55: 0.010895749
... A58: Extremely Unlikely | B58: 0.018330638 | C58: 0.032323839 | D58: 0.023743763 | E58: 0.022101134 | F58: 0.018330638 | G58: 0.014811109 | H58: 0.014530421 | I58: 0.0095590605
A59: Mean | B59: =(B45-B47)*100 -> 40.724426 | C59: =(C45-C47)*100 -> 35.108945 | D59: =(D45-D47)*100 -> 43.561469 | E59: =(E45-E47)*100 -> 43.553446 | F59: =(F45-F47)*100 -> 40.724426 | G59: 43.719344 | H59: 42.72414 | I59: 43.929886
A62: Investment NPS: NAB | B62: All | C62: Apr 2025 - Sep 2025 | D62: May 2025 - Oct 2025 | E62: June 2025 - Nov 2025 | F62: July 2025 - Dec 2025 | G62: August 2025 - Jan 2026 | H62: Sep 2025 - Feb 2026 | I62: Oct 2025 - Mar 2026
A63: Unweighted N | B63: 87 | C63: 24 | D63: 47 | E63: 68 | F63: 87 | G63: 104 | H63: 120 | I63: 117
A64: Promoter | B64: 0.42661054 | C64: 0.53364226 | D64: 0.43238447 | E64: 0.39957102 | F64: 0.42661054 | G64: 0.43373682 | H64: 0.41842987 | I64: 0.43771645
A65: Passive | B65: 0.4558729 | C65: 0.44233977 | D65: 0.46302547 | E65: 0.47493782 | F65: 0.4558729 | G65: 0.4466372 | H65: 0.45920558 | I65: 0.42019663
A66: Detractor | B66: 0.11751656 | C66: 0.024017975 | D66: 0.10459005 | E66: 0.12549116 | F66: 0.11751656 | G66: 0.11962598 | H66: 0.12236455 | I66: 0.14208692
A67: Extremely Likely | B67: 0.1480891 | C67: 0.22173739 | D67: 0.1913851 | E67: 0.15196382 | F67: 0.1480891 | G67: 0.15801526 | H67: 0.15402963 | I67: 0.1648378
A68: 9 | B68: 0.27852144 | C68: 0.31190487 | D68: 0.24099937 | E68: 0.2476072 | F68: 0.27852144 | G68: 0.27572156 | H68: 0.26440025 | I68: 0.27287865
A69: 8 | B69: 0.34698535 | C69: 0.40175225 | D69: 0.33686506 | E69: 0.36895891 | F69: 0.34698535 | G69: 0.34520906 | H69: 0.33132869 | I69: 0.2725657
A70: 7 | B70: 0.10888755 | C70: 0.040587515 | D70: 0.12616041 | E70: 0.10597891 | F70: 0.10888755 | G70: 0.10142813 | H70: 0.12787689 | I70: 0.14763093
A71: 6 | B71: 0.05800294 | C71: 0.024017975 | D71: 0.080583765 | E71: 0.074774446 | F71: 0.05800294 | G71: 0.060030452 | H71: 0.071045055 | I71: 0.08910359
A72: 5 | B72: 0.044942647 | C72: 0 | D72: 0.024006289 | E72: 0.032791987 | F72: 0.044942647 | G72: 0.047426508 | H72: 0.040840383 | I72: 0.042164475
A73: 4 | B73: 0.013904309 | C73: 0 | D73: 0 | E73: 0.01792473 | F73: 0.013904309 | G73: 0.011612259 | H73: 0.0099996634 | I73: 0.010323864
A74: 3 | B74: 0 | C74: 0 | D74: 0 | E74: 0 | F74: 0 | G74: 0 | H74: 0 | I74: 0
... A77: Extremely Unlikely | B77: 0.00066666008 | C77: 0 | D77: 0 | E77: 0 | F77: 0.00066666008 | G77: 0.00055676477 | H77: 0.00047944678 | I77: 0.00049499099
A78: Mean | B78: =(B64-B66)*100 -> 30.909399 | C78: =(C64-C66)*100 -> 50.962428 | D78: =(D64-D66)*100 -> 32.779442 | E78: =(E64-E66)*100 -> 27.407986 | F78: =(F64-F66)*100 -> 30.909399 | G78: 31.411084 | H78: 29.606533 | I78: 29.562953
A81: Investment NPS: Westpac | B81: All | C81: Apr 2025 - Sep 2025 | D81: May 2025 - Oct 2025 | E81: June 2025 - Nov 2025 | F81: July 2025 - Dec 2025 | G81: August 2025 - Jan 2026 | H81: Sep 2025 - Feb 2026 | I81: Oct 2025 - Mar 2026
A82: Unweighted N | B82: 89 | C82: 25 | D82: 48 | E82: 70 | F82: 89 | G82: 113 | H82: 141 | I82: 137
A83: Promoter | B83: 0.5598095 | C83: 0.61657251 | D83: 0.55262819 | E83: 0.50807645 | F83: 0.5598095 | G83: 0.5790449 | H83: 0.55601699 | I83: 0.52802704
A84: Passive | B84: 0.34337323 | C84: 0.38342749 | D84: 0.40255139 | E84: 0.3920206 | F84: 0.34337323 | G84: 0.34303219 | H84: 0.33461926 | I84: 0.32059153
A85: Detractor | B85: 0.096817269 | C85: 0 | D85: 0.044820422 | E85: 0.099902954 | F85: 0.096817269 | G85: 0.077922911 | H85: 0.10936375 | I85: 0.15138143
A86: Extremely Likely | B86: 0.34142431 | C86: 0.4027804 | D86: 0.33932332 | E86: 0.29970643 | F86: 0.34142431 | G86: 0.33157079 | H86: 0.3257811 | I86: 0.31703835
A87: 9 | B87: 0.21838519 | C87: 0.21379211 | D87: 0.21330487 | E87: 0.20837002 | F87: 0.21838519 | G87: 0.24747411 | H87: 0.23023589 | I87: 0.21098869
A88: 8 | B88: 0.19260302 | C88: 0.20044237 | D88: 0.20383828 | E88: 0.21408898 | F88: 0.19260302 | G88: 0.17376253 | H88: 0.16763445 | I88: 0.15589968
A89: 7 | B89: 0.15077021 | C89: 0.18298512 | D89: 0.19871312 | E89: 0.17793161 | F89: 0.15077021 | G89: 0.16926967 | H89: 0.16698481 | I89: 0.16469184
A90: 6 | B90: 0.046912041 | C90: 0 | D90: 0.022410211 | E90: 0.059645292 | F90: 0.046912041 | G90: 0.037756929 | H90: 0.04467341 | I90: 0.077402933
A91: 5 | B91: 0.049905228 | C91: 0 | D91: 0.022410211 | E91: 0.040257663 | F91: 0.049905228 | G91: 0.040165981 | H91: 0.059483748 | I91: 0.061693572
A92: 4 | B92: 0 | C92: 0 | D92: 0 | E92: 0 | F92: 0 | G92: 0 | H92: 0 | I92: 0
A93: 3 | B93: 0 | C93: 0 | D93: 0 | E93: 0 | F93: 0 | G93: 0 | H93: 0 | I93: 0
... A96: Extremely Unlikely | B96: 0 | C96: 0 | D96: 0 | E96: 0 | F96: 0 | G96: 0 | H96: 0 | I96: 0
A97: Mean | B97: =(B83-B85)*100 -> 46.299223 | C97: =(C83-C85)*100 -> 61.657251 | D97: =(D83-D85)*100 -> 50.780776 | E97: =(E83-E85)*100 -> 40.81735 | F97: =(F83-F85)*100 -> 46.299223 | G97: 50.112199 | H97: 44.665324 | I97: 37.664561
A100: Investment NPS: Invisible 1 | B100: All | C100: Apr 2025 - Sep 2025 | D100: May 2025 - Oct 2025 | E100: June 2025 - Nov 2025 | F100: July 2025 - Dec 2025 | G100: August 2025 - Jan 2026 | H100: Sep 2025 - Feb 2026 | I100: Oct 2025 - Mar 2026
A101: Unweighted N | B101: 0 | C101: 0 | D101: 0 | E101: 0 | F101: 0 | G101: 0 | H101: 0 | I101: 0
A102: Promoter | B102: - | C102: - | D102: - | E102: - | F102: - | G102: - | H102: - | I102: -
A103: Passive | B103: - | C103: - | D103: - | E103: - | F103: - | G103: - | H103: - | I103: -
A104: Detractor | B104: - | C104: - | D104: - | E104: - | F104: - | G104: - | H104: - | I104: -
A105: Extremely Likely | B105: - | C105: - | D105: - | E105: - | F105: - | G105: - | H105: - | I105: -
A106: 9 | B106: - | C106: - | D106: - | E106: - | F106: - | G106: - | H106: - | I106: -
A107: 8 | B107: - | C107: - | D107: - | E107: - | F107: - | G107: - | H107: - | I107: -
A108: 7 | B108: - | C108: - | D108: - | E108: - | F108: - | G108: - | H108: - | I108: -
A109: 6 | B109: - | C109: - | D109: - | E109: - | F109: - | G109: - | H109: - | I109: -
A110: 5 | B110: - | C110: - | D110: - | E110: - | F110: - | G110: - | H110: - | I110: -
A111: 4 | B111: - | C111: - | D111: - | E111: - | F111: - | G111: - | H111: - | I111: -
A112: 3 | B112: - | C112: - | D112: - | E112: - | F112: - | G112: - | H112: - | I112: -
A113: 2 | B113: - | C113: - | D113: - | E113: - | F113: - | G113: - | H113: - | I113: -
... A118: Investment NPS: BoQ | B118: All | C118: Apr 2025 - Sep 2025 | D118: May 2025 - Oct 2025 | E118: June 2025 - Nov 2025 | F118: July 2025 - Dec 2025 | G118: August 2025 - Jan 2026 | H118: Sep 2025 - Feb 2026 | I118: Oct 2025 - Mar 2026
A119: Unweighted N | B119: 12 | C119: 6 | D119: 9 | E119: 11 | F119: 12 | G119: 13 | H119: 14 | I119: 13
A120: Promoter | B120: 0.5462161 | C120: 0.43136448 | D120: 0.62215748 | E120: 0.59672576 | F120: 0.5462161 | G120: 0.5790419 | H120: 0.54375992 | I120: 0.61715772
A121: Passive | B121: 0.36913922 | C121: 0.56863552 | D121: 0.37784252 | E121: 0.40327424 | F121: 0.36913922 | G121: 0.34243644 | H121: 0.38250288 | I121: 0.23514579
A122: Detractor | B122: 0.084644683 | C122: 0 | D122: 0 | E122: 0 | F122: 0.084644683 | G122: 0.078521659 | H122: 0.073737205 | I122: 0.14769648
A123: Extremely Likely | B123: 0.16084518 | C123: 0.15773359 | D123: 0.10480959 | E123: 0.17571884 | F123: 0.16084518 | G123: 0.14920996 | H123: 0.14011835 | I123: 0.20274263
A124: 9 | B124: 0.38537092 | C124: 0.27363089 | D124: 0.51734789 | E124: 0.42100692 | F124: 0.38537092 | G124: 0.42983194 | H124: 0.40364157 | I124: 0.4144151
A125: 8 | B125: 0.1894698 | C125: 0.20564017 | D125: 0.13664218 | E125: 0.20699044 | F125: 0.1894698 | G125: 0.17576394 | H125: 0.22598601 | I125: 0.23514579
...

Sheet Belgium (quarter)
B2: Source: Global NPS tracking / Toluna | C2: Q4 - 2025
B4: Rolling NPS Data - Total
B5: ING
B6: NPS - ING (%) | C6: ='Belgium (Month)'!#REF! -> #REF!
B7: Rank - ING | C7: =C41 -> #REF!
B8: Promoter - ING (%) | C8: ='Belgium (Month)'!#REF! -> #REF!
B9: Passive - ING (%) | C9: ='Belgium (Month)'!#REF! -> #REF!
B10: Detractor - ING (%) | C10: ='Belgium (Month)'!#REF! -> #REF!
B12: Key competitors
B13: Belfius
B14: NPS - Belfius (%) | C14: ='Belgium (Month)'!#REF! -> #REF!
B15: Rank - Belfius | C15: =C42 -> #REF!
B16: Promoter - Belfius (%) | C16: ='Belgium (Month)'!#REF! -> #REF!
B17: Passive - Belfius (%) | C17: ='Belgium (Month)'!#REF! -> #REF!
B18: Detractor - Belfius (%) | C18: ='Belgium (Month)'!#REF! -> #REF!
B20: BNP Paribas Fortis
B21: NPS - BNP Paribas Fortis (%) | C21: ='Belgium (Month)'!#REF! -> #REF!
B22: Rank - BNP Paribas Fortis | C22: =C43 -> #REF!
B23: Promoter - BNP Paribas Fortis (%) | C23: ='Belgium (Month)'!#REF! -> #REF!
B24: Passive - BNP Paribas Fortis (%) | C24: ='Belgium (Month)'!#REF! -> #REF!
B25: Detractor - BNP Paribas Fortis (%) | C25: ='Belgium (Month)'!#REF! -> #REF!
B27: KBC/CBC
B28: NPS - KBC/CBC (%) | C28: ='Belgium (Month)'!#REF! -> #REF!
B29: Rank - KBC/CBC | C29: =C44 -> #REF!
B30: Promoter - KBC/CBC (%) | C30: ='Belgium (Month)'!#REF! -> #REF!
B31: Passive - KBC/CBC (%) | C31: ='Belgium (Month)'!#REF! -> #REF!
B32: Detractor - KBC/CBC (%) | C32: ='Belgium (Month)'!#REF! -> #REF!
B34: NPS - ING & Key competitors (For ranking)
B35: ING | C35: =C6 -> #REF!
B36: Belfius | C36: =C14 -> #REF!
B37: BNP Paribas Fortis | C37: =C21 -> #REF!
B38: KBC/CBC | C38: =C28 -> #REF!
B40: Ranking formule
B41: ING | C41: =RANK(C35,C$35:C$38,0) -> #REF!
B42: Belfius | C42: =RANK(C36,C$35:C$38,0) -> #REF!
B43: BNP Paribas Fortis | C43: =RANK(C37,C$35:C$38,0) -> #REF!
B44: KBC/CBC | C44: =RANK(C38,C$35:C$38,0) -> #REF!
B46: Base Size - NPS
B47: ING | C47: ='Belgium (Month)'!#REF! -> #REF!
B48: Belfius | C48: ='Belgium (Month)'!#REF! -> #REF!
B49: BNP Paribas Fortis | C49: ='Belgium (Month)'!#REF! -> #REF!
B50: KBC/CBC | C50: ='Belgium (Month)'!#REF! -> #REF!

Sheet Belgium (Month)
B2: Source: Global NPS tracking / Toluna | C2: January - 2026 (6 months rolling) | D2: February - 2026 (6 months rolling) | E2: March - 2026 (6 months rolling)
B4: NPS total
B5: ING | C5: NPS | D5: NPS | E5: NPS
C6: ='Belgium Crunch Output'!G21 -> 11.545893 | D6: ='Belgium Crunch Output'!H21 -> 10.763037 | E6: ='Belgium Crunch Output'!I21 -> 8.5654767
B7: Promoter | C7: ='Belgium Crunch Output'!G7 -> 0.31415111 | D7: ='Belgium Crunch Output'!H7 -> 0.31045631 | E7: ='Belgium Crunch Output'!I7 -> 0.29914663
B8: Passive | C8: ='Belgium Crunch Output'!G8 -> 0.4871567 | D8: ='Belgium Crunch Output'!H8 -> 0.48671774 | E8: ='Belgium Crunch Output'!I8 -> 0.48736151
B9: Detractor | C9: ='Belgium Crunch Output'!G9 -> 0.19869219 | D9: ='Belgium Crunch Output'!H9 -> 0.20282594 | E9: ='Belgium Crunch Output'!I9 -> 0.21349186
B10: Extremely likely | C10: ='Belgium Crunch Output'!G10 -> 0.14144933 | D10: ='Belgium Crunch Output'!H10 -> 0.14502576 | E10: ='Belgium Crunch Output'!I10 -> 0.13958879
B11: 9 | C11: ='Belgium Crunch Output'!G11 -> 0.17270178 | D11: ='Belgium Crunch Output'!H11 -> 0.16543056 | E11: ='Belgium Crunch Output'!I11 -> 0.15955784
B12: 8 | C12: ='Belgium Crunch Output'!G12 -> 0.26505588 | D12: ='Belgium Crunch Output'!H12 -> 0.28799723 | E12: ='Belgium Crunch Output'!I12 -> 0.29772607
B13: 7 | C13: ='Belgium Crunch Output'!G13 -> 0.22210082 | D13: ='Belgium Crunch Output'!H13 -> 0.19872051 | E13: ='Belgium Crunch Output'!I13 -> 0.18963544
B14: 6 | C14: ='Belgium Crunch Output'!G14 -> 0.079837675 | D14: ='Belgium Crunch Output'!H14 -> 0.079468581 | E14: ='Belgium Crunch Output'!I14 -> 0.088541413
B15: 5 | C15: ='Belgium Crunch Output'!G15 -> 0.060253928 | D15: ='Belgium Crunch Output'!H15 -> 0.064047883 | E15: ='Belgium Crunch Output'!I15 -> 0.070197316
B16: 4 | C16: ='Belgium Crunch Output'!G16 -> 0.0093464287 | D16: ='Belgium Crunch Output'!H16 -> 0.011521884 | E16: ='Belgium Crunch Output'!I16 -> 0.0081749518
B17: 3 | C17: ='Belgium Crunch Output'!G17 -> 0.017404717 | D17: ='Belgium Crunch Output'!H17 -> 0.014243653 | E17: ='Belgium Crunch Output'!I17 -> 0.013844497
B18: 2 | C18: ='Belgium Crunch Output'!G18 -> 0.0039800205 | D18: ='Belgium Crunch Output'!H18 -> 0.0069977466 | E18: ='Belgium Crunch Output'!I18 -> 0.010389363
B19: 1 | C19: ='Belgium Crunch Output'!G19 -> 0.015620898 | D19: ='Belgium Crunch Output'!H19 -> 0.012783814 | E19: ='Belgium Crunch Output'!I19 -> 0.012425567
B20: Extremely Unlikely | C20: ='Belgium Crunch Output'!G20 -> 0.012248519 | D20: ='Belgium Crunch Output'!H20 -> 0.013762381 | E20: ='Belgium Crunch Output'!I20 -> 0.0099187547
B21: n | C21: ='Belgium Crunch Output'!G6 -> 219 | D21: ='Belgium Crunch Output'!H6 -> 268 | E21: ='Belgium Crunch Output'!I6 -> 275
B23: Belfius | C23: NPS | D23: NPS | E23: NPS
C24: ='Belgium Crunch Output'!G40 -> 14.414706 | D24: ='Belgium Crunch Output'!H40 -> 12.472744 | E24: ='Belgium Crunch Output'!I40 -> 12.901733
B25: Promoter | C25: ='Belgium Crunch Output'!G26 -> 0.31699818 | D25: ='Belgium Crunch Output'!H26 -> 0.32070746 | E25: ='Belgium Crunch Output'!I26 -> 0.330788
B26: Passive | C26: ='Belgium Crunch Output'!G27 -> 0.51015071 | D26: ='Belgium Crunch Output'!H27 -> 0.48331252 | E26: ='Belgium Crunch Output'!I27 -> 0.46744133
B27: Detractor | C27: ='Belgium Crunch Output'!G28 -> 0.17285111 | D27: ='Belgium Crunch Output'!H28 -> 0.19598002 | E27: ='Belgium Crunch Output'!I28 -> 0.20177067
B28: Extremely likely | C28: ='Belgium Crunch Output'!G29 -> 0.13346918 | D28: ='Belgium Crunch Output'!H29 -> 0.14031488 | E28: ='Belgium Crunch Output'!I29 -> 0.14339854
B29: 9 | C29: ='Belgium Crunch Output'!G30 -> 0.18352899 | D29: ='Belgium Crunch Output'!H30 -> 0.18039258 | E29: ='Belgium Crunch Output'!I30 -> 0.18738947
B30: 8 | C30: ='Belgium Crunch Output'!G31 -> 0.32402977 | D30: ='Belgium Crunch Output'!H31 -> 0.30842649 | E30: ='Belgium Crunch Output'!I31 -> 0.30866656
B31: 7 | C31: ='Belgium Crunch Output'!G32 -> 0.18612094 | D31: ='Belgium Crunch Output'!H32 -> 0.17488604 | E31: ='Belgium Crunch Output'!I32 -> 0.15877477
B32: 6 | C32: ='Belgium Crunch Output'!G33 -> 0.066691949 | D32: ='Belgium Crunch Output'!H33 -> 0.06986287 | E32: ='Belgium Crunch Output'!I33 -> 0.067553118
B33: 5 | C33: ='Belgium Crunch Output'!G34 -> 0.050741542 | D33: ='Belgium Crunch Output'!H34 -> 0.056580513 | E33: ='Belgium Crunch Output'!I34 -> 0.06491622
B34: 4 | C34: ='Belgium Crunch Output'!G35 -> 0.016608146 | D34: ='Belgium Crunch Output'!H35 -> 0.01719166 | E34: ='Belgium Crunch Output'!I35 -> 0.017508387
B35: 3 | C35: ='Belgium Crunch Output'!G36 -> 0.011581171 | D35: ='Belgium Crunch Output'!H36 -> 0.011453669 | E35: ='Belgium Crunch Output'!I36 -> 0.011477302
B36: 2 | C36: ='Belgium Crunch Output'!G37 -> 0.014175944 | D36: ='Belgium Crunch Output'!H37 -> 0.014973967 | E36: ='Belgium Crunch Output'!I37 -> 0.015316663
B37: 1 | C37: ='Belgium Crunch Output'!G38 -> 0 | D37: ='Belgium Crunch Output'!H38 -> 0.0053344526 | E37: ='Belgium Crunch Output'!I38 -> 0.0054565377
B38: Extremely Unlikely | C38: ='Belgium Crunch Output'!G39 -> 0.01305236 | D38: ='Belgium Crunch Output'!H39 -> 0.020582887 | E38: ='Belgium Crunch Output'!I39 -> 0.01954244
B39: n | C39: ='Belgium Crunch Output'!G25 -> 451 | D39: ='Belgium Crunch Output'!H25 -> 544 | E39: ='Belgium Crunch Output'!I25 -> 530
B41: BNP Paribas Fortis | C41: NPS | D41: NPS | E41: NPS
C42: ='Belgium Crunch Output'!G59 -> 13.642026 | D42: ='Belgium Crunch Output'!H59 -> 10.35423 | E42: ='Belgium Crunch Output'!I59 -> 14.946107
B43: Promoter | C43: ='Belgium Crunch Output'!G45 -> 0.35039206 | D43: ='Belgium Crunch Output'!H45 -> 0.3312292 | E43: ='Belgium Crunch Output'!I45 -> 0.3672793
B44: Passive | C44: ='Belgium Crunch Output'!G46 -> 0.43563614 | D44: ='Belgium Crunch Output'!H46 -> 0.4410839 | E44: ='Belgium Crunch Output'!I46 -> 0.41490247
B45: Detractor | C45: ='Belgium Crunch Output'!G47 -> 0.2139718 | D45: ='Belgium Crunch Output'!H47 -> 0.2276869 | E45: ='Belgium Crunch Output'!I47 -> 0.21781823
B46: Extremely likely | C46: ='Belgium Crunch Output'!G48 -> 0.1678391 | D46: ='Belgium Crunch Output'!H48 -> 0.14660326 | E46: ='Belgium Crunch Output'!I48 -> 0.16017442
B47: 9 | C47: ='Belgium Crunch Output'!G49 -> 0.18255296 | D47: ='Belgium Crunch Output'!H49 -> 0.18462594 | E47: ='Belgium Crunch Output'!I49 -> 0.20710488
B48: 8 | C48: ='Belgium Crunch Output'!G50 -> 0.2831717 | D48: ='Belgium Crunch Output'!H50 -> 0.27931575 | E48: ='Belgium Crunch Output'!I50 -> 0.2544326
B49: 7 | C49: ='Belgium Crunch Output'!G51 -> 0.15246444 | D49: ='Belgium Crunch Output'!H51 -> 0.16176815 | E49: ='Belgium Crunch Output'!I51 -> 0.16046986
B50: 6 | C50: ='Belgium Crunch Output'!G52 -> 0.08909001 | D50: ='Belgium Crunch Output'!H52 -> 0.086978251 | E50: ='Belgium Crunch Output'!I52 -> 0.077183604
B51: 5 | C51: ='Belgium Crunch Output'!G53 -> 0.07024479 | D51: ='Belgium Crunch Output'!H53 -> 0.083607259 | E51: ='Belgium Crunch Output'!I53 -> 0.085837691
B52: 4 | C52: ='Belgium Crunch Output'!G54 -> 0.020224689 | D52: ='Belgium Crunch Output'!H54 -> 0.016802335 | E52: ='Belgium Crunch Output'!I54 -> 0.017553942
B53: 3 | C53: ='Belgium Crunch Output'!G55 -> 0.0095495478 | D53: ='Belgium Crunch Output'!H55 -> 0.011957452 | E53: ='Belgium Crunch Output'!I55 -> 0.010691629
B54: 2 | C54: ='Belgium Crunch Output'!G56 -> 0.011775089 | D54: ='Belgium Crunch Output'!H56 -> 0.013627921 | E54: ='Belgium Crunch Output'!I56 -> 0.011497821
B55: 1 | C55: ='Belgium Crunch Output'!G57 -> 0.0015992005 | D55: ='Belgium Crunch Output'!H57 -> 0.0051692491 | E55: ='Belgium Crunch Output'!I57 -> 0.0070987276
B56: Extremely Unlikely | C56: ='Belgium Crunch Output'!G58 -> 0.011488474 | D56: ='Belgium Crunch Output'!H58 -> 0.0095444324 | E56: ='Belgium Crunch Output'!I58 -> 0.007954818
B57: n | C57: ='Belgium Crunch Output'!G44 -> 455 | D57: ='Belgium Crunch Output'!H44 -> 546 | E57: ='Belgium Crunch Output'!I44 -> 532
B59: KBC/CBC | C59: NPS | D59: NPS | E59: NPS
C60: ='Belgium Crunch Output'!G78 -> 13.918667 | D60: ='Belgium Crunch Output'!H78 -> 14.392067 | E60: ='Belgium Crunch Output'!I78 -> 13.328339
B61: Promoter | C61: ='Belgium Crunch Output'!G64 -> 0.33872715 | D61: ='Belgium Crunch Output'!H64 -> 0.3410537 | E61: ='Belgium Crunch Output'!I64 -> 0.33790359
B62: Passive | C62: ='Belgium Crunch Output'!G65 -> 0.46173236 | D62: ='Belgium Crunch Output'!H65 -> 0.46181328 | E62: ='Belgium Crunch Output'!I65 -> 0.4574762
B63: Detractor | C63: ='Belgium Crunch Output'!G66 -> 0.19954049 | D63: ='Belgium Crunch Output'!H66 -> 0.19713303 | E63: ='Belgium Crunch Output'!I66 -> 0.20462021
B64: Extremely likely | C64: ='Belgium Crunch Output'!G67 -> 0.15692571 | D64: ='Belgium Crunch Output'!H67 -> 0.15887551 | E64: ='Belgium Crunch Output'!I67 -> 0.15931166
B65: 9 | C65: ='Belgium Crunch Output'!G68 -> 0.18180144 | D65: ='Belgium Crunch Output'!H68 -> 0.18217819 | E65: ='Belgium Crunch Output'!I68 -> 0.17859193
B66: 8 | C66: ='Belgium Crunch Output'!G69 -> 0.30316117 | D66: ='Belgium Crunch Output'!H69 -> 0.29868899 | E66: ='Belgium Crunch Output'!I69 -> 0.30679484
B67: 7 | C67: ='Belgium Crunch Output'!G70 -> 0.15857119 | D67: ='Belgium Crunch Output'!H70 -> 0.16312429 | E67: ='Belgium Crunch Output'!I70 -> 0.15068136
B68: 6 | C68: ='Belgium Crunch Output'!G71 -> 0.059928212 | D68: ='Belgium Crunch Output'!H71 -> 0.053493171 | E68: ='Belgium Crunch Output'!I71 -> 0.060079093
B69: 5 | C69: ='Belgium Crunch Output'!G72 -> 0.087444516 | D69: ='Belgium Crunch Output'!H72 -> 0.091060136 | E69: ='Belgium Crunch Output'!I72 -> 0.095599458
B70: 4 | C70: ='Belgium Crunch Output'!G73 -> 0.0079031328 | D70: ='Belgium Crunch Output'!H73 -> 0.012219239 | E70: ='Belgium Crunch Output'!I73 -> 0.012605521
B71: 3 | C71: ='Belgium Crunch Output'!G74 -> 0.0154632 | D71: ='Belgium Crunch Output'!H74 -> 0.012810706 | E71: ='Belgium Crunch Output'!I74 -> 0.013320091
B72: 2 | C72: ='Belgium Crunch Output'!G75 -> 0.0094288155 | D72: ='Belgium Crunch Output'!H75 -> 0.0097010118 | E72: ='Belgium Crunch Output'!I75 -> 0.0084142044
B73: 1 | C73: ='Belgium Crunch Output'!G76 -> 0.0049711048 | D73: ='Belgium Crunch Output'!H76 -> 0.0059176348 | E73: ='Belgium Crunch Output'!I76 -> 0.0040881162
B74: Extremely Unlikely | C74: ='Belgium Crunch Output'!G77 -> 0.014401505 | D74: ='Belgium Crunch Output'!H77 -> 0.011931129 | E74: ='Belgium Crunch Output'!I77 -> 0.010513722
B75: n | C75: ='Belgium Crunch Output'!G63 -> 420 | D75: ='Belgium Crunch Output'!H63 -> 508 | E75: ='Belgium Crunch Output'!I63 -> 496
B77: Argenta | C77: NPS | D77: NPS | E77: NPS
C78: ='Belgium Crunch Output'!G97 -> 8.6148019 | D78: ='Belgium Crunch Output'!H97 -> 10.919803 | E78: ='Belgium Crunch Output'!I97 -> 16.834355
B79: Promoter | C79: ='Belgium Crunch Output'!G83 -> 0.32432042 | D79: ='Belgium Crunch Output'!H83 -> 0.34139233 | E79: ='Belgium Crunch Output'!I83 -> 0.37684087
B80: Passive | C80: ='Belgium Crunch Output'!G84 -> 0.43750717 | D80: ='Belgium Crunch Output'!H84 -> 0.42641337 | E80: ='Belgium Crunch Output'!I84 -> 0.41466181
B81: Detractor | C81: ='Belgium Crunch Output'!G85 -> 0.2381724 | D81: ='Belgium Crunch Output'!H85 -> 0.2321943 | E81: ='Belgium Crunch Output'!I85 -> 0.20849732
B82: Extremely likely | C82: ='Belgium Crunch Output'!G86 -> 0.11208421 | D82: ='Belgium Crunch Output'!H86 -> 0.13888411 | E82: ='Belgium Crunch Output'!I86 -> 0.15306675
B83: 9 | C83: ='Belgium Crunch Output'!G87 -> 0.21223622 | D83: ='Belgium Crunch Output'!H87 -> 0.20250822 | E83: ='Belgium Crunch Output'!I87 -> 0.22377412
B84: 8 | C84: ='Belgium Crunch Output'!G88 -> 0.29832186 | D84: ='Belgium Crunch Output'!H88 -> 0.29303607 | E84: ='Belgium Crunch Output'!I88 -> 0.28681641
B85: 7 | C85: ='Belgium Crunch Output'!G89 -> 0.13918531 | D85: ='Belgium Crunch Output'!H89 -> 0.1333773 | E85: ='Belgium Crunch Output'!I89 -> 0.1278454
B86: 6 | C86: ='Belgium Crunch Output'!G90 -> 0.089104808 | D86: ='Belgium Crunch Output'!H90 -> 0.084884088 | E86: ='Belgium Crunch Output'!I90 -> 0.069973733
B87: 5 | C87: ='Belgium Crunch Output'!G91 -> 0.1068816 | D87: ='Belgium Crunch Output'!H91 -> 0.10719931 | E87: ='Belgium Crunch Output'!I91 -> 0.10753999
B88: 4 | C88: ='Belgium Crunch Output'!G92 -> 0.0061489885 | D88: ='Belgium Crunch Output'!H92 -> 0.0051561475 | E88: ='Belgium Crunch Output'!I92 -> 0.0056260812
B89: 3 | C89: ='Belgium Crunch Output'!G93 -> 0.0063946212 | D89: ='Belgium Crunch Output'!H93 -> 0.007730335 | E89: ='Belgium Crunch Output'!I93 -> 0.0079910104
B90: 2 | C90: ='Belgium Crunch Output'!G94 -> 0.01653576 | D90: ='Belgium Crunch Output'!H94 -> 0.013865828 | E90: ='Belgium Crunch Output'!I94 -> 0.0086914751
B91: 1 | C91: ='Belgium Crunch Output'!G95 -> 0 | D91: ='Belgium Crunch Output'!H95 -> 0 | E91: ='Belgium Crunch Output'!I95 -> 0
B92: Extremely Unlikely | C92: ='Belgium Crunch Output'!G96 -> 0.013106626 | D92: ='Belgium Crunch Output'!H96 -> 0.013358591 | E92: ='Belgium Crunch Output'!I96 -> 0.0086750338
B93: n | C93: ='Belgium Crunch Output'!G82 -> 315 | D93: ='Belgium Crunch Output'!H82 -> 378 | E93: ='Belgium Crunch Output'!I82 -> 366
B95: Beobank | C95: NPS | D95: NPS | E95: NPS
C96: Low N | D96: Low N | E96: Low N
B97: Promoter | C97: Low N | D97: Low N | E97: Low N
B98: Passive | C98: Low N | D98: Low N | E98: Low N
B99: Detractor | C99: Low N | D99: Low N | E99: Low N
B100: Extremely likely | C100: Low N | D100: Low N | E100: Low N
B101: 9 | C101: Low N | D101: Low N | E101: Low N
B102: 8 | C102: Low N | D102: Low N | E102: Low N
B103: 7 | C103: Low N | D103: Low N | E103: Low N
B104: 6 | C104: Low N | D104: Low N | E104: Low N
B105: 5 | C105: Low N | D105: Low N | E105: Low N
B106: 4 | C106: Low N | D106: Low N | E106: Low N
B107: 3 | C107: Low N | D107: Low N | E107: Low N
...

Sheet Belgium Crunch Output
A1: P97511: ING BAM Belgium
A2: Investment NPS
A3: Based on your knowledge and experience with the investment services offered by the brand(s) below, how likely is it that you would recommend their investment services to a friend, family member or colleague?
A5: Investment NPS: ING | B5: All | C5: Apr 2025 - Sep 2025 | D5: May 2025 - Oct 2025 | E5: June 2025 - Nov 2025 | F5: July 2025 - Dec 2025 | G5: Aug 2025 - Jan 2026 | H5: Sep 2025 - Feb 2026 | I5: Oct 2025 - Mar 2026
A6: Unweighted N | B6: 172 | C6: 41 | D6: 85 | E6: 130 | F6: 172 | G6: 219 | H6: 268 | I6: 275
A7: Promoter | B7: 0.32505318 | C7: 0.34409657 | D7: 0.36205785 | E7: 0.32131414 | F7: 0.32505318 | G7: 0.31415111 | H7: 0.31045631 | I7: 0.29914663
A8: Passive | B8: 0.49329913 | C8: 0.54057805 | D8: 0.50468665 | E8: 0.49925155 | F8: 0.49329913 | G8: 0.4871567 | H8: 0.48671774 | I8: 0.48736151
A9: Detractor | B9: 0.18164769 | C9: 0.11532538 | D9: 0.1332555 | E9: 0.17943431 | F9: 0.18164769 | G9: 0.19869219 | H9: 0.20282594 | I9: 0.21349186
A10: Extremely Likely | B10: 0.14480053 | C10: 0.13385802 | D10: 0.17667753 | E10: 0.14692229 | F10: 0.14480053 | G10: 0.14144933 | H10: 0.14502576 | I10: 0.13958879
A11: 9 | B11: 0.18025265 | C11: 0.21023855 | D11: 0.18538032 | E11: 0.17439185 | F11: 0.18025265 | G11: 0.17270178 | H11: 0.16543056 | I11: 0.15955784
A12: 8 | B12: 0.27502123 | C12: 0.31864751 | D12: 0.2848508 | E12: 0.2921581 | F12: 0.27502123 | G12: 0.26505588 | H12: 0.28799723 | I12: 0.29772607
A13: 7 | B13: 0.2182779 | C13: 0.22193054 | D13: 0.21983585 | E13: 0.20709345 | F13: 0.2182779 | G13: 0.22210082 | H13: 0.19872051 | I13: 0.18963544
A14: 6 | B14: 0.0712211 | C14: 0.05004105 | D14: 0.055713539 | E14: 0.064393471 | F14: 0.0712211 | G14: 0.079837675 | H14: 0.079468581 | I14: 0.088541413
A15: 5 | B15: 0.063950716 | C15: 0.021105745 | D15: 0.046451557 | E15: 0.059848858 | F15: 0.063950716 | G15: 0.060253928 | H15: 0.064047883 | I15: 0.070197316
A16: 4 | B16: 0.011859438 | C16: 0.020610627 | D16: 0.0097450185 | E16: 0.015708289 | F16: 0.011859438 | G16: 0.0093464287 | H16: 0.011521884 | I16: 0.0081749518
A17: 3 | B17: 0.015155108 | C17: 0 | D17: 0 | E17: 0.020073532 | F17: 0.015155108 | G17: 0.017404717 | H17: 0.014243653 | I17: 0.013844497
... A21: Mean | B21: 14.340549 | C21: 22.877119 | D21: 22.880235 | E21: 14.187983 | F21: 14.340549 | G21: 11.545893 | H21: 10.763037 | I21: 8.5654767
A24: Investment NPS: Belfius | B24: All | C24: Apr 2025 - Sep 2025 | D24: May 2025 - Oct 2025 | E24: June 2025 - Nov 2025 | F24: July 2025 - Dec 2025 | G24: Aug 2025 - Jan 2026 | H24: Sep 2025 - Feb 2026 | I24: Oct 2025 - Mar 2026
A25: Unweighted N | B25: 360 | C25: 92 | D25: 174 | E25: 270 | F25: 360 | G25: 451 | H25: 544 | I25: 530
A26: Promoter | B26: 0.32471416 | C26: 0.29196114 | D26: 0.29014365 | E26: 0.30856513 | F26: 0.32471416 | G26: 0.31699818 | H26: 0.32070746 | I26: 0.330788
A27: Passive | B27: 0.50139666 | C27: 0.53892473 | D27: 0.5260559 | E27: 0.51757217 | F27: 0.50139666 | G27: 0.51015071 | H27: 0.48331252 | I27: 0.46744133
A28: Detractor | B28: 0.17388918 | C28: 0.16911413 | D28: 0.18380045 | E28: 0.1738627 | F28: 0.17388918 | G28: 0.17285111 | H28: 0.19598002 | I28: 0.20177067
A29: Extremely Likely | B29: 0.1433897 | C29: 0.11191759 | D29: 0.12924574 | E29: 0.1532546 | F29: 0.1433897 | G29: 0.13346918 | H29: 0.14031488 | I29: 0.14339854
A30: 9 | B30: 0.18132446 | C30: 0.18004356 | D30: 0.16089792 | E30: 0.15531053 | F30: 0.18132446 | G30: 0.18352899 | H30: 0.18039258 | I30: 0.18738947
A31: 8 | B31: 0.31725884 | C31: 0.32001618 | D31: 0.32267511 | E31: 0.31546133 | F31: 0.31725884 | G31: 0.32402977 | H31: 0.30842649 | I31: 0.30866656
A32: 7 | B32: 0.18413782 | C32: 0.21890855 | D32: 0.20338079 | E32: 0.20211084 | F32: 0.18413782 | G32: 0.18612094 | H32: 0.17488604 | I32: 0.15877477
A33: 6 | B33: 0.065423313 | C33: 0.090404755 | D33: 0.082058914 | E33: 0.065841999 | F33: 0.065423313 | G33: 0.066691949 | H33: 0.06986287 | I33: 0.067553118
A34: 5 | B34: 0.058705311 | C34: 0.035491963 | D34: 0.055939492 | E34: 0.06363684 | F34: 0.058705311 | G34: 0.050741542 | H34: 0.056580513 | I34: 0.06491622
A35: 4 | B35: 0.015213173 | C35: 0.011174387 | D35: 0.010612084 | E35: 0.01324207 | F35: 0.015213173 | G35: 0.016608146 | H35: 0.01719166 | I35: 0.017508387
A36: 3 | B36: 0.0088407325 | C36: 0.012614794 | D36: 0.013657726 | E36: 0.0086334458 | F36: 0.0088407325 | G36: 0.011581171 | H36: 0.011453669 | I36: 0.011477302
... A40: Mean | B40: 15.082498 | C40: 12.284702 | D40: 10.63432 | E40: 13.470243 | F40: 15.082498 | G40: 14.414706 | H40: 12.472744 | I40: 12.901733
A43: Investment NPS: BNP Paribas Fortis | B43: All | C43: Apr 2025 - Sep 2025 | D43: May 2025 - Oct 2025 | E43: June 2025 - Nov 2025 | F43: July 2025 - Dec 2025 | G43: Aug 2025 - Jan 2026 | H43: Sep 2025 - Feb 2026 | I43: Oct 2025 - Mar 2026
A44: Unweighted N | B44: 360 | C44: 94 | D44: 184 | E44: 270 | F44: 360 | G44: 455 | H44: 546 | I44: 532
A45: Promoter | B45: 0.35028565 | C45: 0.26039857 | D45: 0.33191417 | E45: 0.34394523 | F45: 0.35028565 | G45: 0.35039206 | H45: 0.3312292 | I45: 0.3672793
A46: Passive | B46: 0.43759051 | C46: 0.470285 | D46: 0.44181665 | E46: 0.42855254 | F46: 0.43759051 | G46: 0.43563614 | H46: 0.4410839 | I46: 0.41490247
A47: Detractor | B47: 0.21212383 | C47: 0.26931642 | D47: 0.22626918 | E47: 0.22750223 | F47: 0.21212383 | G47: 0.2139718 | H47: 0.2276869 | I47: 0.21781823
A48: Extremely Likely | B48: 0.16491235 | C48: 0.15640409 | D48: 0.16821658 | E48: 0.16956951 | F48: 0.16491235 | G48: 0.1678391 | H48: 0.14660326 | I48: 0.16017442
A49: 9 | B49: 0.1853733 | C49: 0.10399449 | D49: 0.16369759 | E49: 0.17437572 | F49: 0.1853733 | G49: 0.18255296 | H49: 0.18462594 | I49: 0.20710488
A50: 8 | B50: 0.28694448 | C50: 0.30814693 | D50: 0.26243806 | E50: 0.27572688 | F50: 0.28694448 | G50: 0.2831717 | H50: 0.27931575 | I50: 0.2544326
A51: 7 | B51: 0.15064603 | C51: 0.16213807 | D51: 0.17937859 | E51: 0.15282566 | F51: 0.15064603 | G51: 0.15246444 | H51: 0.16176815 | I51: 0.16046986
A52: 6 | B52: 0.083610964 | C52: 0.12135412 | D52: 0.092510259 | E52: 0.082399321 | F52: 0.083610964 | G52: 0.08909001 | H52: 0.086978251 | I52: 0.077183604
A53: 5 | B53: 0.073993959 | C53: 0.074731907 | D53: 0.080846802 | E53: 0.087426348 | F53: 0.073993959 | G53: 0.07024479 | H53: 0.083607259 | I53: 0.085837691
A54: 4 | B54: 0.017274224 | C54: 0.018838567 | D54: 0.0096920909 | E54: 0.015429395 | F54: 0.017274224 | G54: 0.020224689 | H54: 0.016802335 | I54: 0.017553942
A55: 3 | B55: 0.0086752101 | C55: 0.019425699 | D55: 0.0099941593 | E55: 0.011541487 | F55: 0.0086752101 | G55: 0.0095495478 | H55: 0.011957452 | I55: 0.010691629
... A59: Mean | B59: 13.816182 | C59: -0.89178476 | D59: 10.564499 | E59: 11.644299 | F59: 13.816182 | G59: 13.642026 | H59: 10.35423 | I59: 14.946107
A62: Investment NPS: KBC (NL)/CBC (FR) | B62: All | C62: Apr 2025 - Sep 2025 | D62: May 2025 - Oct 2025 | E62: June 2025 - Nov 2025 | F62: July 2025 - Dec 2025 | G62: Aug 2025 - Jan 2026 | H62: Sep 2025 - Feb 2026 | I62: Oct 2025 - Mar 2026
A63: Unweighted N | B63: 338 | C63: 95 | D63: 169 | E63: 251 | F63: 338 | G63: 420 | H63: 508 | I63: 496
A64: Promoter | B64: 0.34135713 | C64: 0.38829694 | D64: 0.30627322 | E64: 0.30811897 | F64: 0.34135713 | G64: 0.33872715 | H64: 0.3410537 | I64: 0.33790359
A65: Passive | B65: 0.44926892 | C65: 0.45571969 | D65: 0.4918966 | E65: 0.4759389 | F65: 0.44926892 | G65: 0.46173236 | H65: 0.46181328 | I65: 0.4574762
A66: Detractor | B66: 0.20937395 | C66: 0.15598336 | D66: 0.20183018 | E66: 0.21594213 | F66: 0.20937395 | G66: 0.19954049 | H66: 0.19713303 | I66: 0.20462021
A67: Extremely Likely | B67: 0.1560843 | C67: 0.169598 | D67: 0.10464535 | E67: 0.12755003 | F67: 0.1560843 | G67: 0.15692571 | H67: 0.15887551 | I67: 0.15931166
A68: 9 | B68: 0.18527284 | C68: 0.21869895 | D68: 0.20162787 | E68: 0.18056894 | F68: 0.18527284 | G68: 0.18180144 | H68: 0.18217819 | I68: 0.17859193
A69: 8 | B69: 0.31119552 | C69: 0.26165132 | D69: 0.30175168 | E69: 0.31863872 | F69: 0.31119552 | G69: 0.30316117 | H69: 0.29868899 | I69: 0.30679484
A70: 7 | B70: 0.1380734 | C70: 0.19406837 | D70: 0.19014492 | E70: 0.15730018 | F70: 0.1380734 | G70: 0.15857119 | H70: 0.16312429 | I70: 0.15068136
A71: 6 | B71: 0.070828051 | C71: 0.077424368 | D71: 0.070064884 | E71: 0.066974236 | F71: 0.070828051 | G71: 0.059928212 | H71: 0.053493171 | I71: 0.060079093
A72: 5 | B72: 0.091835758 | C72: 0.040493596 | D72: 0.078555617 | E72: 0.095060462 | F72: 0.091835758 | G72: 0.087444516 | H72: 0.091060136 | I72: 0.095599458
A73: 4 | B73: 0.0037468329 | C73: 0 | D73: 0 | E73: 0.0049893964 | F73: 0.0037468329 | G73: 0.0079031328 | H73: 0.012219239 | I73: 0.012605521
A74: 3 | B74: 0.016277892 | C74: 0.0094887103 | D74: 0.018721058 | E74: 0.021676134 | F74: 0.016277892 | G74: 0.0154632 | H74: 0.012810706 | I74: 0.013320091
... A78: Mean | B78: 13.198319 | C78: 23.231358 | D78: 10.444305 | E78: 9.2176839 | F78: 13.198319 | G78: 13.918667 | H78: 14.392067 | I78: 13.328339
A81: Investment NPS: Argenta | B81: All | C81: Apr 2025 - Sep 2025 | D81: May 2025 - Oct 2025 | E81: June 2025 - Nov 2025 | F81: July 2025 - Dec 2025 | G81: Aug 2025 - Jan 2026 | H81: Sep 2025 - Feb 2026 | I81: Oct 2025 - Mar 2026
A82: Unweighted N | B82: 244 | C82: 67 | D82: 116 | E82: 189 | F82: 244 | G82: 315 | H82: 378 | I82: 366
A83: Promoter | B83: 0.31818633 | C83: 0.25966821 | D83: 0.25580825 | E83: 0.31685461 | F83: 0.31818633 | G83: 0.32432042 | H83: 0.34139233 | I83: 0.37684087
A84: Passive | B84: 0.42419873 | C84: 0.39841222 | D84: 0.44471457 | E84: 0.41580928 | F84: 0.42419873 | G84: 0.43750717 | H84: 0.42641337 | I84: 0.41466181
A85: Detractor | B85: 0.25761494 | C85: 0.34191957 | D85: 0.29947717 | E85: 0.2673361 | F85: 0.25761494 | G85: 0.2381724 | H85: 0.2321943 | I85: 0.20849732
A86: Extremely Likely | B86: 0.12705014 | C86: 0.12113071 | D86: 0.13970742 | E86: 0.14806626 | F86: 0.12705014 | G86: 0.11208421 | H86: 0.13888411 | I86: 0.15306675
A87: 9 | B87: 0.19113619 | C87: 0.13853751 | D87: 0.11610083 | E87: 0.16878835 | F87: 0.19113619 | G87: 0.21223622 | H87: 0.20250822 | I87: 0.22377412
A88: 8 | B88: 0.28258893 | C88: 0.2381955 | D88: 0.28350163 | E88: 0.27410514 | F88: 0.28258893 | G88: 0.29832186 | H88: 0.29303607 | I88: 0.28681641
A89: 7 | B89: 0.1416098 | C89: 0.16021672 | D89: 0.16121294 | E89: 0.14170414 | F89: 0.1416098 | G89: 0.13918531 | H89: 0.1333773 | I89: 0.1278454
A90: 6 | B90: 0.1019101 | C90: 0.14605723 | D90: 0.10110872 | E90: 0.10404507 | F90: 0.1019101 | G90: 0.089104808 | H90: 0.084884088 | I90: 0.069973733
A91: 5 | B91: 0.11512406 | C91: 0.11977898 | D91: 0.12595375 | E91: 0.11669773 | F91: 0.11512406 | G91: 0.1068816 | H91: 0.10719931 | I91: 0.10753999
A92: 4 | B92: 0.0078520477 | C92: 0.013941023 | D92: 0.0077510338 | E92: 0.0045724823 | F92: 0.0078520477 | G92: 0.0061489885 | H92: 0.0051561475 | I92: 0.0056260812
A93: 3 | B93: 0.0030177263 | C93: 0 | D93: 0 | E93: 0.0038744953 | F93: 0.0030177263 | G93: 0.0063946212 | H93: 0.007730335 | I93: 0.0079910104
... A97: Mean | B97: 6.0571391 | C97: -8.2251351 | D97: -4.3668918 | E97: 4.9518508 | F97: 6.0571391 | G97: 8.6148019 | H97: 10.919803 | I97: 16.834355
A100: Investment NPS: AXA | B100: All | C100: Apr 2025 - Sep 2025 | D100: May 2025 - Oct 2025 | E100: June 2025 - Nov 2025 | F100: July 2025 - Dec 2025 | G100: Aug 2025 - Jan 2026 | H100: Sep 2025 - Feb 2026 | I100: Oct 2025 - Mar 2026
A101: Unweighted N | B101: 0 | C101: 0 | D101: 0 | E101: 0 | F101: 0 | G101: 0 | H101: 0 | I101: 0
A102: Promoter | B102: - | C102: - | D102: - | E102: - | F102: - | G102: - | H102: - | I102: -
A103: Passive | B103: - | C103: - | D103: - | E103: - | F103: - | G103: - | H103: - | I103: -
A104: Detractor | B104: - | C104: - | D104: - | E104: - | F104: - | G104: - | H104: - | I104: -
A105: Extremely Likely | B105: - | C105: - | D105: - | E105: - | F105: - | G105: - | H105: - | I105: -
A106: 9 | B106: - | C106: - | D106: - | E106: - | F106: - | G106: - | H106: - | I106: -
A107: 8 | B107: - | C107: - | D107: - | E107: - | F107: - | G107: - | H107: - | I107: -
A108: 7 | B108: - | C108: - | D108: - | E108: - | F108: - | G108: - | H108: - | I108: -
A109: 6 | B109: - | C109: - | D109: - | E109: - | F109: - | G109: - | H109: - | I109: -
A110: 5 | B110: - | C110: - | D110: - | E110: - | F110: - | G110: - | H110: - | I110: -
A111: 4 | B111: - | C111: - | D111: - | E111: - | F111: - | G111: - | H111: - | I111: -
A112: 3 | B112: - | C112: - | D112: - | E112: - | F112: - | G112: - | H112: - | I112: -
A113: 2 | B113: - | C113: - | D113: - | E113: - | F113: - | G113: - | H113: - | I113: -
... A118: Investment NPS: Invisible 1 | B118: All | C118: Apr 2025 - Sep 2025 | D118: May 2025 - Oct 2025 | E118: June 2025 - Nov 2025 | F118: July 2025 - Dec 2025 | G118: Aug 2025 - Jan 2026 | H118: Sep 2025 - Feb 2026 | I118: Oct 2025 - Mar 2026
A119: Unweighted N | B119: 0 | C119: 0 | D119: 0 | E119: 0 | F119: 0 | G119: 0 | H119: 0 | I119: 0
A120: Promoter | B120: - | C120: - | D120: - | E120: - | F120: - | G120: - | H120: - | I120: -
A121: Passive | B121: - | C121: - | D121: - | E121: - | F121: - | G121: - | H121: - | I121: -
A122: Detractor | B122: - | C122: - | D122: - | E122: - | F122: - | G122: - | H122: - | I122: -
A123: Extremely Likely | B123: - | C123: - | D123: - | E123: - | F123: - | G123: - | H123: - | I123: -
A124: 9 | B124: - | C124: - | D124: - | E124: - | F124: - | G124: - | H124: - | I124: -
A125: 8 | B125: - | C125: - | D125: - | E125: - | F125: - | G125: - | H125: - | I125: -
A126: 7 | B126: - | C126: - | D126: - | E126: - | F126: - | G126: - | H126: - | I126: -
A127: 6 | B127: - | C127: - | D127: - | E127: - | F127: - | G127: - | H127: - | I127: -
A128: 5 | B128: - | C128: - | D128: - | E128: - | F128: - | G128: - | H128: - | I128: -
A129: 4 | B129: - | C129: - | D129: - | E129: - | F129: - | G129: - | H129: - | I129: -
A130: 3 | B130: - | C130: - | D130: - | E130: - | F130: - | G130: - | H130: - | I130: -
...

Sheet Germany (quarter)
B2: Source: Global NPS tracking / Toluna | C2: Q4 - 2025
B4: Rolling NPS Data - Total
B5: ING
B6: NPS - ING (%) | C6: ='Germany (Month)'!#REF! -> #REF!
B7: Rank - ING | C7: =C57 -> #REF!
B8: Promoter - ING (%) | C8: ='Germany (Month)'!#REF! -> #REF!
B9: Passive - ING (%) | C9: ='Germany (Month)'!#REF! -> #REF!
B10: Detractor - ING (%) | C10: ='Germany (Month)'!#REF! -> #REF!
B12: Key competitors
B13: Commerzbank
B14: NPS - Commerzbank (%) | C14: ='Germany (Month)'!#REF! -> #REF!
B15: Rank - Commerzbank | C15: =C58 -> #REF!
B16: Promoter - Commerzbank (%) | C16: ='Germany (Month)'!#REF! -> #REF!
B17: Passive - Commerzbank (%) | C17: ='Germany (Month)'!#REF! -> #REF!
B18: Detractor - Commerzbank (%) | C18: ='Germany (Month)'!#REF! -> #REF!
B20: DKB
B21: NPS - DKB (%) | C21: ='Germany (Month)'!#REF! -> #REF!
B22: Rank - DKB | C22: =C59 -> #REF!
B23: Promoter - DKB (%) | C23: ='Germany (Month)'!#REF! -> #REF!
B24: Passive - DKB (%) | C24: ='Germany (Month)'!#REF! -> #REF!
B25: Detractor - DKB (%) | C25: ='Germany (Month)'!#REF! -> #REF!
B27: Postbank
B28: NPS - Postbank (%) | C28: ='Germany (Month)'!#REF! -> #REF!
B29: Rank - Postbank | C29: =C60 -> #REF!
B30: Promoter - Postbank (%) | C30: ='Germany (Month)'!#REF! -> #REF!
B31: Passive - Postbank (%) | C31: ='Germany (Month)'!#REF! -> #REF!
B32: Detractor - Postbank (%) | C32: ='Germany (Month)'!#REF! -> #REF!
B34: Sparkasse
B35: NPS - Sparkasse (%) | C35: ='Germany (Month)'!#REF! -> #REF!
B36: Rank - Sparkasse | C36: =C61 -> #REF!
B37: Promoter - Sparkasse (%) | C37: ='Germany (Month)'!#REF! -> #REF!
B38: Passive - Sparkasse (%) | C38: ='Germany (Month)'!#REF! -> #REF!
B39: Detractor - Sparkasse (%) | C39: ='Germany (Month)'!#REF! -> #REF!
B41: VR-Banken
B42: NPS - VR-Banken (%) | C42: ='Germany (Month)'!#REF! -> #REF!
B43: Rank - VR-Banken | C43: =C62 -> #REF!
B44: Promoter - VR-Banken (%) | C44: ='Germany (Month)'!#REF! -> #REF!
B45: Passive - VR-Banken (%) | C45: ='Germany (Month)'!#REF! -> #REF!
B46: Detractor - VR-Banken (%) | C46: ='Germany (Month)'!#REF! -> #REF!
B48: NPS - ING & Key competitors (For ranking)
B49: ING | C49: =C6 -> #REF!
B50: Commerzbank | C50: =C14 -> #REF!
B51: DKB | C51: =C21 -> #REF!
B52: Postbank | C52: =C28 -> #REF!
B53: Sparkasse | C53: =C35 -> #REF!
B54: VR-Banken | C54: =C42 -> #REF!
B56: Ranking formule
B57: ING | C57: =RANK(C49,C$49:C$54,0) -> #REF!
B58: Commerzbank | C58: =RANK(C50,C$49:C$54,0) -> #REF!
B59: DKB | C59: =RANK(C51,C$49:C$54,0) -> #REF!
B60: Postbank | C60: =RANK(C52,C$49:C$54,0) -> #REF!
B61: Sparkasse | C61: =RANK(C53,C$49:C$54,0) -> #REF!
B62: VR-Banken | C62: =RANK(C54,C$49:C$54,0) -> #REF!
B64: Base Size - NPS
B65: ING | C65: ='Germany (Month)'!#REF! -> #REF!
B66: Commerzbank | C66: ='Germany (Month)'!#REF! -> #REF!
B67: DKB | C67: ='Germany (Month)'!#REF! -> #REF!
B68: Postbank | C68: ='Germany (Month)'!#REF! -> #REF!
B69: Sparkasse | C69: ='Germany (Month)'!#REF! -> #REF!
B70: VR-Banken | C70: ='Germany (Month)'!#REF! -> #REF!
B72: Rolling NPS - Main bank clients
B73: Main bank ING - NPS
B74: NPS - ING (%) | C74: =#REF! -> #REF!
B75: Promoter - ING (%) | C75: =#REF! -> #REF!
B76: Passive - ING (%) | C76: =#REF! -> #REF!
B77: Detractor - ING (%) | C77: =#REF! -> #REF!
B79: Main bank Commerzbank - NPS
B80: NPS - Commerzbank (%) | C80: =#REF! -> #REF!
B81: Promoter - Commerzbank (%) | C81: =#REF! -> #REF!
B82: Passive - Commerzbank (%) | C82: =#REF! -> #REF!
B83: Detractor - Commerzbank (%) | C83: =#REF! -> #REF!
B85: Main bank DKB - NPS
B86: NPS - DKB (%) | C86: =#REF! -> #REF!
B87: Promoter - DKB (%) | C87: =#REF! -> #REF!
B88: Passive - DKB (%) | C88: =#REF! -> #REF!
B89: Detractor - DKB (%) | C89: =#REF! -> #REF!
B91: Main bank Postbank - NPS
B92: NPS - Postbank (%) | C92: =#REF! -> #REF!
B93: Promoter - Postbank (%) | C93: =#REF! -> #REF!
B94: Passive - Postbank (%) | C94: =#REF! -> #REF!
B95: Detractor - Postbank (%) | C95: =#REF! -> #REF!
B97: Main bank Sparkasse - NPS
B98: NPS - Sparkasse (%) | C98: =#REF! -> #REF!
B99: Promoter - Sparkasse (%) | C99: =#REF! -> #REF!
B100: Passive - Sparkasse (%) | C100: =#REF! -> #REF!
B101: Detractor - Sparkasse (%) | C101: =#REF! -> #REF!
B103: Main bank VR-Banken - NPS
B104: NPS - VR-Banken (%) | C104: =#REF! -> #REF!
B105: Promoter -VR-Banken (%) | C105: =#REF! -> #REF!
B106: Passive - VR-Banken (%) | C106: =#REF! -> #REF!
B107: Detractor - VR-Banken (%) | C107: =#REF! -> #REF!
B109: Main bank - Client share (%)
B110: Main bank - ING (%) | C110: =#REF! -> #REF!
B111: Main bank - Commerzbank (%) | C111: =#REF! -> #REF!
B112: Main bank - DKB (%) | C112: =#REF! -> #REF!
B113: Main bank - Postbank (%) | C113: =#REF! -> #REF!
B114: Main bank - Sparkasse (%) | C114: =#REF! -> #REF!
B115: Main bank - VR- Banken (%) | C115: =#REF! -> #REF!
B117: Base size - Main bank clients
B118: Main bank - ING | C118: =#REF! -> #REF!
...

Sheet Germany (Month)
B2: Source: Global NPS tracking / Toluna | C2: January - 2026 (6 months rolling) | D2: February - 2026 (6 months rolling) | E2: March - 2026 (6 months rolling)
B4: NPS total
B5: ING | C5: NPS | D5: NPS | E5: NPS
C6: ='Germany Crunch Output'!G21 -> 37.351547 | D6: ='Germany Crunch Output'!H21 -> 40.748368 | E6: ='Germany Crunch Output'!I21 -> 38.60839
B7: Promoter | C7: ='Germany Crunch Output'!G7 -> 0.51919561 | D7: ='Germany Crunch Output'!H7 -> 0.53085983 | E7: ='Germany Crunch Output'!I7 -> 0.51806757
B8: Passive | C8: ='Germany Crunch Output'!G8 -> 0.33512425 | D8: ='Germany Crunch Output'!H8 -> 0.34576402 | E8: ='Germany Crunch Output'!I8 -> 0.34994875
B9: Detractor | C9: ='Germany Crunch Output'!G9 -> 0.14568014 | D9: ='Germany Crunch Output'!H9 -> 0.12337615 | E9: ='Germany Crunch Output'!I9 -> 0.13198368
B10: Extremely likely | C10: ='Germany Crunch Output'!G10 -> 0.29116013 | D10: ='Germany Crunch Output'!H10 -> 0.29674692 | E10: ='Germany Crunch Output'!I10 -> 0.28992646
B11: 9 | C11: ='Germany Crunch Output'!G11 -> 0.22803548 | D11: ='Germany Crunch Output'!H11 -> 0.23411291 | E11: ='Germany Crunch Output'!I11 -> 0.22814112
B12: 8 | C12: ='Germany Crunch Output'!G12 -> 0.25052702 | D12: ='Germany Crunch Output'!H12 -> 0.25709205 | E12: ='Germany Crunch Output'!I12 -> 0.25989679
B13: 7 | C13: ='Germany Crunch Output'!G13 -> 0.084597237 | D13: ='Germany Crunch Output'!H13 -> 0.088671967 | E13: ='Germany Crunch Output'!I13 -> 0.090051959
B14: 6 | C14: ='Germany Crunch Output'!G14 -> 0.058065004 | D14: ='Germany Crunch Output'!H14 -> 0.047857094 | E14: ='Germany Crunch Output'!I14 -> 0.046945298
B15: 5 | C15: ='Germany Crunch Output'!G15 -> 0.044852787 | D15: ='Germany Crunch Output'!H15 -> 0.036967604 | E15: ='Germany Crunch Output'!I15 -> 0.044694224
B16: 4 | C16: ='Germany Crunch Output'!G16 -> 0.0099705346 | D16: ='Germany Crunch Output'!H16 -> 0.0082177005 | E16: ='Germany Crunch Output'!I16 -> 0.00824947
B17: 3 | C17: ='Germany Crunch Output'!G17 -> 0.0092906878 | D17: ='Germany Crunch Output'!H17 -> 0.0076573718 | E17: ='Germany Crunch Output'!I17 -> 0.0045689004
B18: 2 | C18: ='Germany Crunch Output'!G18 -> 0 | D18: ='Germany Crunch Output'!H18 -> 0 | E18: ='Germany Crunch Output'!I18 -> 0.0037022419
B19: 1 | C19: ='Germany Crunch Output'!G19 -> 0 | D19: ='Germany Crunch Output'!H19 -> 0 | E19: ='Germany Crunch Output'!I19 -> 0
B20: Extremely Unlikely | C20: ='Germany Crunch Output'!G20 -> 0.023501126 | D20: ='Germany Crunch Output'!H20 -> 0.022676378 | E20: ='Germany Crunch Output'!I20 -> 0.023823543
B21: n | C21: ='Germany Crunch Output'!G6 -> 210 | D21: ='Germany Crunch Output'!H6 -> 255 | E21: ='Germany Crunch Output'!I6 -> 256
B23: Commerzbank | C23: NPS | D23: NPS | E23: NPS
C24: Low N | D24: ='Germany Crunch Output'!H97 -> 27.770398 | E24: ='Germany Crunch Output'!I97 -> 25.112411
B25: Promoter | C25: Low N | D25: ='Germany Crunch Output'!H83 -> 0.49966714 | E25: ='Germany Crunch Output'!I83 -> 0.46763512
B26: Passive | C26: Low N | D26: ='Germany Crunch Output'!H84 -> 0.2783697 | E26: ='Germany Crunch Output'!I84 -> 0.31585386
B27: Detractor | C27: Low N | D27: ='Germany Crunch Output'!H85 -> 0.22196316 | E27: ='Germany Crunch Output'!I85 -> 0.21651102
B28: Extremely likely | C28: Low N | D28: ='Germany Crunch Output'!H86 -> 0.2519732 | E28: ='Germany Crunch Output'!I86 -> 0.2666574
B29: 9 | C29: Low N | D29: ='Germany Crunch Output'!H87 -> 0.24769394 | E29: ='Germany Crunch Output'!I87 -> 0.20097772
B30: 8 | C30: Low N | D30: ='Germany Crunch Output'!H88 -> 0.1396274 | E30: ='Germany Crunch Output'!I88 -> 0.18333383
B31: 7 | C31: Low N | D31: ='Germany Crunch Output'!H89 -> 0.1387423 | E31: ='Germany Crunch Output'!I89 -> 0.13252003
B32: 6 | C32: Low N | D32: ='Germany Crunch Output'!H90 -> 0.058508877 | E32: ='Germany Crunch Output'!I90 -> 0.06451441
B33: 5 | C33: Low N | D33: ='Germany Crunch Output'!H91 -> 0.089564336 | E33: ='Germany Crunch Output'!I91 -> 0.098267876
B34: 4 | C34: Low N | D34: ='Germany Crunch Output'!H92 -> 0.00709068 | E34: ='Germany Crunch Output'!I92 -> 0
B35: 3 | C35: Low N | D35: ='Germany Crunch Output'!H93 -> 0.019832188 | E35: ='Germany Crunch Output'!I93 -> 0.019212811
B36: 2 | C36: Low N | D36: ='Germany Crunch Output'!H94 -> 0.010272294 | E36: ='Germany Crunch Output'!I94 -> 0.0099514808
B37: 1 | C37: Low N | D37: ='Germany Crunch Output'!H95 -> 0 | E37: ='Germany Crunch Output'!I95 -> 0
B38: Extremely Unlikely | C38: Low N | D38: ='Germany Crunch Output'!H96 -> 0.036694785 | E38: ='Germany Crunch Output'!I96 -> 0.024564438
B39: n | C39: ='Germany Crunch Output'!G82 -> 91 | D39: ='Germany Crunch Output'!H82 -> 106 | E39: ='Germany Crunch Output'!I82 -> 109
B41: DKB | C41: NPS | D41: NPS | E41: NPS
C42: Low N | D42: Low N | E42: Low N
B43: Promoter | C43: Low N | D43: Low N | E43: Low N
B44: Passive | C44: Low N | D44: Low N | E44: Low N
B45: Detractor | C45: Low N | D45: Low N | E45: Low N
B46: Extremely likely | C46: Low N | D46: Low N | E46: Low N
B47: 9 | C47: Low N | D47: Low N | E47: Low N
B48: 8 | C48: Low N | D48: Low N | E48: Low N
B49: 7 | C49: Low N | D49: Low N | E49: Low N
B50: 6 | C50: Low N | D50: Low N | E50: Low N
B51: 5 | C51: Low N | D51: Low N | E51: Low N
B52: 4 | C52: Low N | D52: Low N | E52: Low N
B53: 3 | C53: Low N | D53: Low N | E53: Low N
B54: 2 | C54: Low N | D54: Low N | E54: Low N
B55: 1 | C55: Low N | D55: Low N | E55: Low N
B56: Extremely Unlikely | C56: Low N | D56: Low N | E56: Low N
B57: n | C57: ='Germany Crunch Output'!G157 -> 47 | D57: ='Germany Crunch Output'!H157 -> 52 | E57: ='Germany Crunch Output'!I157 -> 60
B59: Postbank | C59: NPS | D59: NPS | E59: NPS
C60: Low N | D60: Low N | E60: Low N
B61: Promoter | C61: Low N | D61: Low N | E61: Low N
B62: Passive | C62: Low N | D62: Low N | E62: Low N
B63: Detractor | C63: Low N | D63: Low N | E63: Low N
B64: Extremely likely | C64: Low N | D64: Low N | E64: Low N
B65: 9 | C65: Low N | D65: Low N | E65: Low N
B66: 8 | C66: Low N | D66: Low N | E66: Low N
B67: 7 | C67: Low N | D67: Low N | E67: Low N
B68: 6 | C68: Low N | D68: Low N | E68: Low N
B69: 5 | C69: Low N | D69: Low N | E69: Low N
B70: 4 | C70: Low N | D70: Low N | E70: Low N
B71: 3 | C71: Low N | D71: Low N | E71: Low N
B72: 2 | C72: Low N | D72: Low N | E72: Low N
B73: 1 | C73: Low N | D73: Low N | E73: Low N
B74: Extremely Unlikely | C74: Low N | D74: Low N | E74: Low N
B75: n | C75: ='Germany Crunch Output'!G63 -> 61 | D75: ='Germany Crunch Output'!H63 -> 70 | E75: ='Germany Crunch Output'!I63 -> 59
B77: Sparkasse | C77: NPS | D77: NPS | E77: NPS
C78: ='Germany Crunch Output'!G40 -> 32.435297 | D78: ='Germany Crunch Output'!H40 -> 32.793778 | E78: ='Germany Crunch Output'!I40 -> 36.593052
B79: Promoter | C79: ='Germany Crunch Output'!G26 -> 0.48349876 | D79: ='Germany Crunch Output'!H26 -> 0.49828598 | E79: ='Germany Crunch Output'!I26 -> 0.53151866
B80: Passive | C80: ='Germany Crunch Output'!G27 -> 0.35735545 | D80: ='Germany Crunch Output'!H27 -> 0.33136582 | E80: ='Germany Crunch Output'!I27 -> 0.3028932
B81: Detractor | C81: ='Germany Crunch Output'!G28 -> 0.15914579 | D81: ='Germany Crunch Output'!H28 -> 0.1703482 | E81: ='Germany Crunch Output'!I28 -> 0.16558814
B82: Extremely likely | C82: ='Germany Crunch Output'!G29 -> 0.32349093 | D82: ='Germany Crunch Output'!H29 -> 0.32390662 | E82: ='Germany Crunch Output'!I29 -> 0.33963262
B83: 9 | C83: ='Germany Crunch Output'!G30 -> 0.16000782 | D83: ='Germany Crunch Output'!H30 -> 0.17437936 | E83: ='Germany Crunch Output'!I30 -> 0.19188604
B84: 8 | C84: ='Germany Crunch Output'!G31 -> 0.21736482 | D84: ='Germany Crunch Output'!H31 -> 0.20582978 | E84: ='Germany Crunch Output'!I31 -> 0.19003799
B85: 7 | C85: ='Germany Crunch Output'!G32 -> 0.13999063 | D85: ='Germany Crunch Output'!H32 -> 0.12553604 | E85: ='Germany Crunch Output'!I32 -> 0.11285521
B86: 6 | C86: ='Germany Crunch Output'!G33 -> 0.042752988 | D86: ='Germany Crunch Output'!H33 -> 0.051849746 | E86: ='Germany Crunch Output'!I33 -> 0.052367675
B87: 5 | C87: ='Germany Crunch Output'!G34 -> 0.066935862 | D87: ='Germany Crunch Output'!H34 -> 0.068394665 | E87: ='Germany Crunch Output'!I34 -> 0.063291882
B88: 4 | C88: ='Germany Crunch Output'!G35 -> 0.015048747 | D88: ='Germany Crunch Output'!H35 -> 0.014745305 | E88: ='Germany Crunch Output'!I35 -> 0.013260411
B89: 3 | C89: ='Germany Crunch Output'!G36 -> 0.015153648 | D89: ='Germany Crunch Output'!H36 -> 0.012838725 | E89: ='Germany Crunch Output'!I36 -> 0.013268837
B90: 2 | C90: ='Germany Crunch Output'!G37 -> 0.0042256418 | D90: ='Germany Crunch Output'!H37 -> 0.0035801184 | E90: ='Germany Crunch Output'!I37 -> 0.0019849799
B91: 1 | C91: ='Germany Crunch Output'!G38 -> 0.0023453017 | D91: ='Germany Crunch Output'!H38 -> 0.0059135021 | E91: ='Germany Crunch Output'!I38 -> 0.0061116112
B92: Extremely Unlikely | C92: ='Germany Crunch Output'!G39 -> 0.012683601 | D92: ='Germany Crunch Output'!H39 -> 0.013026141 | E92: ='Germany Crunch Output'!I39 -> 0.015302747
B93: n | C93: ='Germany Crunch Output'!G25 -> 383 | D93: ='Germany Crunch Output'!H25 -> 452 | E93: ='Germany Crunch Output'!I25 -> 436
B95: VR-Banken | C95: NPS | D95: NPS | E95: NPS
C96: ='Germany Crunch Output'!G59 -> 22.486678 | D96: ='Germany Crunch Output'!H59 -> 23.118379 | E96: ='Germany Crunch Output'!I59 -> 22.281993
B97: Promoter | C97: ='Germany Crunch Output'!G45 -> 0.43804723 | D97: ='Germany Crunch Output'!H45 -> 0.43066902 | E97: ='Germany Crunch Output'!I45 -> 0.43301729
B98: Passive | C98: ='Germany Crunch Output'!G46 -> 0.34877233 | D98: ='Germany Crunch Output'!H46 -> 0.36984575 | E98: ='Germany Crunch Output'!I46 -> 0.35678535
B99: Detractor | C99: ='Germany Crunch Output'!G47 -> 0.21318045 | D99: ='Germany Crunch Output'!H47 -> 0.19948523 | E99: ='Germany Crunch Output'!I47 -> 0.21019736
B100: Extremely likely | C100: ='Germany Crunch Output'!G48 -> 0.3127165 | D100: ='Germany Crunch Output'!H48 -> 0.29116759 | E100: ='Germany Crunch Output'!I48 -> 0.27108605
B101: 9 | C101: ='Germany Crunch Output'!G49 -> 0.12533073 | D101: ='Germany Crunch Output'!H49 -> 0.13950143 | E101: ='Germany Crunch Output'!I49 -> 0.16193124
B102: 8 | C102: ='Germany Crunch Output'!G50 -> 0.20130819 | D102: ='Germany Crunch Output'!H50 -> 0.22558841 | E102: ='Germany Crunch Output'!I50 -> 0.24461507
B103: 7 | C103: ='Germany Crunch Output'!G51 -> 0.14746414 | D103: ='Germany Crunch Output'!H51 -> 0.14425735 | E103: ='Germany Crunch Output'!I51 -> 0.11217029
B104: 6 | C104: ='Germany Crunch Output'!G52 -> 0.061293228 | D104: ='Germany Crunch Output'!H52 -> 0.059738053 | E104: ='Germany Crunch Output'!I52 -> 0.063219875
B105: 5 | C105: ='Germany Crunch Output'!G53 -> 0.093815418 | D105: ='Germany Crunch Output'!H53 -> 0.092227477 | E105: ='Germany Crunch Output'!I53 -> 0.1033044
B106: 4 | C106: ='Germany Crunch Output'!G54 -> 0 | D106: ='Germany Crunch Output'!H54 -> 0 | E106: ='Germany Crunch Output'!I54 -> 0
B107: 3 | C107: ='Germany Crunch Output'!G55 -> 0.0064976445 | D107: ='Germany Crunch Output'!H55 -> 0.0053169717 | E107: ='Germany Crunch Output'!I55 -> 0.0053189244
...

Sheet Germany Crunch Output
A1: P97511:ING BAM Germany
A2: Investment NPS
A3: Based on your knowledge and experience with the investment services offered by the brand(s) below, how likely is it that you would recommend their investment services to a friend, family member or colleague?
A5: Investment NPS: ING | B5: All | C5: Apr 2025 - Sep 2025 | D5: May 2025 - Oct 2025 | E5: June 2025 - Nov 2025 | F5: July 2025 - Dec 2025 | G5: Aug 2025 - Jan 2026 | H5: Sep 2025 - Feb 2026 | I5: Oct 2025 - Mar 2026
A6: Unweighted N | B6: 179 | C6: 48 | D6: 102 | E6: 138 | F6: 179 | G6: 210 | H6: 255 | I6: 256
A7: Promoter | B7: 0.49982677 | C7: 0.59465369 | D7: 0.53821203 | E7: 0.51833131 | F7: 0.49982677 | G7: 0.51919561 | H7: 0.53085983 | I7: 0.51806757
A8: Passive | B8: 0.36195482 | C8: 0.33156523 | D8: 0.38219667 | E8: 0.35693717 | F8: 0.36195482 | G8: 0.33512425 | H8: 0.34576402 | I8: 0.34994875
A9: Detractor | B9: 0.13821841 | C9: 0.073781077 | D9: 0.0795913 | E9: 0.12473152 | F9: 0.13821841 | G9: 0.14568014 | H9: 0.12337615 | I9: 0.13198368
A10: Extremely Likely | B10: 0.27003729 | C10: 0.30207186 | D10: 0.3017201 | E10: 0.26353875 | F10: 0.27003729 | G10: 0.29116013 | H10: 0.29674692 | I10: 0.28992646
A11: 9 | B11: 0.22978948 | C11: 0.29258183 | D11: 0.23649192 | E11: 0.25479255 | F11: 0.22978948 | G11: 0.22803548 | H11: 0.23411291 | I11: 0.22814112
A12: 8 | B12: 0.26741089 | C12: 0.23170057 | D12: 0.27930922 | E12: 0.25096076 | F12: 0.26741089 | G12: 0.25052702 | H12: 0.25709205 | I12: 0.25989679
A13: 7 | B13: 0.094543932 | C13: 0.099864668 | D13: 0.10288746 | E13: 0.10597641 | F13: 0.094543932 | G13: 0.084597237 | H13: 0.088671967 | I13: 0.090051959
A14: 6 | B14: 0.056904828 | C14: 0.023727159 | D14: 0.035248796 | E14: 0.057868592 | F14: 0.056904828 | G14: 0.058065004 | H14: 0.047857094 | I14: 0.046945298
A15: 5 | B15: 0.037391536 | C15: 0 | D15: 0.011994982 | E15: 0.027920486 | F15: 0.037391536 | G15: 0.044852787 | H15: 0.036967604 | I15: 0.044694224
A16: 4 | B16: 0.011759487 | C16: 0 | D16: 0 | E16: 0.014935276 | F16: 0.011759487 | G16: 0.0099705346 | H16: 0.0082177005 | I16: 0.00824947
A17: 3 | B17: 0.0044447653 | C17: 0.015897305 | D17: 0.0076063055 | E17: 0.0056451268 | F17: 0.0044447653 | G17: 0.0092906878 | H17: 0.0076573718 | I17: 0.0045689004
... A20: Extremely Unlikely | B20: 0.02771779 | C20: 0.034156613 | D20: 0.024741218 | E20: 0.018362043 | F20: 0.02771779 | G20: 0.023501126 | H20: 0.022676378 | I20: 0.023823543
A21: Mean | B21: =(B7-B9)*100 -> 36.160837 | C21: =(C7-C9)*100 -> 52.087261 | D21: =(D7-D9)*100 -> 45.862072 | E21: =(E7-E9)*100 -> 39.359978 | F21: =(F7-F9)*100 -> 36.160837 | G21: 37.351547 | H21: 40.748368 | I21: 38.60839
A24: Investment NPS: Sparkasse | B24: All | C24: Apr 2025 - Sep 2025 | D24: May 2025 - Oct 2025 | E24: June 2025 - Nov 2025 | F24: July 2025 - Dec 2025 | G24: Aug 2025 - Jan 2026 | H24: Sep 2025 - Feb 2026 | I24: Oct 2025 - Mar 2026
A25: Unweighted N | B25: 308 | C25: 67 | D25: 147 | E25: 233 | F25: 308 | G25: 383 | H25: 452 | I25: 436
A26: Promoter | B26: 0.44375588 | C26: 0.40871554 | D26: 0.47770192 | E26: 0.44773701 | F26: 0.44375588 | G26: 0.48349876 | H26: 0.49828598 | I26: 0.53151866
A27: Passive | B27: 0.38331787 | C27: 0.45918312 | D27: 0.40600108 | E27: 0.3964827 | F27: 0.38331787 | G27: 0.35735545 | H27: 0.33136582 | I27: 0.3028932
A28: Detractor | B28: 0.17292626 | C28: 0.13210134 | D28: 0.116297 | E28: 0.15578029 | F28: 0.17292626 | G28: 0.15914579 | H28: 0.1703482 | I28: 0.16558814
A29: Extremely Likely | B29: 0.26992314 | C29: 0.2705036 | D29: 0.27171775 | E29: 0.25228063 | F29: 0.26992314 | G29: 0.32349093 | H29: 0.32390662 | I29: 0.33963262
A30: 9 | B30: 0.17383274 | C30: 0.13821194 | D30: 0.20598417 | E30: 0.19545638 | F30: 0.17383274 | G30: 0.16000782 | H30: 0.17437936 | I30: 0.19188604
A31: 8 | B31: 0.24555671 | C31: 0.27062248 | D31: 0.24229781 | E31: 0.25036285 | F31: 0.24555671 | G31: 0.21736482 | H31: 0.20582978 | I31: 0.19003799
A32: 7 | B32: 0.13776115 | C32: 0.18856064 | D32: 0.16370327 | E32: 0.14611985 | F32: 0.13776115 | G32: 0.13999063 | H32: 0.12553604 | I32: 0.11285521
A33: 6 | B33: 0.053112821 | C33: 0.024013969 | D33: 0.017693052 | E33: 0.049476926 | F33: 0.053112821 | G33: 0.042752988 | H33: 0.051849746 | I33: 0.052367675
A34: 5 | B34: 0.074146775 | C34: 0.0663322 | D34: 0.068305486 | E34: 0.071128886 | F34: 0.074146775 | G34: 0.066935862 | H34: 0.068394665 | I34: 0.063291882
A35: 4 | B35: 0.014851227 | C35: 0.030325956 | D35: 0.019250753 | E35: 0.016039422 | F35: 0.014851227 | G35: 0.015048747 | H35: 0.014745305 | I35: 0.013260411
A36: 3 | B36: 0.012937344 | C36: 0 | D36: 0.0060040358 | E36: 0.011836461 | F36: 0.012937344 | G36: 0.015153648 | H36: 0.012838725 | I36: 0.013268837
... A39: Extremely Unlikely | B39: 0.012628498 | C39: 0 | D39: 0 | E39: 0.0040777413 | F39: 0.012628498 | G39: 0.012683601 | H39: 0.013026141 | I39: 0.015302747
A40: Mean | B40: =(B26-B28)*100 -> 27.082962 | C40: =(C26-C28)*100 -> 27.66142 | D40: =(D26-D28)*100 -> 36.140491 | E40: =(E26-E28)*100 -> 29.195673 | F40: =(F26-F28)*100 -> 27.082962 | G40: 32.435297 | H40: 32.793778 | I40: 36.593052
A43: Investment NPS: VR-Banken | B43: All | C43: Apr 2025 - Sep 2025 | D43: May 2025 - Oct 2025 | E43: June 2025 - Nov 2025 | F43: July 2025 - Dec 2025 | G43: Aug 2025 - Jan 2026 | H43: Sep 2025 - Feb 2026 | I43: Oct 2025 - Mar 2026
A44: Unweighted N | B44: 148 | C44: 39 | D44: 83 | E44: 115 | F44: 148 | G44: 177 | H44: 215 | I44: 217
A45: Promoter | B45: 0.43832769 | C45: 0.42788404 | D45: 0.42009849 | E45: 0.42863646 | F45: 0.43832769 | G45: 0.43804723 | H45: 0.43066902 | I45: 0.43301729
A46: Passive | B46: 0.36223448 | C46: 0.423846 | D46: 0.37463144 | E46: 0.3641071 | F46: 0.36223448 | G46: 0.34877233 | H46: 0.36984575 | I46: 0.35678535
A47: Detractor | B47: 0.19943783 | C47: 0.14826996 | D47: 0.20527008 | E47: 0.20725644 | F47: 0.19943783 | G47: 0.21318045 | H47: 0.19948523 | I47: 0.21019736
A48: Extremely Likely | B48: 0.3156411 | C48: 0.34297117 | D48: 0.32412114 | E48: 0.31105221 | F48: 0.3156411 | G48: 0.3127165 | H48: 0.29116759 | I48: 0.27108605
A49: 9 | B49: 0.12268659 | C49: 0.084912869 | D49: 0.095977349 | E49: 0.11758425 | F49: 0.12268659 | G49: 0.12533073 | H49: 0.13950143 | I49: 0.16193124
A50: 8 | B50: 0.19928119 | C50: 0.14957243 | D50: 0.17737036 | E50: 0.16963641 | F50: 0.19928119 | G50: 0.20130819 | H50: 0.22558841 | I50: 0.24461507
A51: 7 | B51: 0.16295329 | C51: 0.27427357 | D51: 0.19726108 | E51: 0.19447068 | F51: 0.16295329 | G51: 0.14746414 | H51: 0.14425735 | I51: 0.11217029
A52: 6 | B52: 0.059336244 | C52: 0.031294394 | D52: 0.072885249 | E52: 0.068546817 | F52: 0.059336244 | G52: 0.061293228 | H52: 0.059738053 | I52: 0.063219875
A53: 5 | B53: 0.096815577 | C53: 0.096008183 | D53: 0.10022714 | E53: 0.093310943 | F53: 0.096815577 | G53: 0.093815418 | H53: 0.092227477 | I53: 0.1033044
A54: 4 | B54: 0 | C54: 0 | D54: 0 | E54: 0 | F54: 0 | G54: 0 | H54: 0 | I54: 0
A55: 3 | B55: 0 | C55: 0 | D55: 0 | E55: 0 | F55: 0 | G55: 0.0064976445 | H55: 0.0053169717 | I55: 0.0053189244
... A58: Extremely Unlikely | B58: 0.013637262 | C58: 0 | D58: 0.010339695 | E58: 0.0075027671 | F58: 0.013637262 | G58: 0.011374938 | H58: 0.0093080224 | I58: 0.009311441
A59: Mean | B59: =(B45-B47)*100 -> 23.888986 | C59: =(C45-C47)*100 -> 27.961407 | D59: =(D45-D47)*100 -> 21.482841 | E59: =(E45-E47)*100 -> 22.138002 | F59: =(F45-F47)*100 -> 23.888986 | G59: 22.486678 | H59: 23.118379 | I59: 22.281993
A62: Investment NPS: Postbank | B62: All | C62: Apr 2025 - Sep 2025 | D62: May 2025 - Oct 2025 | E62: June 2025 - Nov 2025 | F62: July 2025 - Dec 2025 | G62: Aug 2025 - Jan 2026 | H62: Sep 2025 - Feb 2026 | I62: Oct 2025 - Mar 2026
A63: Unweighted N | B63: 53 | C63: 15 | D63: 21 | E63: 39 | F63: 53 | G63: 61 | H63: 70 | I63: 59
A64: Promoter | B64: 0.34681604 | C64: 0.35219071 | D64: 0.37731677 | E64: 0.33946184 | F64: 0.34681604 | G64: 0.38567754 | H64: 0.34968941 | I64: 0.37368836
A65: Passive | B65: 0.29296144 | C65: 0.32400773 | D65: 0.29052044 | E65: 0.22024148 | F65: 0.29296144 | G65: 0.27150149 | H65: 0.30839101 | I65: 0.30225585
A66: Detractor | B66: 0.36022252 | C66: 0.32380157 | D66: 0.33216279 | E66: 0.44029668 | F66: 0.36022252 | G66: 0.34282097 | H66: 0.34191958 | I66: 0.32405579
A67: Extremely Likely | B67: 0.21696295 | C67: 0.22802069 | D67: 0.24298966 | E67: 0.18979232 | F67: 0.21696295 | G67: 0.24411632 | H67: 0.21349782 | I67: 0.22854563
A68: 9 | B68: 0.12985309 | C68: 0.12417002 | D68: 0.13432711 | E68: 0.14966951 | F68: 0.12985309 | G68: 0.14156123 | H68: 0.13619159 | I68: 0.14514273
A69: 8 | B69: 0.19094071 | C69: 0.17211484 | D69: 0.18007682 | E69: 0.13586488 | F69: 0.19094071 | G69: 0.18248472 | H69: 0.18898903 | I69: 0.1809773
A70: 7 | B70: 0.10202073 | C70: 0.15189288 | D70: 0.11044362 | E70: 0.084376602 | F70: 0.10202073 | G70: 0.08901677 | H70: 0.11940198 | I70: 0.12127855
A71: 6 | B71: 0.074418379 | C71: 0.073271438 | D71: 0.092039593 | E71: 0.072320883 | F71: 0.074418379 | G71: 0.064932721 | H71: 0.068801523 | I71: 0.063003942
A72: 5 | B72: 0.16381385 | C72: 0.17725869 | D72: 0.12888748 | E72: 0.20185336 | F72: 0.16381385 | G72: 0.14293349 | H72: 0.13996204 | I72: 0.12051219
A73: 4 | B73: 0.020727485 | C73: 0 | D73: 0 | E73: 0.028226018 | F73: 0.020727485 | G73: 0.018085478 | H73: 0.015817092 | I73: 0.019056783
A74: 3 | B74: 0.062966307 | C74: 0.073271438 | D74: 0.053276772 | E74: 0.085745479 | F74: 0.062966307 | G74: 0.054940375 | H74: 0.048049433 | I74: 0.038001365
... A77: Extremely Unlikely | B77: 0.014761903 | C77: 0 | D77: 0 | E77: 0.020102281 | F77: 0.014761903 | G77: 0.027181361 | H77: 0.023772116 | I77: 0.028641172
A78: Mean | B78: =(B64-B66)*100 -> -1.3406483 | C78: =(C64-C66)*100 -> 2.8389142 | D78: =(D64-D66)*100 -> 4.5153979 | E78: =(E64-E66)*100 -> -10.083485 | F78: =(F64-F66)*100 -> -1.3406483 | G78: 4.2856574 | H78: 0.77698382 | I78: 4.9632565
A81: Investment NPS: Commerzbank | B81: All | C81: Apr 2025 - Sep 2025 | D81: May 2025 - Oct 2025 | E81: June 2025 - Nov 2025 | F81: July 2025 - Dec 2025 | G81: Aug 2025 - Jan 2026 | H81: Sep 2025 - Feb 2026 | I81: Oct 2025 - Mar 2026
A82: Unweighted N | B82: 73 | C82: 18 | D82: 38 | E82: 53 | F82: 73 | G82: 91 | H82: 106 | I82: 109
A83: Promoter | B83: 0.49366683 | C83: 0.63549806 | D83: 0.51242748 | E83: 0.46358544 | F83: 0.49366683 | G83: 0.4849376 | H83: 0.49966714 | I83: 0.46763512
A84: Passive | B84: 0.29008265 | C84: 0.20551759 | D84: 0.3057842 | E84: 0.30929028 | F84: 0.29008265 | G84: 0.27790266 | H84: 0.2783697 | I84: 0.31585386
A85: Detractor | B85: 0.21625051 | C85: 0.15898435 | D85: 0.18178831 | E85: 0.22712429 | F85: 0.21625051 | G85: 0.23715974 | H85: 0.22196316 | I85: 0.21651102
A86: Extremely Likely | B86: 0.2285972 | C86: 0.11499921 | D86: 0.21892166 | E86: 0.20533665 | F86: 0.2285972 | G86: 0.22665984 | H86: 0.2519732 | I86: 0.2666574
A87: 9 | B87: 0.26506963 | C87: 0.52049885 | D87: 0.29350582 | E87: 0.25824879 | F87: 0.26506963 | G87: 0.25827776 | H87: 0.24769394 | I87: 0.20097772
A88: 8 | B88: 0.11246195 | C88: 0.056748478 | D88: 0.12441456 | E88: 0.12302377 | F88: 0.11246195 | G88: 0.12575718 | H88: 0.1396274 | I88: 0.18333383
A89: 7 | B89: 0.1776207 | C89: 0.14876911 | D89: 0.18136965 | E89: 0.18626651 | F89: 0.1776207 | G89: 0.15214548 | H89: 0.1387423 | I89: 0.13252003
A90: 6 | B90: 0.060174334 | C90: 0 | D90: 0.072885072 | E90: 0.069642123 | F90: 0.060174334 | G90: 0.068168996 | H90: 0.058508877 | I90: 0.06451441
A91: 5 | B91: 0.10533365 | C91: 0.046613094 | D91: 0.05613622 | E91: 0.085375643 | F91: 0.10533365 | G91: 0.10435187 | H91: 0.089564336 | I91: 0.098267876
A92: 4 | B92: 0.010310916 | C92: 0.043235293 | D92: 0.020302323 | E92: 0.014652091 | F92: 0.010310916 | G92: 0.0082613881 | H92: 0.00709068 | I92: 0
A93: 3 | B93: 0.011992246 | C93: 0 | D93: 0 | E93: 0.017041308 | F93: 0.011992246 | G93: 0.023106585 | H93: 0.019832188 | I93: 0.019212811
... A96: Extremely Unlikely | B96: 0.028439374 | C96: 0.069135968 | D96: 0.032464699 | E96: 0.040413123 | F96: 0.028439374 | G96: 0.0332709 | H96: 0.036694785 | I96: 0.024564438
A97: Mean | B97: =(B83-B85)*100 -> 27.741632 | C97: =(C83-C85)*100 -> 47.65137 | D97: =(D83-D85)*100 -> 33.063917 | E97: =(E83-E85)*100 -> 23.646115 | F97: =(F83-F85)*100 -> 27.741632 | G97: 24.777786 | H97: 27.770398 | I97: 25.112411
A100: Investment NPS: Invisible 1 | B100: All | C100: Apr 2025 - Sep 2025 | D100: May 2025 - Oct 2025 | E100: June 2025 - Nov 2025 | F100: July 2025 - Dec 2025 | G100: Aug 2025 - Jan 2026 | H100: Sep 2025 - Feb 2026 | I100: Oct 2025 - Mar 2026
A101: Unweighted N | B101: 0 | C101: 0 | D101: 0 | E101: 0 | F101: 0 | G101: 0 | H101: 0 | I101: 0
A102: Promoter | B102: - | C102: - | D102: - | E102: - | F102: - | G102: - | H102: - | I102: -
A103: Passive | B103: - | C103: - | D103: - | E103: - | F103: - | G103: - | H103: - | I103: -
A104: Detractor | B104: - | C104: - | D104: - | E104: - | F104: - | G104: - | H104: - | I104: -
A105: Extremely Likely | B105: - | C105: - | D105: - | E105: - | F105: - | G105: - | H105: - | I105: -
A106: 9 | B106: - | C106: - | D106: - | E106: - | F106: - | G106: - | H106: - | I106: -
A107: 8 | B107: - | C107: - | D107: - | E107: - | F107: - | G107: - | H107: - | I107: -
A108: 7 | B108: - | C108: - | D108: - | E108: - | F108: - | G108: - | H108: - | I108: -
A109: 6 | B109: - | C109: - | D109: - | E109: - | F109: - | G109: - | H109: - | I109: -
A110: 5 | B110: - | C110: - | D110: - | E110: - | F110: - | G110: - | H110: - | I110: -
A111: 4 | B111: - | C111: - | D111: - | E111: - | F111: - | G111: - | H111: - | I111: -
A112: 3 | B112: - | C112: - | D112: - | E112: - | F112: - | G112: - | H112: - | I112: -
A113: 2 | B113: - | C113: - | D113: - | E113: - | F113: - | G113: - | H113: - | I113: -
... A118: Investment NPS: Comdirect | B118: All | C118: Apr 2025 - Sep 2025 | D118: May 2025 - Oct 2025 | E118: June 2025 - Nov 2025 | F118: July 2025 - Dec 2025 | G118: Aug 2025 - Jan 2026 | H118: Sep 2025 - Feb 2026 | I118: Oct 2025 - Mar 2026
A119: Unweighted N | B119: 71 | C119: 12 | D119: 34 | E119: 45 | F119: 71 | G119: 87 | H119: 97 | I119: 108
A120: Promoter | B120: 0.40358775 | C120: 0.49195873 | D120: 0.4022234 | E120: 0.36385167 | F120: 0.40358775 | G120: 0.44013511 | H120: 0.43731214 | I120: 0.4371134
A121: Passive | B121: 0.36627938 | C121: 0.32905965 | D121: 0.38258893 | E121: 0.36285661 | F121: 0.36627938 | G121: 0.3754083 | H121: 0.37575387 | I121: 0.38019594
A122: Detractor | B122: 0.23013286 | C122: 0.17898162 | D122: 0.21518766 | E122: 0.27329172 | F122: 0.23013286 | G122: 0.18445658 | H122: 0.18693399 | I122: 0.18269066
A123: Extremely Likely | B123: 0.16877818 | C123: 0.1453576 | D123: 0.076406663 | E123: 0.098959594 | F123: 0.16877818 | G123: 0.22483397 | H123: 0.21219176 | I123: 0.23777859
A124: 9 | B124: 0.23480957 | C124: 0.34660113 | D124: 0.32581674 | E124: 0.26489207 | F124: 0.23480957 | G124: 0.21530114 | H124: 0.22512038 | I124: 0.19933481
A125: 8 | B125: 0.2567302 | C125: 0.32905965 | D125: 0.29749007 | E125: 0.27403725 | F125: 0.2567302 | G125: 0.27338092 | H125: 0.27525707 | I125: 0.26569072
...

Sheet Italy (quarter)
B2: Source: Global NPS tracking / Toluna | C2: Q4 - 2025
B4: Rolling NPS Data - Total
B5: ING
B6: NPS - ING (%) | C6: ='Italy (Month)'!#REF! -> #REF!
B7: Rank - ING | C7: =C57 -> #REF!
B8: Promoter - ING (%) | C8: ='Italy (Month)'!#REF! -> #REF!
B9: Passive - ING (%) | C9: ='Italy (Month)'!#REF! -> #REF!
B10: Detractor - ING (%) | C10: ='Italy (Month)'!#REF! -> #REF!
B12: Key competitors
B13: Banco Mediolanum
B14: NPS - Banco Mediolanum (%) | C14: ='Italy (Month)'!#REF! -> #REF!
B15: Rank - Banco Mediolanum | C15: =C58 -> #REF!
B16: Promoter - Banco Mediolanum (%) | C16: ='Italy (Month)'!#REF! -> #REF!
B17: Passive - Banco Mediolanum (%) | C17: ='Italy (Month)'!#REF! -> #REF!
B18: Detractor - Banco Mediolanum (%) | C18: ='Italy (Month)'!#REF! -> #REF!
B20: BancoPosta
B21: NPS - BancoPosta (%) | C21: ='Italy (Month)'!#REF! -> #REF!
B22: Rank - BancoPosta | C22: =C59 -> #REF!
B23: Promoter - BancoPosta (%) | C23: ='Italy (Month)'!#REF! -> #REF!
B24: Passive - BancoPosta (%) | C24: ='Italy (Month)'!#REF! -> #REF!
B25: Detractor - BancoPosta (%) | C25: ='Italy (Month)'!#REF! -> #REF!
B27: Fineco
B28: NPS - Fineco (%) | C28: ='Italy (Month)'!#REF! -> #REF!
B29: Rank - Fineco | C29: =C60 -> #REF!
B30: Promoter - Fineco (%) | C30: ='Italy (Month)'!#REF! -> #REF!
B31: Passive - Fineco (%) | C31: ='Italy (Month)'!#REF! -> #REF!
B32: Detractor - Fineco (%) | C32: ='Italy (Month)'!#REF! -> #REF!
B34: Intesa Sanpaolo
B35: NPS - Intesa Sanpaolo (%) | C35: ='Italy (Month)'!#REF! -> #REF!
B36: Rank - Intesa Sanpaolo | C36: =C61 -> #REF!
B37: Promoter - Intesa Sanpaolo (%) | C37: ='Italy (Month)'!#REF! -> #REF!
B38: Passive - Intesa Sanpaolo (%) | C38: ='Italy (Month)'!#REF! -> #REF!
B39: Detractor - Intesa Sanpaolo (%) | C39: ='Italy (Month)'!#REF! -> #REF!
B41: Unicredit
B42: NPS - Unicredit (%) | C42: ='Italy (Month)'!#REF! -> #REF!
B43: Rank - Unicredit | C43: =C62 -> #REF!
B44: Promoter - Unicredit (%) | C44: ='Italy (Month)'!#REF! -> #REF!
B45: Passive - Unicredit (%) | C45: ='Italy (Month)'!#REF! -> #REF!
B46: Detractor - Unicredit (%) | C46: ='Italy (Month)'!#REF! -> #REF!
B48: NPS - ING & Key competitors (For ranking)
B49: ING | C49: =C6 -> #REF!
B50: Banco Mediolanum | C50: =C14 -> #REF!
B51: BancoPosta | C51: =C21 -> #REF!
B52: Fineco | C52: =C28 -> #REF!
B53: Intesa Sanpaolo | C53: =C35 -> #REF!
B54: Unicredit | C54: =C42 -> #REF!
B56: Ranking formule
B57: ING | C57: =RANK(C49,C$49:C$54,0) -> #REF!
B58: Banco Mediolanum | C58: =RANK(C50,C$49:C$54,0) -> #REF!
B59: BancoPosta | C59: =RANK(C51,C$49:C$54,0) -> #REF!
B60: Fineco | C60: =RANK(C52,C$49:C$54,0) -> #REF!
B61: Intesa Sanpaolo | C61: =RANK(C53,C$49:C$54,0) -> #REF!
B62: Unicredit | C62: =RANK(C54,C$49:C$54,0) -> #REF!
B64: Base Size - NPS
B65: ING | C65: ='Italy (Month)'!#REF! -> #REF!
B66: Banco Mediolanum | C66: ='Italy (Month)'!#REF! -> #REF!
B67: BancoPosta | C67: ='Italy (Month)'!#REF! -> #REF!
B68: Fineco | C68: ='Italy (Month)'!#REF! -> #REF!
B69: Intesa Sanpaolo | C69: ='Italy (Month)'!#REF! -> #REF!
B70: Unicredit | C70: ='Italy (Month)'!#REF! -> #REF!

Sheet Italy (Month)
B2: Source: Global NPS tracking / Toluna | C2: January - 2026 (6 months rolling) | D2: February - 2026 (6 months rolling) | E2: March - 2026 (6 months rolling)
B4: NPS total
B5: ING | C5: NPS | D5: NPS | E5: NPS
C6: ='Italy Crunch Outputs'!G21 -> 41.703194 | D6: ='Italy Crunch Outputs'!H21 -> 38.719898 | E6: ='Italy Crunch Outputs'!I21 -> 38.887289
B7: Promoter | C7: ='Italy Crunch Outputs'!G7 -> 0.52840888 | D7: ='Italy Crunch Outputs'!H7 -> 0.50575071 | E7: ='Italy Crunch Outputs'!I7 -> 0.50260135
B8: Passive | C8: ='Italy Crunch Outputs'!G8 -> 0.36021419 | D8: ='Italy Crunch Outputs'!H8 -> 0.37569756 | E8: ='Italy Crunch Outputs'!I8 -> 0.38367018
B9: Detractor | C9: ='Italy Crunch Outputs'!G9 -> 0.11137694 | D9: ='Italy Crunch Outputs'!H9 -> 0.11855173 | E9: ='Italy Crunch Outputs'!I9 -> 0.11372846
B10: Extremely likely | C10: ='Italy Crunch Outputs'!G10 -> 0.33473567 | D10: ='Italy Crunch Outputs'!H10 -> 0.3178736 | E10: ='Italy Crunch Outputs'!I10 -> 0.31586166
B11: 9 | C11: ='Italy Crunch Outputs'!G11 -> 0.1936732 | D11: ='Italy Crunch Outputs'!H11 -> 0.18787711 | E11: ='Italy Crunch Outputs'!I11 -> 0.1867397
B12: 8 | C12: ='Italy Crunch Outputs'!G12 -> 0.23372213 | D12: ='Italy Crunch Outputs'!H12 -> 0.25396142 | E12: ='Italy Crunch Outputs'!I12 -> 0.26250132
B13: 7 | C13: ='Italy Crunch Outputs'!G13 -> 0.12649205 | D13: ='Italy Crunch Outputs'!H13 -> 0.12173613 | E13: ='Italy Crunch Outputs'!I13 -> 0.12116886
B14: 6 | C14: ='Italy Crunch Outputs'!G14 -> 0.021437039 | D14: ='Italy Crunch Outputs'!H14 -> 0.027790039 | E14: ='Italy Crunch Outputs'!I14 -> 0.020349044
B15: 5 | C15: ='Italy Crunch Outputs'!G15 -> 0.057560834 | D15: ='Italy Crunch Outputs'!H15 -> 0.063630739 | E15: ='Italy Crunch Outputs'!I15 -> 0.065465958
B16: 4 | C16: ='Italy Crunch Outputs'!G16 -> 0 | D16: ='Italy Crunch Outputs'!H16 -> 0 | E16: ='Italy Crunch Outputs'!I16 -> 0
B17: 3 | C17: ='Italy Crunch Outputs'!G17 -> 0 | D17: ='Italy Crunch Outputs'!H17 -> 0 | E17: ='Italy Crunch Outputs'!I17 -> 0
B18: 2 | C18: ='Italy Crunch Outputs'!G18 -> 0.010867289 | D18: ='Italy Crunch Outputs'!H18 -> 0.0091058826 | E18: ='Italy Crunch Outputs'!I18 -> 0.0093685119
B19: 1 | C19: ='Italy Crunch Outputs'!G19 -> 0 | D19: ='Italy Crunch Outputs'!H19 -> 0 | E19: ='Italy Crunch Outputs'!I19 -> 0
B20: Extremely Unlikely | C20: ='Italy Crunch Outputs'!G20 -> 0.021511774 | D20: ='Italy Crunch Outputs'!H20 -> 0.018025074 | E20: ='Italy Crunch Outputs'!I20 -> 0.018544948
B21: n | C21: ='Italy Crunch Outputs'!G6 -> 90 | D21: ='Italy Crunch Outputs'!H6 -> 108 | E21: ='Italy Crunch Outputs'!I6 -> 104
B23: Banco Mediolanum | C23: NPS | D23: NPS | E23: NPS
C24: ='Italy Crunch Outputs'!G154 -> 40.753957 | D24: ='Italy Crunch Outputs'!H154 -> 43.349631 | E24: ='Italy Crunch Outputs'!I154 -> 43.023035
B25: Promoter | C25: ='Italy Crunch Outputs'!G140 -> 0.523978 | D25: ='Italy Crunch Outputs'!H140 -> 0.55144508 | E25: ='Italy Crunch Outputs'!I140 -> 0.55773136
B26: Passive | C26: ='Italy Crunch Outputs'!G141 -> 0.35958356 | D26: ='Italy Crunch Outputs'!H141 -> 0.33060616 | E26: ='Italy Crunch Outputs'!I141 -> 0.31476764
B27: Detractor | C27: ='Italy Crunch Outputs'!G142 -> 0.11643844 | D27: ='Italy Crunch Outputs'!H142 -> 0.11794877 | E27: ='Italy Crunch Outputs'!I142 -> 0.12750101
B28: Extremely likely | C28: ='Italy Crunch Outputs'!G143 -> 0.30318651 | D28: ='Italy Crunch Outputs'!H143 -> 0.31669237 | E28: ='Italy Crunch Outputs'!I143 -> 0.30194934
B29: 9 | C29: ='Italy Crunch Outputs'!G144 -> 0.2207915 | D29: ='Italy Crunch Outputs'!H144 -> 0.2347527 | E29: ='Italy Crunch Outputs'!I144 -> 0.25578202
B30: 8 | C30: ='Italy Crunch Outputs'!G145 -> 0.23844055 | D30: ='Italy Crunch Outputs'!H145 -> 0.22268345 | E30: ='Italy Crunch Outputs'!I145 -> 0.22270668
B31: 7 | C31: ='Italy Crunch Outputs'!G146 -> 0.12114301 | D31: ='Italy Crunch Outputs'!H146 -> 0.10792271 | E31: ='Italy Crunch Outputs'!I146 -> 0.09206096
B32: 6 | C32: ='Italy Crunch Outputs'!G147 -> 0.051259698 | D32: ='Italy Crunch Outputs'!H147 -> 0.063339332 | E32: ='Italy Crunch Outputs'!I147 -> 0.06595243
B33: 5 | C33: ='Italy Crunch Outputs'!G148 -> 0.03254915 | D33: ='Italy Crunch Outputs'!H148 -> 0.027271018 | E33: ='Italy Crunch Outputs'!I148 -> 0.030736308
B34: 4 | C34: ='Italy Crunch Outputs'!G149 -> 0.00804472 | D34: ='Italy Crunch Outputs'!H149 -> 0.0067401977 | E34: ='Italy Crunch Outputs'!I149 -> 0.0075966651
B35: 3 | C35: ='Italy Crunch Outputs'!G150 -> 0.01628835 | D35: ='Italy Crunch Outputs'!H150 -> 0.01364705 | E35: ='Italy Crunch Outputs'!I150 -> 0.015381162
B36: 2 | C36: ='Italy Crunch Outputs'!G151 -> 0 | D36: ='Italy Crunch Outputs'!H151 -> 0 | E36: ='Italy Crunch Outputs'!I151 -> 0
B37: 1 | C37: ='Italy Crunch Outputs'!G152 -> 0 | D37: ='Italy Crunch Outputs'!H152 -> 0 | E37: ='Italy Crunch Outputs'!I152 -> 0
B38: Extremely Unlikely | C38: ='Italy Crunch Outputs'!G153 -> 0.0082965216 | D38: ='Italy Crunch Outputs'!H153 -> 0.0069511675 | E38: ='Italy Crunch Outputs'!I153 -> 0.0078344425
B39: n | C39: ='Italy Crunch Outputs'!G139 -> 123 | D39: ='Italy Crunch Outputs'!H139 -> 146 | E39: ='Italy Crunch Outputs'!I139 -> 127
B41: Fineco | C41: NPS | D41: NPS | E41: NPS
C42: ='Italy Crunch Outputs'!G192 -> 66.036846 | D42: ='Italy Crunch Outputs'!H192 -> 63.103222 | E42: ='Italy Crunch Outputs'!I192 -> 63.19128
B43: Promoter | C43: ='Italy Crunch Outputs'!G178 -> 0.70667391 | D43: ='Italy Crunch Outputs'!H178 -> 0.68205607 | E43: ='Italy Crunch Outputs'!I178 -> 0.68882894
B44: Passive | C44: ='Italy Crunch Outputs'!G179 -> 0.24702063 | D44: ='Italy Crunch Outputs'!H179 -> 0.26692007 | E44: ='Italy Crunch Outputs'!I179 -> 0.25425492
B45: Detractor | C45: ='Italy Crunch Outputs'!G180 -> 0.046305451 | D45: ='Italy Crunch Outputs'!H180 -> 0.051023853 | E45: ='Italy Crunch Outputs'!I180 -> 0.05691614
B46: Extremely likely | C46: ='Italy Crunch Outputs'!G181 -> 0.38521343 | D46: ='Italy Crunch Outputs'!H181 -> 0.38169804 | E46: ='Italy Crunch Outputs'!I181 -> 0.36833272
B47: 9 | C47: ='Italy Crunch Outputs'!G182 -> 0.32146048 | D47: ='Italy Crunch Outputs'!H182 -> 0.30035803 | E47: ='Italy Crunch Outputs'!I182 -> 0.32049622
B48: 8 | C48: ='Italy Crunch Outputs'!G183 -> 0.17311861 | D48: ='Italy Crunch Outputs'!H183 -> 0.18904865 | E48: ='Italy Crunch Outputs'!I183 -> 0.1716947
B49: 7 | C49: ='Italy Crunch Outputs'!G184 -> 0.073902021 | D49: ='Italy Crunch Outputs'!H184 -> 0.077871421 | E49: ='Italy Crunch Outputs'!I184 -> 0.082560224
B50: 6 | C50: ='Italy Crunch Outputs'!G185 -> 0.02758046 | D50: ='Italy Crunch Outputs'!H185 -> 0.028394107 | E50: ='Italy Crunch Outputs'!I185 -> 0.027851252
B51: 5 | C51: ='Italy Crunch Outputs'!G186 -> 0.011654191 | D51: ='Italy Crunch Outputs'!H186 -> 0.016626587 | E51: ='Italy Crunch Outputs'!I186 -> 0.01809885
B52: 4 | C52: ='Italy Crunch Outputs'!G187 -> 0 | D52: ='Italy Crunch Outputs'!H187 -> 0 | E52: ='Italy Crunch Outputs'!I187 -> 0
B53: 3 | C53: ='Italy Crunch Outputs'!G188 -> 0.0070708006 | D53: ='Italy Crunch Outputs'!H188 -> 0.0060031592 | E53: ='Italy Crunch Outputs'!I188 -> 0.010966038
B54: 2 | C54: ='Italy Crunch Outputs'!G189 -> 0 | D54: ='Italy Crunch Outputs'!H189 -> 0 | E54: ='Italy Crunch Outputs'!I189 -> 0
B55: 1 | C55: ='Italy Crunch Outputs'!G190 -> 0 | D55: ='Italy Crunch Outputs'!H190 -> 0 | E55: ='Italy Crunch Outputs'!I190 -> 0
B56: Extremely Unlikely | C56: ='Italy Crunch Outputs'!G191 -> 0 | D56: ='Italy Crunch Outputs'!H191 -> 0 | E56: ='Italy Crunch Outputs'!I191 -> 0
B57: n | C57: ='Italy Crunch Outputs'!G177 -> 149 | D57: ='Italy Crunch Outputs'!H177 -> 176 | E57: ='Italy Crunch Outputs'!I177 -> 180
B59: Intesa Sanpaolo | C59: NPS | D59: NPS | E59: NPS
C60: ='Italy Crunch Outputs'!G78 -> 29.89663 | D60: ='Italy Crunch Outputs'!H78 -> 29.271521 | E60: ='Italy Crunch Outputs'!I78 -> 26.860344
B61: Promoter | C61: ='Italy Crunch Outputs'!G64 -> 0.43516416 | D61: ='Italy Crunch Outputs'!H64 -> 0.43564318 | E61: ='Italy Crunch Outputs'!I64 -> 0.41505492
B62: Passive | C62: ='Italy Crunch Outputs'!G65 -> 0.42863798 | D62: ='Italy Crunch Outputs'!H65 -> 0.42142885 | E62: ='Italy Crunch Outputs'!I65 -> 0.43849359
B63: Detractor | C63: ='Italy Crunch Outputs'!G66 -> 0.13619786 | D63: ='Italy Crunch Outputs'!H66 -> 0.14292797 | E63: ='Italy Crunch Outputs'!I66 -> 0.14645148
B64: Extremely likely | C64: ='Italy Crunch Outputs'!G67 -> 0.21145344 | D64: ='Italy Crunch Outputs'!H67 -> 0.21692283 | E64: ='Italy Crunch Outputs'!I67 -> 0.20425366
B65: 9 | C65: ='Italy Crunch Outputs'!G68 -> 0.22371072 | D65: ='Italy Crunch Outputs'!H68 -> 0.21872035 | E65: ='Italy Crunch Outputs'!I68 -> 0.21080126
B66: 8 | C66: ='Italy Crunch Outputs'!G69 -> 0.28286225 | D66: ='Italy Crunch Outputs'!H69 -> 0.28208622 | E66: ='Italy Crunch Outputs'!I69 -> 0.29359596
B67: 7 | C67: ='Italy Crunch Outputs'!G70 -> 0.14577573 | D67: ='Italy Crunch Outputs'!H70 -> 0.13934262 | E67: ='Italy Crunch Outputs'!I70 -> 0.14489764
B68: 6 | C68: ='Italy Crunch Outputs'!G71 -> 0.060546855 | D68: ='Italy Crunch Outputs'!H71 -> 0.06114785 | E68: ='Italy Crunch Outputs'!I71 -> 0.060488791
B69: 5 | C69: ='Italy Crunch Outputs'!G72 -> 0.041774827 | D69: ='Italy Crunch Outputs'!H72 -> 0.045043924 | E69: ='Italy Crunch Outputs'!I72 -> 0.046738396
B70: 4 | C70: ='Italy Crunch Outputs'!G73 -> 0.0053628249 | D70: ='Italy Crunch Outputs'!H73 -> 0.0045188563 | E70: ='Italy Crunch Outputs'!I73 -> 0.0021873584
B71: 3 | C71: ='Italy Crunch Outputs'!G74 -> 0.013514441 | D71: ='Italy Crunch Outputs'!H74 -> 0.011387621 | E71: ='Italy Crunch Outputs'!I74 -> 0.014572578
B72: 2 | C72: ='Italy Crunch Outputs'!G75 -> 0.0024040355 | D72: ='Italy Crunch Outputs'!H75 -> 0.0020257031 | E72: ='Italy Crunch Outputs'!I75 -> 0.0021846729
B73: 1 | C73: ='Italy Crunch Outputs'!G76 -> 0.0037071191 | D73: ='Italy Crunch Outputs'!H76 -> 0.0031237153 | E73: ='Italy Crunch Outputs'!I76 -> 0.0033688532
B74: Extremely Unlikely | C74: ='Italy Crunch Outputs'!G77 -> 0.0088877572 | D74: ='Italy Crunch Outputs'!H77 -> 0.015680301 | E74: ='Italy Crunch Outputs'!I77 -> 0.016910835
B75: n | C75: ='Italy Crunch Outputs'!G63 -> 342 | D75: ='Italy Crunch Outputs'!H63 -> 405 | E75: ='Italy Crunch Outputs'!I63 -> 379
B77: Unicredit | C77: NPS | D77: NPS | E77: NPS
C78: ='Italy Crunch Outputs'!G116 -> 39.055306 | D78: ='Italy Crunch Outputs'!H116 -> 37.424715 | E78: ='Italy Crunch Outputs'!I116 -> 39.030946
B79: Promoter | C79: ='Italy Crunch Outputs'!G102 -> 0.48367958 | D79: ='Italy Crunch Outputs'!H102 -> 0.47072628 | E79: ='Italy Crunch Outputs'!I102 -> 0.48816751
B80: Passive | C80: ='Italy Crunch Outputs'!G103 -> 0.4231939 | D80: ='Italy Crunch Outputs'!H103 -> 0.43279459 | E80: ='Italy Crunch Outputs'!I103 -> 0.41397443
B81: Detractor | C81: ='Italy Crunch Outputs'!G104 -> 0.093126519 | D81: ='Italy Crunch Outputs'!H104 -> 0.096479132 | E81: ='Italy Crunch Outputs'!I104 -> 0.097858054
B82: Extremely likely | C82: ='Italy Crunch Outputs'!G105 -> 0.25296779 | D82: ='Italy Crunch Outputs'!H105 -> 0.24360592 | E82: ='Italy Crunch Outputs'!I105 -> 0.25757045
B83: 9 | C83: ='Italy Crunch Outputs'!G106 -> 0.23071179 | D83: ='Italy Crunch Outputs'!H106 -> 0.22712036 | E83: ='Italy Crunch Outputs'!I106 -> 0.23059707
B84: 8 | C84: ='Italy Crunch Outputs'!G107 -> 0.27931047 | D84: ='Italy Crunch Outputs'!H107 -> 0.27567394 | E84: ='Italy Crunch Outputs'!I107 -> 0.26286328
B85: 7 | C85: ='Italy Crunch Outputs'!G108 -> 0.14388343 | D85: ='Italy Crunch Outputs'!H108 -> 0.15712065 | E85: ='Italy Crunch Outputs'!I108 -> 0.15111115
B86: 6 | C86: ='Italy Crunch Outputs'!G109 -> 0.04875576 | D86: ='Italy Crunch Outputs'!H109 -> 0.043076733 | E86: ='Italy Crunch Outputs'!I109 -> 0.051677069
B87: 5 | C87: ='Italy Crunch Outputs'!G110 -> 0.010797313 | D87: ='Italy Crunch Outputs'!H110 -> 0.014596657 | E87: ='Italy Crunch Outputs'!I110 -> 0.01048438
B88: 4 | C88: ='Italy Crunch Outputs'!G111 -> 0.011484764 | D88: ='Italy Crunch Outputs'!H111 -> 0.010147029 | E88: ='Italy Crunch Outputs'!I111 -> 0.0043753376
B89: 3 | C89: ='Italy Crunch Outputs'!G112 -> 0.0064053316 | D89: ='Italy Crunch Outputs'!H112 -> 0.0098976859 | E89: ='Italy Crunch Outputs'!I112 -> 0.0046194177
B90: 2 | C90: ='Italy Crunch Outputs'!G113 -> 0.0068905441 | D90: ='Italy Crunch Outputs'!H113 -> 0.0060879398 | E90: ='Italy Crunch Outputs'!I113 -> 0.0066351596
B91: 1 | C91: ='Italy Crunch Outputs'!G114 -> 0.0042116636 | D91: ='Italy Crunch Outputs'!H114 -> 0.0086255516 | E91: ='Italy Crunch Outputs'!I114 -> 0.015655338
B92: Extremely Unlikely | C92: ='Italy Crunch Outputs'!G115 -> 0.004581143 | D92: ='Italy Crunch Outputs'!H115 -> 0.0040475356 | E92: ='Italy Crunch Outputs'!I115 -> 0.0044113519
B93: n | C93: ='Italy Crunch Outputs'!G101 -> 176 | D93: ='Italy Crunch Outputs'!H101 -> 200 | E93: ='Italy Crunch Outputs'!I101 -> 184
B95: BancoPosta | C95: NPS | D95: NPS | E95: NPS
C96: ='Italy Crunch Outputs'!G40 -> 34.563509 | D96: ='Italy Crunch Outputs'!H40 -> 34.87419 | E96: ='Italy Crunch Outputs'!I40 -> 30.505965
B97: Promoter | C97: ='Italy Crunch Outputs'!G26 -> 0.48823294 | D97: ='Italy Crunch Outputs'!H26 -> 0.49215916 | E97: ='Italy Crunch Outputs'!I26 -> 0.48576449
B98: Passive | C98: ='Italy Crunch Outputs'!G27 -> 0.36916921 | D98: ='Italy Crunch Outputs'!H27 -> 0.36442359 | E98: ='Italy Crunch Outputs'!I27 -> 0.33353068
B99: Detractor | C99: ='Italy Crunch Outputs'!G28 -> 0.14259785 | D99: ='Italy Crunch Outputs'!H28 -> 0.14341725 | E99: ='Italy Crunch Outputs'!I28 -> 0.18070484
B100: Extremely likely | C100: ='Italy Crunch Outputs'!G29 -> 0.23673887 | D100: ='Italy Crunch Outputs'!H29 -> 0.24249495 | E100: ='Italy Crunch Outputs'!I29 -> 0.2557344
B101: 9 | C101: ='Italy Crunch Outputs'!G30 -> 0.25149407 | D101: ='Italy Crunch Outputs'!H30 -> 0.2496642 | E101: ='Italy Crunch Outputs'!I30 -> 0.23003009
B102: 8 | C102: ='Italy Crunch Outputs'!G31 -> 0.25082276 | D102: ='Italy Crunch Outputs'!H31 -> 0.24507709 | E102: ='Italy Crunch Outputs'!I31 -> 0.22920891
B103: 7 | C103: ='Italy Crunch Outputs'!G32 -> 0.11834645 | D103: ='Italy Crunch Outputs'!H32 -> 0.1193465 | E103: ='Italy Crunch Outputs'!I32 -> 0.10432177
B104: 6 | C104: ='Italy Crunch Outputs'!G33 -> 0.067562723 | D104: ='Italy Crunch Outputs'!H33 -> 0.071650764 | E104: ='Italy Crunch Outputs'!I33 -> 0.091970294
B105: 5 | C105: ='Italy Crunch Outputs'!G34 -> 0.035290918 | D105: ='Italy Crunch Outputs'!H34 -> 0.031025631 | E105: ='Italy Crunch Outputs'!I34 -> 0.053920835
B106: 4 | C106: ='Italy Crunch Outputs'!G35 -> 0.0078421822 | D106: ='Italy Crunch Outputs'!H35 -> 0.0099147416 | E106: ='Italy Crunch Outputs'!I35 -> 0.0068650576
B107: 3 | C107: ='Italy Crunch Outputs'!G36 -> 0.012979049 | D107: ='Italy Crunch Outputs'!H36 -> 0.014190186 | E107: ='Italy Crunch Outputs'!I36 -> 0.015149851
...

Sheet Italy Crunch Outputs
A1: P105170 : ING BAM Italy (Main+Boost)
A2: Investment NPS
A3: Based on your knowledge and experience with the investment services offered by the brand(s) below, how likely is it that you would recommend their investment services to a friend, family member or colleague?
A5: Investment NPS: ING | B5: All | C5: Apr 2025 - Sep 2025 | D5: May 2025 - Oct 2025 | E5: June 2025 - Nov 2025 | F5: July 2025 - Dec 2025 | G5: August 2025 - Jan 2026 | H5: Sep 2025 - Feb 2026 | I5: Oct 2025 - Mar 2026
A6: Unweighted N | B6: 66 | C6: 17 | D6: 39 | E6: 51 | F6: 66 | G6: 90 | H6: 108 | I6: 104
A7: Promoter | B7: 0.48733401 | C7: 0.5343269 | D7: 0.48576476 | E7: 0.47013707 | F7: 0.48733401 | G7: 0.52840888 | H7: 0.50575071 | I7: 0.50260135
A8: Passive | B8: 0.43043926 | C8: 0.41453789 | D8: 0.46485332 | E8: 0.45417915 | F8: 0.43043926 | G8: 0.36021419 | H8: 0.37569756 | I8: 0.38367018
A9: Detractor | B9: 0.082226726 | C9: 0.051135203 | D9: 0.049381924 | E9: 0.075683771 | F9: 0.082226726 | G9: 0.11137694 | H9: 0.11855173 | I9: 0.11372846
A10: Extremely Likely | B10: 0.31190311 | C10: 0.36807791 | D10: 0.31356335 | E10: 0.31477117 | F10: 0.31190311 | G10: 0.33473567 | H10: 0.3178736 | I10: 0.31586166
A11: 9 | B11: 0.1754309 | C11: 0.16624899 | D11: 0.17220141 | E11: 0.15536591 | F11: 0.1754309 | G11: 0.1936732 | H11: 0.18787711 | I11: 0.1867397
A12: 8 | B12: 0.30449704 | C12: 0.31912954 | D12: 0.34981627 | E12: 0.32745775 | F12: 0.30449704 | G12: 0.23372213 | H12: 0.25396142 | I12: 0.26250132
A13: 7 | B13: 0.12594222 | C13: 0.095408349 | D13: 0.11503705 | E13: 0.12672141 | F13: 0.12594222 | G13: 0.12649205 | H13: 0.12173613 | I13: 0.12116886
A14: 6 | B14: 0.029048503 | C14: 0.051135203 | D14: 0.049381924 | E14: 0.03741729 | F14: 0.029048503 | G14: 0.021437039 | H14: 0.027790039 | I14: 0.020349044
A15: 5 | B15: 0.03845238 | C15: 0 | D15: 0 | E15: 0.019298166 | F15: 0.03845238 | G15: 0.057560834 | H15: 0.063630739 | I15: 0.065465958
A16: 4 | B16: 0 | C16: 0 | D16: 0 | E16: 0 | F16: 0 | G16: 0 | H16: 0 | I16: 0
A17: 3 | B17: 0 | C17: 0 | D17: 0 | E17: 0 | F17: 0 | G17: 0 | H17: 0 | I17: 0
... A21: Mean | B21: 40.510729 | C21: 48.31917 | D21: 43.638283 | E21: 39.44533 | F21: 40.510729 | G21: 41.703194 | H21: 38.719898 | I21: 38.887289
A24: Investment NPS: BancoPosta | B24: All | C24: Apr 2025 - Sep 2025 | D24: May 2025 - Oct 2025 | E24: June 2025 - Nov 2025 | F24: July 2025 - Dec 2025 | G24: August 2025 - Jan 2026 | H24: Sep 2025 - Feb 2026 | I24: Oct 2025 - Mar 2026
A25: Unweighted N | B25: 232 | C25: 74 | D25: 135 | E25: 182 | F25: 232 | G25: 274 | H25: 311 | I25: 293
A26: Promoter | B26: 0.51093619 | C26: 0.46321529 | D26: 0.49739302 | E26: 0.49510571 | F26: 0.51093619 | G26: 0.48823294 | H26: 0.49215916 | I26: 0.48576449
A27: Passive | B27: 0.35876763 | C27: 0.45464665 | D27: 0.40202654 | E27: 0.38330223 | F27: 0.35876763 | G27: 0.36916921 | H27: 0.36442359 | I27: 0.33353068
A28: Detractor | B28: 0.13029618 | C28: 0.082138057 | D28: 0.10058045 | E28: 0.12159206 | F28: 0.13029618 | G28: 0.14259785 | H28: 0.14341725 | I28: 0.18070484
A29: Extremely Likely | B29: 0.2451136 | C29: 0.22766398 | D29: 0.21497004 | E29: 0.22445427 | F29: 0.2451136 | G29: 0.23673887 | H29: 0.24249495 | I29: 0.2557344
A30: 9 | B30: 0.26582259 | C30: 0.23555131 | D30: 0.28242298 | E30: 0.27065143 | F30: 0.26582259 | G30: 0.25149407 | H30: 0.2496642 | I30: 0.23003009
A31: 8 | B31: 0.24988876 | C31: 0.26292209 | D31: 0.26895274 | E31: 0.26449241 | F31: 0.24988876 | G31: 0.25082276 | H31: 0.24507709 | I31: 0.22920891
A32: 7 | B32: 0.10887887 | C32: 0.19172456 | D32: 0.1330738 | E32: 0.11880983 | F32: 0.10887887 | G32: 0.11834645 | H32: 0.1193465 | I32: 0.10432177
A33: 6 | B33: 0.062444791 | C33: 0.036951967 | D33: 0.035770309 | E33: 0.056016474 | F33: 0.062444791 | G33: 0.067562723 | H33: 0.071650764 | I33: 0.091970294
A34: 5 | B34: 0.021076035 | C34: 0 | D34: 0.013381095 | E34: 0.016385353 | F34: 0.021076035 | G34: 0.035290918 | H34: 0.031025631 | I34: 0.053920835
A35: 4 | B35: 0.0092295424 | C35: 0.014283969 | D35: 0.015789158 | E35: 0.011719924 | F35: 0.0092295424 | G35: 0.0078421822 | H35: 0.0099147416 | I35: 0.0068650576
A36: 3 | B36: 0.015275172 | C36: 0 | D36: 0.018375524 | E36: 0.019396829 | F36: 0.015275172 | G36: 0.012979049 | H36: 0.014190186 | I36: 0.015149851
... A40: Mean | B40: 38.064001 | C40: 38.107724 | D40: 39.681257 | E40: 37.351365 | F40: 38.064001 | G40: 34.563509 | H40: 34.87419 | I40: 30.505965
A43: Investment NPS: BNL | B43: All | C43: Apr 2025 - Sep 2025 | D43: May 2025 - Oct 2025 | E43: June 2025 - Nov 2025 | F43: July 2025 - Dec 2025 | G43: August 2025 - Jan 2026 | H43: Sep 2025 - Feb 2026 | I43: Oct 2025 - Mar 2026
A44: Unweighted N | B44: 48 | C44: 12 | D44: 26 | E44: 37 | F44: 48 | G44: 59 | H44: 65 | I44: 66
A45: Promoter | B45: 0.56999378 | C45: 0.59116158 | D45: 0.46251746 | E45: 0.51327733 | F45: 0.56999378 | G45: 0.50938692 | H45: 0.4898764 | I45: 0.48609024
A46: Passive | B46: 0.33383351 | C46: 0.40883842 | D46: 0.42370869 | E46: 0.4088483 | F46: 0.33383351 | G46: 0.36405543 | H46: 0.37831798 | I46: 0.32549631
A47: Detractor | B47: 0.096172714 | C47: 0 | D47: 0.11377385 | E47: 0.077874367 | F47: 0.096172714 | G47: 0.12655764 | H47: 0.13180562 | I47: 0.18841345
A48: Extremely Likely | B48: 0.3033361 | C48: 0.35082055 | D48: 0.2460763 | E48: 0.30275007 | F48: 0.3033361 | G48: 0.27666905 | H48: 0.26618871 | I48: 0.27967233
A49: 9 | B49: 0.26665768 | C49: 0.24034103 | D49: 0.21644116 | E49: 0.21052726 | F49: 0.26665768 | G49: 0.23271787 | H49: 0.22368769 | I49: 0.20641791
A50: 8 | B50: 0.2479375 | C50: 0.3306655 | D50: 0.29600387 | E50: 0.32143866 | F50: 0.2479375 | G50: 0.25483173 | H50: 0.24508932 | I50: 0.19475636
A51: 7 | B51: 0.085896003 | C51: 0.078172918 | D51: 0.12770482 | E51: 0.087409648 | F51: 0.085896003 | G51: 0.10922371 | H51: 0.13322866 | I51: 0.13073995
A52: 6 | B52: 0.016826906 | C52: 0 | D52: 0.031871909 | E52: 0.021815248 | F52: 0.016826906 | G52: 0.04299413 | H52: 0.056585758 | I52: 0.070216256
A53: 5 | B53: 0.079345808 | C53: 0 | D53: 0.081901941 | E53: 0.056059119 | F53: 0.079345808 | G53: 0.064194002 | H53: 0.057784357 | I53: 0.074482198
A54: 4 | B54: 0 | C54: 0 | D54: 0 | E54: 0 | F54: 0 | G54: 0 | H54: 0 | I54: 0.013084792
A55: 3 | B55: 0 | C55: 0 | D55: 0 | E55: 0 | F55: 0 | G55: 0 | H55: 0 | I55: 0
... A59: Mean | B59: 47.382107 | C59: 59.116158 | D59: 34.874361 | E59: 43.540296 | F59: 47.382107 | G59: 38.282928 | H59: 35.807078 | I59: 29.76768
A62: Investment NPS: Intesa Sanpaolo | B62: All | C62: Apr 2025 - Sep 2025 | D62: May 2025 - Oct 2025 | E62: June 2025 - Nov 2025 | F62: July 2025 - Dec 2025 | G62: August 2025 - Jan 2026 | H62: Sep 2025 - Feb 2026 | I62: Oct 2025 - Mar 2026
A63: Unweighted N | B63: 272 | C63: 69 | D63: 142 | E63: 210 | F63: 272 | G63: 342 | H63: 405 | I63: 379
A64: Promoter | B64: 0.43848122 | C64: 0.55713194 | D64: 0.47960203 | E64: 0.43960438 | F64: 0.43848122 | G64: 0.43516416 | H64: 0.43564318 | I64: 0.41505492
A65: Passive | B65: 0.41676792 | C65: 0.34771675 | D65: 0.41129646 | E65: 0.43870334 | F65: 0.41676792 | G65: 0.42863798 | H65: 0.42142885 | I65: 0.43849359
A66: Detractor | B66: 0.14475085 | C66: 0.095151304 | D66: 0.10910151 | E66: 0.12169228 | F66: 0.14475085 | G66: 0.13619786 | H66: 0.14292797 | I66: 0.14645148
A67: Extremely Likely | B67: 0.2093326 | C67: 0.27473611 | D67: 0.22158272 | E67: 0.20263919 | F67: 0.2093326 | G67: 0.21145344 | H67: 0.21692283 | I67: 0.20425366
A68: 9 | B68: 0.22914862 | C68: 0.28239583 | D68: 0.25801931 | E68: 0.23696519 | F68: 0.22914862 | G68: 0.22371072 | H68: 0.21872035 | I68: 0.21080126
A69: 8 | B69: 0.26634188 | C69: 0.24147069 | D69: 0.22921574 | E69: 0.27345842 | F69: 0.26634188 | G69: 0.28286225 | H69: 0.28208622 | I69: 0.29359596
A70: 7 | B70: 0.15042605 | C70: 0.10624606 | D70: 0.18208072 | E70: 0.16524492 | F70: 0.15042605 | G70: 0.14577573 | H70: 0.13934262 | I70: 0.14489764
A71: 6 | B71: 0.06025827 | C71: 0.045211378 | D71: 0.049877804 | E71: 0.040332449 | F71: 0.06025827 | G71: 0.060546855 | H71: 0.06114785 | I71: 0.060488791
A72: 5 | B72: 0.048457041 | C72: 0.021138226 | D72: 0.039318013 | E72: 0.047661135 | F72: 0.048457041 | G72: 0.041774827 | H72: 0.045043924 | I72: 0.046738396
A73: 4 | B73: 0.0067193633 | C73: 0.014195687 | D73: 0.012702228 | E73: 0.0087338243 | F73: 0.0067193633 | G73: 0.0053628249 | H73: 0.0045188563 | I73: 0.0021873584
A74: 3 | B74: 0.010523261 | C74: 0.014606014 | D74: 0.0072034682 | E74: 0.0049529757 | F74: 0.010523261 | G74: 0.013514441 | H74: 0.011387621 | I74: 0.014572578
... A78: Mean | B78: 29.373037 | C78: 46.198064 | D78: 37.050052 | E78: 31.79121 | F78: 29.373037 | G78: 29.89663 | H78: 29.271521 | I78: 26.860344
A81: Investment NPS: Monte dei Paschi di Siena | B81: All | C81: Apr 2025 - Sep 2025 | D81: May 2025 - Oct 2025 | E81: June 2025 - Nov 2025 | F81: July 2025 - Dec 2025 | G81: August 2025 - Jan 2026 | H81: Sep 2025 - Feb 2026 | I81: Oct 2025 - Mar 2026
A82: Unweighted N | B82: 53 | C82: 12 | D82: 22 | E82: 39 | F82: 53 | G82: 66 | H82: 76 | I82: 73
A83: Promoter | B83: 0.56125459 | C83: 0.44200525 | D83: 0.4401123 | E83: 0.55031475 | F83: 0.56125459 | G83: 0.53127681 | H83: 0.53024642 | I83: 0.50150757
A84: Passive | B84: 0.33482913 | C84: 0.48692315 | D84: 0.43297476 | E84: 0.35523592 | F84: 0.33482913 | G84: 0.35313608 | H84: 0.35404328 | I84: 0.39027184
A85: Detractor | B85: 0.10391628 | C85: 0.071071599 | D85: 0.12691294 | E85: 0.094449335 | F85: 0.10391628 | G85: 0.11558711 | H85: 0.1157103 | I85: 0.10822059
A86: Extremely Likely | B86: 0.31583161 | C86: 0.34591352 | D86: 0.29964438 | E86: 0.37632642 | F86: 0.31583161 | G86: 0.28580461 | H86: 0.27641026 | I86: 0.24133348
A87: 9 | B87: 0.24542298 | C87: 0.096091735 | D87: 0.14046793 | E87: 0.17398833 | F87: 0.24542298 | G87: 0.2454722 | H87: 0.25383617 | I87: 0.2601741
A88: 8 | B88: 0.17972261 | C88: 0.21604822 | D88: 0.19710309 | E88: 0.19347188 | F88: 0.17972261 | G88: 0.1887159 | H88: 0.16325134 | I88: 0.17840124
A89: 7 | B89: 0.15510652 | C89: 0.27087493 | D89: 0.23587167 | E89: 0.16176404 | F89: 0.15510652 | G89: 0.16442018 | H89: 0.19079193 | I89: 0.21187059
A90: 6 | B90: 0.065865103 | C90: 0.071071599 | D90: 0.077809772 | E90: 0.043322817 | F90: 0.065865103 | G90: 0.084762906 | H90: 0.089045387 | I90: 0.080534939
A91: 5 | B91: 0.017703543 | C91: 0 | D91: 0 | E91: 0.023786927 | F91: 0.017703543 | G91: 0.014341152 | H91: 0.012406015 | I91: 0.012880919
A92: 4 | B92: 0 | C92: 0 | D92: 0 | E92: 0 | F92: 0 | G92: 0 | H92: 0 | I92: 0
A93: 3 | B93: 0 | C93: 0 | D93: 0 | E93: 0 | F93: 0 | G93: 0 | H93: 0 | I93: 0
... A97: Mean | B97: 45.733832 | C97: 37.093365 | D97: 31.319937 | E97: 45.586541 | F97: 45.733832 | G97: 41.568969 | H97: 41.453612 | I97: 39.328699
A100: Investment NPS: Unicredit | B100: All | C100: Apr 2025 - Sep 2025 | D100: May 2025 - Oct 2025 | E100: June 2025 - Nov 2025 | F100: July 2025 - Dec 2025 | G100: August 2025 - Jan 2026 | H100: Sep 2025 - Feb 2026 | I100: Oct 2025 - Mar 2026
A101: Unweighted N | B101: 141 | C101: 38 | D101: 69 | E101: 99 | F101: 141 | G101: 176 | H101: 200 | I101: 184
A102: Promoter | B102: 0.48719109 | C102: 0.48419024 | D102: 0.47697059 | E102: 0.48359457 | F102: 0.48719109 | G102: 0.48367958 | H102: 0.47072628 | I102: 0.48816751
A103: Passive | B103: 0.41973005 | C103: 0.42734167 | D103: 0.42149893 | E103: 0.38957057 | F103: 0.41973005 | G103: 0.4231939 | H103: 0.43279459 | I103: 0.41397443
A104: Detractor | B104: 0.09307886 | C104: 0.088468089 | D104: 0.10153048 | E104: 0.12683486 | F104: 0.09307886 | G104: 0.093126519 | H104: 0.096479132 | I104: 0.097858054
A105: Extremely Likely | B105: 0.24489141 | C105: 0.24271881 | D105: 0.24828499 | E105: 0.2477171 | F105: 0.24489141 | G105: 0.25296779 | H105: 0.24360592 | I105: 0.25757045
A106: 9 | B106: 0.24229969 | C106: 0.24147143 | D106: 0.2286856 | E106: 0.23587747 | F106: 0.24229969 | G106: 0.23071179 | H106: 0.22712036 | I106: 0.23059707
A107: 8 | B107: 0.28498892 | C107: 0.28452085 | D107: 0.30468483 | E107: 0.27688257 | F107: 0.28498892 | G107: 0.27931047 | H107: 0.27567394 | I107: 0.26286328
A108: 7 | B108: 0.13474112 | C108: 0.14282082 | D108: 0.11681409 | E108: 0.112688 | F108: 0.13474112 | G108: 0.14388343 | H108: 0.15712065 | I108: 0.15111115
A109: 6 | B109: 0.038054645 | C109: 0 | D109: 0.023370916 | E109: 0.055226293 | F109: 0.038054645 | G109: 0.04875576 | H109: 0.043076733 | I109: 0.051677069
A110: 5 | B110: 0.013389757 | C110: 0.026257285 | D110: 0.014476351 | E110: 0.019431705 | F110: 0.013389757 | G110: 0.010797313 | H110: 0.014596657 | I110: 0.01048438
A111: 4 | B111: 0.014242265 | C111: 0.032353896 | D111: 0.02951444 | E111: 0.020668896 | F111: 0.014242265 | G111: 0.011484764 | H111: 0.010147029 | I111: 0.0043753376
A112: 3 | B112: 0.0079432569 | C112: 0.029856907 | D112: 0.016460919 | E112: 0.011527545 | F112: 0.0079432569 | G112: 0.0064053316 | H112: 0.0098976859 | I112: 0.0046194177
... A116: Mean | B116: 39.411223 | C116: 39.572215 | D116: 37.544011 | E116: 35.675971 | F116: 39.411223 | G116: 39.055306 | H116: 37.424715 | I116: 39.030946
A119: Investment NPS: CheBanca! | B119: All | C119: Apr 2025 - Sep 2025 | D119: May 2025 - Oct 2025 | E119: June 2025 - Nov 2025 | F119: July 2025 - Dec 2025 | G119: August 2025 - Jan 2026 | H119: Sep 2025 - Feb 2026 | I119: Oct 2025 - Mar 2026
A120: Unweighted N | B120: 20 | C120: 5 | D120: 7 | E120: 13 | F120: 20 | G120: 25 | H120: 32 | I120: 29
A121: Promoter | B121: 0.57615748 | C121: 0.61682652 | D121: 0.4580593 | E121: 0.50200532 | F121: 0.57615748 | G121: 0.53852912 | H121: 0.58064799 | I121: 0.57369761
A122: Passive | B122: 0.33197356 | C122: 0.38317348 | D122: 0.4144829 | E122: 0.42877901 | F122: 0.33197356 | G122: 0.38921216 | H122: 0.32989254 | I122: 0.32831614
A123: Detractor | B123: 0.091868965 | C123: 0 | D123: 0.1274578 | E123: 0.069215674 | F123: 0.091868965 | G123: 0.072258721 | H123: 0.089459467 | I123: 0.09798625
A124: Extremely Likely | B124: 0.47109298 | C124: 0.39789114 | D124: 0.2954765 | E124: 0.41371509 | F124: 0.47109298 | G124: 0.37053401 | H124: 0.37948762 | I124: 0.39160333
A125: 9 | B125: 0.1050645 | C125: 0.21893537 | D125: 0.1625828 | E125: 0.088290229 | F125: 0.1050645 | G125: 0.16799511 | H125: 0.20116037 | I125: 0.18209429
A126: 8 | B126: 0.23429018 | C126: 0.18925131 | D126: 0.27047506 | E126: 0.2813852 | F126: 0.23429018 | G126: 0.18427887 | H126: 0.17443519 | I126: 0.19191219
A127: 7 | B127: 0.09768338 | C127: 0.19392217 | D127: 0.14400784 | E127: 0.14739381 | F127: 0.09768338 | G127: 0.20493329 | H127: 0.15545735 | I127: 0.13640395
A128: 6 | B128: 0.091868965 | C128: 0 | D128: 0.1274578 | E128: 0.069215674 | F128: 0.091868965 | G128: 0.072258721 | H128: 0.054813688 | I128: 0.060038226
A129: 5 | B129: 0 | C129: 0 | D129: 0 | E129: 0 | F129: 0 | G129: 0 | H129: 0 | I129: 0
A130: 4 | B130: 0 | C130: 0 | D130: 0 | E130: 0 | F130: 0 | G130: 0 | H130: 0 | I130: 0
A131: 3 | B131: 0 | C131: 0 | D131: 0 | E131: 0 | F131: 0 | G131: 0 | H131: 0.03464578 | I131: 0.037948024
...

Sheet Netherlands (quarter)
B2: Source: Global NPS tracking / Toluna | C2: Q4 - 2025
B4: Rolling NPS Data - Total
B5: ING
B6: NPS - ING (%) | C6: ='Netherlands (Month)'!#REF! -> #REF!
B7: Rank - ING | C7: =C41 -> #REF!
B8: Promoter - ING (%) | C8: ='Netherlands (Month)'!#REF! -> #REF!
B9: Passive - ING (%) | C9: ='Netherlands (Month)'!#REF! -> #REF!
B10: Detractor - ING (%) | C10: ='Netherlands (Month)'!#REF! -> #REF!
B12: Key competitors
B13: ABN AMRO
B14: NPS - ABN AMRO (%) | C14: ='Netherlands (Month)'!#REF! -> #REF!
B15: Rank - ABN AMRO | C15: =C42 -> #REF!
B16: Promoter - ABN AMRO (%) | C16: ='Netherlands (Month)'!#REF! -> #REF!
B17: Passive - ABN AMRO (%) | C17: ='Netherlands (Month)'!#REF! -> #REF!
B18: Detractor - ABN AMRO (%) | C18: ='Netherlands (Month)'!#REF! -> #REF!
B20: Rabobank
B21: NPS - Rabobank (%) | C21: ='Netherlands (Month)'!#REF! -> #REF!
B22: Rank - Rabobank | C22: =C43 -> #REF!
B23: Promoter - Rabobank (%) | C23: ='Netherlands (Month)'!#REF! -> #REF!
B24: Passive - Rabobank (%) | C24: ='Netherlands (Month)'!#REF! -> #REF!
B25: Detractor - Rabobank (%) | C25: ='Netherlands (Month)'!#REF! -> #REF!
B27: ASN Bank
B28: NPS - ASN Bank(%) | C28: ='Netherlands (Month)'!#REF! -> #REF!
B29: Rank - ASN Bank | C29: =C44 -> #REF!
B30: Promoter - ASN Bank(%) | C30: ='Netherlands (Month)'!#REF! -> #REF!
B31: Passive - ASN Bank(%) | C31: ='Netherlands (Month)'!#REF! -> #REF!
B32: Detractor - ASN Bank(%) | C32: ='Netherlands (Month)'!#REF! -> #REF!
B34: NPS - ING & Key competitors (For ranking)
B35: ING | C35: =C6 -> #REF!
B36: ABN AMRO | C36: =C14 -> #REF!
B37: Rabobank | C37: =C21 -> #REF!
B38: ASN Bank | C38: =C28 -> #REF!
B40: Ranking formule
B41: ING | C41: =RANK(C35,C$35:C$38,0) -> #REF!
B42: ABN AMRO | C42: =RANK(C36,C$35:C$38,0) -> #REF!
B43: Rabobank | C43: =RANK(C37,C$35:C$38,0) -> #REF!
B44: ASN Bank | C44: =RANK(C38,C$35:C$38,0) -> #REF!
B46: Base Size - NPS
B47: ING | C47: ='Netherlands (Month)'!#REF! -> #REF!
B48: ABN AMRO | C48: ='Netherlands (Month)'!#REF! -> #REF!
B49: Rabobank | C49: ='Netherlands (Month)'!#REF! -> #REF!
B50: ASN Bank | C50: ='Netherlands (Month)'!#REF! -> #REF!

Sheet Netherlands (Month)
B2: Source: Global NPS tracking / Toluna | C2: January - 2026 (6 months rolling) | D2: February - 2026 (6 months rolling) | E2: March - 2026 (6 months rolling)
B4: NPS total
B5: ING | C5: NPS | D5: NPS | E5: NPS
C6: ='Netherlands Crunch Outputs'!G21 -> 22.590758 | D6: ='Netherlands Crunch Outputs'!H21 -> 20.112431 | E6: ='Netherlands Crunch Outputs'!I21 -> 21.139988
B7: Promoter | C7: ='Netherlands Crunch Outputs'!G7 -> 0.3897262 | D7: ='Netherlands Crunch Outputs'!H7 -> 0.36822405 | E7: ='Netherlands Crunch Outputs'!I7 -> 0.37409157
B8: Passive | C8: ='Netherlands Crunch Outputs'!G8 -> 0.44645519 | D8: ='Netherlands Crunch Outputs'!H8 -> 0.4646762 | E8: ='Netherlands Crunch Outputs'!I8 -> 0.46321675
B9: Detractor | C9: ='Netherlands Crunch Outputs'!G9 -> 0.16381861 | D9: ='Netherlands Crunch Outputs'!H9 -> 0.16709974 | E9: ='Netherlands Crunch Outputs'!I9 -> 0.16269168
B10: Extremely likely | C10: ='Netherlands Crunch Outputs'!G10 -> 0.20225298 | D10: ='Netherlands Crunch Outputs'!H10 -> 0.18801022 | E10: ='Netherlands Crunch Outputs'!I10 -> 0.19582274
B11: 9 | C11: ='Netherlands Crunch Outputs'!G11 -> 0.18747321 | D11: ='Netherlands Crunch Outputs'!H11 -> 0.18021383 | E11: ='Netherlands Crunch Outputs'!I11 -> 0.17826883
B12: 8 | C12: ='Netherlands Crunch Outputs'!G12 -> 0.27970927 | D12: ='Netherlands Crunch Outputs'!H12 -> 0.28296045 | E12: ='Netherlands Crunch Outputs'!I12 -> 0.28457702
B13: 7 | C13: ='Netherlands Crunch Outputs'!G13 -> 0.16674592 | D13: ='Netherlands Crunch Outputs'!H13 -> 0.18171576 | E13: ='Netherlands Crunch Outputs'!I13 -> 0.17863973
B14: 6 | C14: ='Netherlands Crunch Outputs'!G14 -> 0.076006514 | D14: ='Netherlands Crunch Outputs'!H14 -> 0.080787445 | E14: ='Netherlands Crunch Outputs'!I14 -> 0.074846122
B15: 5 | C15: ='Netherlands Crunch Outputs'!G15 -> 0.046988703 | D15: ='Netherlands Crunch Outputs'!H15 -> 0.046161635 | E15: ='Netherlands Crunch Outputs'!I15 -> 0.049678974
B16: 4 | C16: ='Netherlands Crunch Outputs'!G16 -> 0.017889077 | D16: ='Netherlands Crunch Outputs'!H16 -> 0.020193942 | E16: ='Netherlands Crunch Outputs'!I16 -> 0.016538513
B17: 3 | C17: ='Netherlands Crunch Outputs'!G17 -> 0.012113646 | D17: ='Netherlands Crunch Outputs'!H17 -> 0.010540912 | E17: ='Netherlands Crunch Outputs'!I17 -> 0.011016511
B18: 2 | C18: ='Netherlands Crunch Outputs'!G18 -> 0 | D18: ='Netherlands Crunch Outputs'!H18 -> 0 | E18: ='Netherlands Crunch Outputs'!I18 -> 0
B19: 1 | C19: ='Netherlands Crunch Outputs'!G19 -> 0 | D19: ='Netherlands Crunch Outputs'!H19 -> 0 | E19: ='Netherlands Crunch Outputs'!I19 -> 0
B20: Extremely Unlikely | C20: ='Netherlands Crunch Outputs'!G20 -> 0.010820674 | D20: ='Netherlands Crunch Outputs'!H20 -> 0.0094158082 | E20: ='Netherlands Crunch Outputs'!I20 -> 0.010611565
B21: n | C21: ='Netherlands Crunch Outputs'!G6 -> 260 | D21: ='Netherlands Crunch Outputs'!H6 -> 296 | E21: ='Netherlands Crunch Outputs'!I6 -> 272
B23: ABN AMRO | C23: NPS | D23: NPS | E23: NPS
C24: ='Netherlands Crunch Outputs'!G59 -> 13.164507 | D24: ='Netherlands Crunch Outputs'!H59 -> 15.574583 | E24: ='Netherlands Crunch Outputs'!I59 -> 13.836482
B25: Promoter | C25: ='Netherlands Crunch Outputs'!G45 -> 0.32986538 | D25: ='Netherlands Crunch Outputs'!H45 -> 0.3310277 | E25: ='Netherlands Crunch Outputs'!I45 -> 0.30247024
B26: Passive | C26: ='Netherlands Crunch Outputs'!G46 -> 0.47191431 | D26: ='Netherlands Crunch Outputs'!H46 -> 0.49369042 | E26: ='Netherlands Crunch Outputs'!I46 -> 0.53342434
B27: Detractor | C27: ='Netherlands Crunch Outputs'!G47 -> 0.19822031 | D27: ='Netherlands Crunch Outputs'!H47 -> 0.17528187 | E27: ='Netherlands Crunch Outputs'!I47 -> 0.16410542
B28: Extremely likely | C28: ='Netherlands Crunch Outputs'!G48 -> 0.13368885 | D28: ='Netherlands Crunch Outputs'!H48 -> 0.14536701 | E28: ='Netherlands Crunch Outputs'!I48 -> 0.13463556
B29: 9 | C29: ='Netherlands Crunch Outputs'!G49 -> 0.19617654 | D29: ='Netherlands Crunch Outputs'!H49 -> 0.18566069 | E29: ='Netherlands Crunch Outputs'!I49 -> 0.16783467
B30: 8 | C30: ='Netherlands Crunch Outputs'!G50 -> 0.28171163 | D30: ='Netherlands Crunch Outputs'!H50 -> 0.29862784 | E30: ='Netherlands Crunch Outputs'!I50 -> 0.34262357
B31: 7 | C31: ='Netherlands Crunch Outputs'!G51 -> 0.19020268 | D31: ='Netherlands Crunch Outputs'!H51 -> 0.19506258 | E31: ='Netherlands Crunch Outputs'!I51 -> 0.19080077
B32: 6 | C32: ='Netherlands Crunch Outputs'!G52 -> 0.054889749 | D32: ='Netherlands Crunch Outputs'!H52 -> 0.051233776 | E32: ='Netherlands Crunch Outputs'!I52 -> 0.055336056
B33: 5 | C33: ='Netherlands Crunch Outputs'!G53 -> 0.074821789 | D33: ='Netherlands Crunch Outputs'!H53 -> 0.062053654 | E33: ='Netherlands Crunch Outputs'!I53 -> 0.054615473
B34: 4 | C34: ='Netherlands Crunch Outputs'!G54 -> 0.0086520677 | D34: ='Netherlands Crunch Outputs'!H54 -> 0.0071756158 | E34: ='Netherlands Crunch Outputs'!I54 -> 0.0071984599
B35: 3 | C35: ='Netherlands Crunch Outputs'!G55 -> 0.011784821 | D35: ='Netherlands Crunch Outputs'!H55 -> 0.0097737735 | E35: ='Netherlands Crunch Outputs'!I55 -> 0.0028634136
B36: 2 | C36: ='Netherlands Crunch Outputs'!G56 -> 0.010785865 | D36: ='Netherlands Crunch Outputs'!H56 -> 0.01412179 | E36: ='Netherlands Crunch Outputs'!I56 -> 0.014166748
B37: 1 | C37: ='Netherlands Crunch Outputs'!G57 -> 0.0087630112 | D37: ='Netherlands Crunch Outputs'!H57 -> 0.0072676272 | E37: ='Netherlands Crunch Outputs'!I57 -> 0.0097842725
B38: Extremely Unlikely | C38: ='Netherlands Crunch Outputs'!G58 -> 0.028523007 | D38: ='Netherlands Crunch Outputs'!H58 -> 0.023655633 | E38: ='Netherlands Crunch Outputs'!I58 -> 0.020140996
B39: n | C39: ='Netherlands Crunch Outputs'!G44 -> 168 | D39: ='Netherlands Crunch Outputs'!H44 -> 203 | E39: ='Netherlands Crunch Outputs'!I44 -> 199
B41: Rabobank | C41: NPS | D41: NPS | E41: NPS
C42: ='Netherlands Crunch Outputs'!G40 -> 10.872639 | D42: ='Netherlands Crunch Outputs'!H40 -> 9.9592566 | E42: ='Netherlands Crunch Outputs'!I40 -> 9.2983737
B43: Promoter | C43: ='Netherlands Crunch Outputs'!G26 -> 0.268365 | D43: ='Netherlands Crunch Outputs'!H26 -> 0.26549101 | E43: ='Netherlands Crunch Outputs'!I26 -> 0.26681679
B44: Passive | C44: ='Netherlands Crunch Outputs'!G27 -> 0.57199639 | D44: ='Netherlands Crunch Outputs'!H27 -> 0.56861054 | E44: ='Netherlands Crunch Outputs'!I27 -> 0.55935015
B45: Detractor | C45: ='Netherlands Crunch Outputs'!G28 -> 0.15963861 | D45: ='Netherlands Crunch Outputs'!H28 -> 0.16589845 | E45: ='Netherlands Crunch Outputs'!I28 -> 0.17383305
B46: Extremely likely | C46: ='Netherlands Crunch Outputs'!G29 -> 0.12409961 | D46: ='Netherlands Crunch Outputs'!H29 -> 0.12392893 | E46: ='Netherlands Crunch Outputs'!I29 -> 0.13236287
B47: 9 | C47: ='Netherlands Crunch Outputs'!G30 -> 0.14426539 | D47: ='Netherlands Crunch Outputs'!H30 -> 0.14156208 | E47: ='Netherlands Crunch Outputs'!I30 -> 0.13445392
B48: 8 | C48: ='Netherlands Crunch Outputs'!G31 -> 0.37426643 | D48: ='Netherlands Crunch Outputs'!H31 -> 0.36865616 | E48: ='Netherlands Crunch Outputs'!I31 -> 0.32438798
B49: 7 | C49: ='Netherlands Crunch Outputs'!G32 -> 0.19772996 | D49: ='Netherlands Crunch Outputs'!H32 -> 0.19995438 | E49: ='Netherlands Crunch Outputs'!I32 -> 0.23496218
B50: 6 | C50: ='Netherlands Crunch Outputs'!G33 -> 0.086551395 | D50: ='Netherlands Crunch Outputs'!H33 -> 0.08972469 | E50: ='Netherlands Crunch Outputs'!I33 -> 0.088750446
B51: 5 | C51: ='Netherlands Crunch Outputs'!G34 -> 0.048033655 | D51: ='Netherlands Crunch Outputs'!H34 -> 0.054553648 | E51: ='Netherlands Crunch Outputs'!I34 -> 0.054560661
B52: 4 | C52: ='Netherlands Crunch Outputs'!G35 -> 0 | D52: ='Netherlands Crunch Outputs'!H35 -> 0 | E52: ='Netherlands Crunch Outputs'!I35 -> 0.0037652538
B53: 3 | C53: ='Netherlands Crunch Outputs'!G36 -> 0.0043303733 | D53: ='Netherlands Crunch Outputs'!H36 -> 0.0037369198 | E53: ='Netherlands Crunch Outputs'!I36 -> 0.0040077291
B54: 2 | C54: ='Netherlands Crunch Outputs'!G37 -> 0 | D54: ='Netherlands Crunch Outputs'!H37 -> 0 | E54: ='Netherlands Crunch Outputs'!I37 -> 0
B55: 1 | C55: ='Netherlands Crunch Outputs'!G38 -> 0.0046018183 | D55: ='Netherlands Crunch Outputs'!H38 -> 0.0039711648 | E55: ='Netherlands Crunch Outputs'!I38 -> 0
B56: Extremely Unlikely | C56: ='Netherlands Crunch Outputs'!G39 -> 0.016121367 | D56: ='Netherlands Crunch Outputs'!H39 -> 0.013912023 | E56: ='Netherlands Crunch Outputs'!I39 -> 0.022748965
B57: n | C57: ='Netherlands Crunch Outputs'!G25 -> 193 | D57: ='Netherlands Crunch Outputs'!H25 -> 223 | E57: ='Netherlands Crunch Outputs'!I25 -> 213
B59: ASN Bank | C59: NPS | D59: NPS | E59: NPS
C60: Low N | D60: Low N | E60: Low N
B61: Promoter | C61: Low N | D61: Low N | E61: Low N
B62: Passive | C62: Low N | D62: Low N | E62: Low N
B63: Detractor | C63: Low N | D63: Low N | E63: Low N
B64: Extremely likely | C64: Low N | D64: Low N | E64: Low N
B65: 9 | C65: Low N | D65: Low N | E65: Low N
B66: 8 | C66: Low N | D66: Low N | E66: Low N
B67: 7 | C67: Low N | D67: Low N | E67: Low N
B68: 6 | C68: Low N | D68: Low N | E68: Low N
B69: 5 | C69: Low N | D69: Low N | E69: Low N
B70: 4 | C70: Low N | D70: Low N | E70: Low N
B71: 3 | C71: Low N | D71: Low N | E71: Low N
B72: 2 | C72: Low N | D72: Low N | E72: Low N
B73: 1 | C73: Low N | D73: Low N | E73: Low N
B74: Extremely Unlikely | C74: Low N | D74: Low N | E74: Low N
B75: n | C75: ='Netherlands Crunch Outputs'!G82 -> 50 | D75: ='Netherlands Crunch Outputs'!H82 -> 66 | E75: ='Netherlands Crunch Outputs'!I82 -> 69
B77: SNS Bank | C77: NPS | D77: NPS | E77: NPS
C78: Low N | D78: Low N
B79: Promoter | C79: Low N | D79: Low N
B80: Passive | C80: Low N | D80: Low N
B81: Detractor | C81: Low N | D81: Low N
B82: Extremely likely | C82: Low N | D82: Low N
B83: 9 | C83: Low N | D83: Low N
B84: 8 | C84: Low N | D84: Low N
B85: 7 | C85: Low N | D85: Low N
B86: 6 | C86: Low N | D86: Low N
B87: 5 | C87: Low N | D87: Low N
B88: 4 | C88: Low N | D88: Low N
B89: 3 | C89: Low N | D89: Low N
B90: 2 | C90: Low N | D90: Low N
B91: 1 | C91: Low N | D91: Low N
B92: Extremely Unlikely | C92: Low N | D92: Low N
B93: n | C93: ='Netherlands Crunch Outputs'!G63 -> 9 | D93: ='Netherlands Crunch Outputs'!H63 -> 9
B95: Bunq | C95: NPS | D95: NPS | E95: NPS
C96: Low N | D96: Low N | E96: Low N
B97: Promoter | C97: Low N | D97: Low N | E97: Low N
B98: Passive | C98: Low N | D98: Low N | E98: Low N
B99: Detractor | C99: Low N | D99: Low N | E99: Low N
B100: Extremely likely | C100: Low N | D100: Low N | E100: Low N
B101: 9 | C101: Low N | D101: Low N | E101: Low N
B102: 8 | C102: Low N | D102: Low N | E102: Low N
B103: 7 | C103: Low N | D103: Low N | E103: Low N
B104: 6 | C104: Low N | D104: Low N | E104: Low N
B105: 5 | C105: Low N | D105: Low N | E105: Low N
B106: 4 | C106: Low N | D106: Low N | E106: Low N
B107: 3 | C107: Low N | D107: Low N | E107: Low N
...

Sheet Netherlands Crunch Outputs
A1: P97511: ING BAM Netherlands
A2: Investment NPS
A3: Based on your knowledge and experience with the investment services offered by the brand(s) below, how likely is it that you would recommend their investment services to a friend, family member or colleague?
A5: Investment NPS: ING | B5: All | C5: Apr 2025 - Sep 2025 | D5: May 2025 - Oct 2025 | E5: June 2025 - Nov 2025 | F5: July 2025 - Dec 2025 | G5: August 2025 - Jan 2026 | H5: Sep 2025 - Feb 2026 | I5: Oct 2025 - Mar 2026
A6: Unweighted N | B6: 197 | C6: 54 | D6: 97 | E6: 150 | F6: 197 | G6: 260 | H6: 296 | I6: 272
A7: Promoter | B7: 0.37017549 | C7: 0.33548463 | D7: 0.30479964 | E7: 0.30352546 | F7: 0.37017549 | G7: 0.3897262 | H7: 0.36822405 | I7: 0.37409157
A8: Passive | B8: 0.44653116 | C8: 0.48427462 | D8: 0.52344791 | E8: 0.50061809 | F8: 0.44653116 | G8: 0.44645519 | H8: 0.4646762 | I8: 0.46321675
A9: Detractor | B9: 0.18329335 | C9: 0.18024076 | D9: 0.17175245 | E9: 0.19585645 | F9: 0.18329335 | G9: 0.16381861 | H9: 0.16709974 | I9: 0.16269168
A10: Extremely Likely | B10: 0.24526365 | C10: 0.18984516 | D10: 0.16118481 | E10: 0.17961286 | F10: 0.24526365 | G10: 0.20225298 | H10: 0.18801022 | I10: 0.19582274
A11: 9 | B11: 0.12491185 | C11: 0.14563946 | D11: 0.14361483 | E11: 0.12391259 | F11: 0.12491185 | G11: 0.18747321 | H11: 0.18021383 | I11: 0.17826883
A12: 8 | B12: 0.28851919 | C12: 0.26900286 | D12: 0.32338547 | E12: 0.31270197 | F12: 0.28851919 | G12: 0.27970927 | H12: 0.28296045 | I12: 0.28457702
A13: 7 | B13: 0.15801197 | C13: 0.21527176 | D13: 0.20006245 | E13: 0.18791612 | F13: 0.15801197 | G13: 0.16674592 | H13: 0.18171576 | I13: 0.17863973
A14: 6 | B14: 0.082811172 | C14: 0.096762038 | D14: 0.088733873 | E14: 0.095912095 | F14: 0.082811172 | G14: 0.076006514 | H14: 0.080787445 | I14: 0.074846122
A15: 5 | B15: 0.051841761 | C15: 0 | D15: 0.027341422 | E15: 0.046284468 | F15: 0.051841761 | G15: 0.046988703 | H15: 0.046161635 | I15: 0.049678974
A16: 4 | B16: 0.018884368 | C16: 0.027826239 | D16: 0.014918087 | E16: 0.018580996 | F16: 0.018884368 | G16: 0.017889077 | H16: 0.020193942 | I16: 0.016538513
A17: 3 | B17: 0.015716806 | C17: 0.027826239 | D17: 0.025840978 | E17: 0.016497895 | F17: 0.015716806 | G17: 0.012113646 | H17: 0.010540912 | I17: 0.011016511
... A21: Mean | B21: 18.688214 | C21: 15.524387 | D21: 13.304719 | E21: 10.766901 | F21: 18.688214 | G21: 22.590758 | H21: 20.112431 | I21: 21.139988
A24: Investment NPS: Rabobank | B24: All | C24: Apr 2025 - Sep 2025 | D24: May 2025 - Oct 2025 | E24: June 2025 - Nov 2025 | F24: July 2025 - Dec 2025 | G24: August 2025 - Jan 2026 | H24: Sep 2025 - Feb 2026 | I24: Oct 2025 - Mar 2026
A25: Unweighted N | B25: 157 | C25: 46 | D25: 84 | E25: 115 | F25: 157 | G25: 193 | H25: 223 | I25: 213
A26: Promoter | B26: 0.27637912 | C26: 0.32182516 | D26: 0.31926334 | E26: 0.25963715 | F26: 0.27637912 | G26: 0.268365 | H26: 0.26549101 | I26: 0.26681679
A27: Passive | B27: 0.57296555 | C27: 0.55650898 | D27: 0.53240362 | E27: 0.56476629 | F27: 0.57296555 | G27: 0.57199639 | H27: 0.56861054 | I27: 0.55935015
A28: Detractor | B28: 0.15065533 | C28: 0.12166586 | D28: 0.14833304 | E28: 0.17559656 | F28: 0.15065533 | G28: 0.15963861 | H28: 0.16589845 | I28: 0.17383305
A29: Extremely Likely | B29: 0.12701219 | C29: 0.11341972 | D29: 0.1436833 | E29: 0.11426664 | F29: 0.12701219 | G29: 0.12409961 | H29: 0.12392893 | I29: 0.13236287
A30: 9 | B30: 0.14936693 | C30: 0.20840544 | D30: 0.17558003 | E30: 0.14537052 | F30: 0.14936693 | G30: 0.14426539 | H30: 0.14156208 | I30: 0.13445392
A31: 8 | B31: 0.3474166 | C31: 0.42903662 | D31: 0.32741658 | E31: 0.34990237 | F31: 0.3474166 | G31: 0.37426643 | H31: 0.36865616 | I31: 0.32438798
A32: 7 | B32: 0.22554895 | C32: 0.12747236 | D32: 0.20498705 | E32: 0.21486392 | F32: 0.22554895 | G32: 0.19772996 | H32: 0.19995438 | I32: 0.23496218
A33: 6 | B33: 0.084899139 | C33: 0.068943646 | D33: 0.084082688 | E33: 0.09916664 | F33: 0.084899139 | G33: 0.086551395 | H33: 0.08972469 | I33: 0.088750446
A34: 5 | B34: 0.049684605 | C34: 0.034599995 | D34: 0.034123188 | E34: 0.054624153 | F34: 0.049684605 | G34: 0.048033655 | H34: 0.054553648 | I34: 0.054560661
A35: 4 | B35: 0 | C35: 0 | D35: 0 | E35: 0 | F35: 0 | G35: 0 | H35: 0 | I35: 0.0037652538
A36: 3 | B36: 0.0052475506 | C36: 0 | D36: 0.0098368508 | E36: 0.007119822 | F36: 0.0052475506 | G36: 0.0043303733 | H36: 0.0037369198 | I36: 0.0040077291
... A40: Mean | B40: 12.572378 | C40: 20.01593 | D40: 17.09303 | E40: 8.4040594 | F40: 12.572378 | G40: 10.872639 | H40: 9.9592566 | I40: 9.2983737
A43: Investment NPS: ABN AMRO | B43: All | C43: Apr 2025 - Sep 2025 | D43: May 2025 - Oct 2025 | E43: June 2025 - Nov 2025 | F43: July 2025 - Dec 2025 | G43: August 2025 - Jan 2026 | H43: Sep 2025 - Feb 2026 | I43: Oct 2025 - Mar 2026
A44: Unweighted N | B44: 133 | C44: 38 | D44: 67 | E44: 98 | F44: 133 | G44: 168 | H44: 203 | I44: 199
A45: Promoter | B45: 0.30932401 | C45: 0.40452732 | D45: 0.3217627 | E45: 0.33513915 | F45: 0.30932401 | G45: 0.32986538 | H45: 0.3310277 | I45: 0.30247024
A46: Passive | B46: 0.46657558 | C46: 0.39353783 | D46: 0.47341288 | E46: 0.44395476 | F46: 0.46657558 | G46: 0.47191431 | H46: 0.49369042 | I46: 0.53342434
A47: Detractor | B47: 0.22410041 | C47: 0.20193485 | D47: 0.20482443 | E47: 0.22090608 | F47: 0.22410041 | G47: 0.19822031 | H47: 0.17528187 | I47: 0.16410542
A48: Extremely Likely | B48: 0.1273606 | C48: 0.16506275 | D48: 0.13737368 | E48: 0.09395009 | F48: 0.1273606 | G48: 0.13368885 | H48: 0.14536701 | I48: 0.13463556
A49: 9 | B49: 0.18196342 | C49: 0.23946457 | D49: 0.18438901 | E49: 0.24118906 | F49: 0.18196342 | G49: 0.19617654 | H49: 0.18566069 | I49: 0.16783467
A50: 8 | B50: 0.26031272 | C50: 0.27477716 | D50: 0.33054685 | E50: 0.29197632 | F50: 0.26031272 | G50: 0.28171163 | H50: 0.29862784 | I50: 0.34262357
A51: 7 | B51: 0.20626286 | C51: 0.11876067 | D51: 0.14286603 | E51: 0.15197845 | F51: 0.20626286 | G51: 0.19020268 | H51: 0.19506258 | I51: 0.19080077
A52: 6 | B52: 0.053803985 | C52: 0.026699582 | D52: 0.029621608 | E52: 0.06390683 | F52: 0.053803985 | G52: 0.054889749 | H52: 0.051233776 | I52: 0.055336056
A53: 5 | B53: 0.083409474 | C53: 0.080429375 | D53: 0.068988833 | E53: 0.084359329 | F53: 0.083409474 | G53: 0.074821789 | H53: 0.062053654 | I53: 0.054615473
A54: 4 | B54: 0.010973073 | C54: 0 | D54: 0.021840403 | E54: 0.014936688 | F54: 0.010973073 | G54: 0.0086520677 | H54: 0.0071756158 | I54: 0.0071984599
A55: 3 | B55: 0.01494622 | C55: 0.039596233 | D55: 0.021060702 | E55: 0.014403449 | F55: 0.01494622 | G55: 0.011784821 | H55: 0.0097737735 | I55: 0.0028634136
... A59: Mean | B59: 8.5223604 | C59: 20.259246 | D59: 11.693827 | E59: 11.423307 | F59: 8.5223604 | G59: 13.164507 | H59: 15.574583 | I59: 13.836482
A62: Investment NPS: SNS Bank | B62: All | C62: Apr 2025 - Sep 2025 | D62: May 2025 - Oct 2025 | E62: June 2025 - Nov 2025 | F62: July 2025 - Dec 2025 | G62: August 2025 - Jan 2026 | H62: Sep 2025 - Feb 2026 | I62: Oct 2025 - Mar 2026
A63: Unweighted N | B63: 9 | C63: 5 | D63: 9 | E63: 9 | F63: 9 | G63: 9 | H63: 9 | I63: 4
A64: Promoter | B64: 0.26062452 | C64: 0.21291728 | D64: 0.26062452 | E64: 0.26062452 | F64: 0.26062452 | G64: 0.26062452 | H64: 0.26062452 | I64: 0.30659989
A65: Passive | B65: 0.49650479 | C65: 0.78708272 | D65: 0.49650479 | E65: 0.49650479 | F65: 0.49650479 | G65: 0.49650479 | H65: 0.49650479 | I65: 0.21647546
A66: Detractor | B66: 0.24287069 | C66: 0 | D66: 0.24287069 | E66: 0.24287069 | F66: 0.24287069 | G66: 0.24287069 | H66: 0.24287069 | I66: 0.47692465
A67: Extremely Likely | B67: 0 | C67: 0 | D67: 0 | E67: 0 | F67: 0 | G67: 0 | H67: 0 | I67: 0
A68: 9 | B68: 0.26062452 | C68: 0.21291728 | D68: 0.26062452 | E68: 0.26062452 | F68: 0.26062452 | G68: 0.26062452 | H68: 0.26062452 | I68: 0.30659989
A69: 8 | B69: 0.23819314 | C69: 0.48535892 | D69: 0.23819314 | E69: 0.23819314 | F69: 0.23819314 | G69: 0.23819314 | H69: 0.23819314 | I69: 0
A70: 7 | B70: 0.25831165 | C70: 0.30172379 | D70: 0.25831165 | E70: 0.25831165 | F70: 0.25831165 | G70: 0.25831165 | H70: 0.25831165 | I70: 0.21647546
A71: 6 | B71: 0.091209965 | C71: 0 | D71: 0.091209965 | E71: 0.091209965 | F71: 0.091209965 | G71: 0.091209965 | H71: 0.091209965 | I71: 0.17910881
A72: 5 | B72: 0.15166072 | C72: 0 | D72: 0.15166072 | E72: 0.15166072 | F72: 0.15166072 | G72: 0.15166072 | H72: 0.15166072 | I72: 0.29781584
A73: 4 | B73: 0 | C73: 0 | D73: 0 | E73: 0 | F73: 0 | G73: 0 | H73: 0 | I73: 0
A74: 3 | B74: 0 | C74: 0 | D74: 0 | E74: 0 | F74: 0 | G74: 0 | H74: 0 | I74: 0
... A78: Mean | B78: 1.7753836 | C78: 21.291728 | D78: 1.7753836 | E78: 1.7753836 | F78: 1.7753836 | G78: 1.7753836 | H78: 1.7753836 | I78: -17.032476
A81: Investment NPS: ASN Bank | B81: All | C81: Apr 2025 - Sep 2025 | D81: May 2025 - Oct 2025 | E81: June 2025 - Nov 2025 | F81: July 2025 - Dec 2025 | G81: August 2025 - Jan 2026 | H81: Sep 2025 - Feb 2026 | I81: Oct 2025 - Mar 2026
A82: Unweighted N | B82: 39 | C82: 17 | D82: 23 | E82: 32 | F82: 39 | G82: 50 | H82: 66 | I82: 69
A83: Promoter | B83: 0.21740906 | C83: 0.32254572 | D83: 0.27742786 | E83: 0.19985288 | F83: 0.21740906 | G83: 0.20447409 | H83: 0.19815287 | I83: 0.15952968
A84: Passive | B84: 0.41537209 | C84: 0.36799518 | D84: 0.45913518 | E84: 0.45316936 | F84: 0.41537209 | G84: 0.39989644 | H84: 0.42202055 | I84: 0.51528513
A85: Detractor | B85: 0.36721885 | C85: 0.3094591 | D85: 0.26343697 | E85: 0.34697776 | F85: 0.36721885 | G85: 0.39562946 | H85: 0.37982658 | I85: 0.3251852
A86: Extremely Likely | B86: 0.13071223 | C86: 0.19263355 | D86: 0.18853934 | E86: 0.13581956 | F86: 0.13071223 | G86: 0.1024705 | H86: 0.090770385 | I86: 0.04223596
A87: 9 | B87: 0.086696827 | C87: 0.12991217 | D87: 0.088888517 | E87: 0.064033317 | F87: 0.086696827 | G87: 0.10200359 | H87: 0.10738249 | I87: 0.11729372
A88: 8 | B88: 0.28939989 | C88: 0.18202587 | D88: 0.27670797 | E88: 0.29427746 | F88: 0.28939989 | G88: 0.28614718 | H88: 0.28655774 | I88: 0.34339144
A89: 7 | B89: 0.1259722 | C89: 0.18596931 | D89: 0.18242721 | E89: 0.1588919 | F89: 0.1259722 | G89: 0.11374926 | H89: 0.1354628 | I89: 0.17189369
A90: 6 | B90: 0.17307627 | C90: 0.052058177 | D90: 0.035619251 | E90: 0.18286293 | F90: 0.17307627 | G90: 0.15283934 | H90: 0.14669227 | I90: 0.12709192
A91: 5 | B91: 0.16870609 | C91: 0.19230883 | D91: 0.1832804 | E91: 0.13203114 | F91: 0.16870609 | G91: 0.18884959 | H91: 0.17715353 | I91: 0.14310935
A92: 4 | B92: 0.025436497 | C92: 0.065092089 | D92: 0.044537315 | E92: 0.032083694 | F92: 0.025436497 | G92: 0.053940529 | H92: 0.042199045 | I92: 0.025187112
A93: 3 | B93: 0 | C93: 0 | D93: 0 | E93: 0 | F93: 0 | G93: 0 | H93: 0.013781735 | I93: 0.013050221
... A97: Mean | B97: -14.980979 | C97: 1.3086624 | D97: 1.399089 | E97: -14.712489 | F97: -14.980979 | G97: -19.115537 | H97: -18.167371 | I97: -16.565552
A100: Investment NPS: Triodos Bank | B100: All | C100: Apr 2025 - Sep 2025 | D100: May 2025 - Oct 2025 | E100: June 2025 - Nov 2025 | F100: July 2025 - Dec 2025 | G100: August 2025 - Jan 2026 | H100: Sep 2025 - Feb 2026 | I100: Oct 2025 - Mar 2026
A101: Unweighted N | B101: 18 | C101: 5 | D101: 9 | E101: 13 | F101: 18 | G101: 21 | H101: 23 | I101: 25
A102: Promoter | B102: 0.22340835 | C102: 0.13183756 | D102: 0.30953979 | E102: 0.25235073 | F102: 0.22340835 | G102: 0.25672569 | H102: 0.2610607 | I102: 0.30661514
A103: Passive | B103: 0.42207454 | C103: 0.58708422 | D103: 0.53472868 | E103: 0.50555202 | F103: 0.42207454 | G103: 0.40207925 | H103: 0.43193954 | I103: 0.33638969
A104: Detractor | B104: 0.35451711 | C104: 0.28107821 | D104: 0.15573154 | E104: 0.24209726 | F104: 0.35451711 | G104: 0.34119506 | H104: 0.30699976 | I104: 0.35699517
A105: Extremely Likely | B105: 0.034419902 | C105: 0 | D105: 0 | E105: 0.046131563 | F105: 0.034419902 | G105: 0.029268677 | H105: 0.056399924 | I105: 0.11269463
A106: 9 | B106: 0.18898845 | C106: 0.13183756 | D106: 0.30953979 | E106: 0.20621916 | F106: 0.18898845 | G106: 0.22745701 | H106: 0.20466078 | I106: 0.1939205
A107: 8 | B107: 0.24664128 | C107: 0.32812747 | D107: 0.18179921 | E107: 0.27042612 | F107: 0.24664128 | G107: 0.25290104 | H107: 0.22755475 | I107: 0.15160234
A108: 7 | B108: 0.17543326 | C108: 0.25895675 | D108: 0.35292947 | E108: 0.2351259 | F108: 0.17543326 | G108: 0.14917821 | H108: 0.20438479 | I108: 0.18478735
A109: 6 | B109: 0.22191963 | C109: 0.28107821 | D109: 0.15573154 | E109: 0.24209726 | F109: 0.22191963 | G109: 0.18870751 | H109: 0.16979483 | I109: 0.13908321
A110: 5 | B110: 0 | C110: 0 | D110: 0 | E110: 0 | F110: 0 | G110: 0 | H110: 0 | I110: 0
A111: 4 | B111: 0.068744774 | C111: 0 | D111: 0 | E111: 0 | F111: 0.068744774 | G111: 0.098190939 | H111: 0.088350031 | I111: 0.084551961
A112: 3 | B112: 0 | C112: 0 | D112: 0 | E112: 0 | F112: 0 | G112: 0 | H112: 0 | I112: 0.03667837
... A116: Mean | B116: -13.110876 | C116: -14.924065 | D116: 15.380825 | E116: 1.025347 | F116: -13.110876 | G116: -8.4469376 | H116: -4.5939055 | I116: -5.0380034
A119: Investment NPS: KNAB | B119: All | C119: Apr 2025 - Sep 2025 | D119: May 2025 - Oct 2025 | E119: June 2025 - Nov 2025 | F119: July 2025 - Dec 2025 | G119: August 2025 - Jan 2026 | H119: Sep 2025 - Feb 2026 | I119: Oct 2025 - Mar 2026
A120: Unweighted N | B120: 16 | C120: 6 | D120: 8 | E120: 13 | F120: 16 | G120: 20 | H120: 25 | I120: 24
A121: Promoter | B121: 0.1410719 | C121: 0.19716212 | D121: 0.15057135 | E121: 0.093463308 | F121: 0.1410719 | G121: 0.1229019 | H121: 0.17175758 | I121: 0.23625665
A122: Passive | B122: 0.73732654 | C122: 0.62895634 | D122: 0.71663652 | E122: 0.75951334 | F122: 0.73732654 | G122: 0.64235921 | H122: 0.60439672 | I122: 0.57535585
A123: Detractor | B123: 0.12160156 | C123: 0.17388153 | D123: 0.13279213 | E123: 0.14702336 | F123: 0.12160156 | G123: 0.23473889 | H123: 0.2238457 | I123: 0.1883875
A124: Extremely Likely | B124: 0.077302577 | C124: 0.19716212 | D124: 0.15057135 | E124: 0.093463308 | F124: 0.077302577 | G124: 0.06734604 | H124: 0.084535305 | I124: 0.032184921
A125: 9 | B125: 0.063769322 | C125: 0 | D125: 0 | E125: 0 | F125: 0.063769322 | G125: 0.055555862 | H125: 0.087222277 | I125: 0.20407173
A126: 8 | B126: 0.32789077 | C126: 0.24107005 | D126: 0.18410353 | E126: 0.2644817 | F126: 0.32789077 | G126: 0.28565858 | H126: 0.31570979 | I126: 0.3272083
A127: 7 | B127: 0.40943577 | C127: 0.38788629 | D127: 0.53253299 | E127: 0.49503164 | F127: 0.40943577 | G127: 0.35670063 | H127: 0.28868693 | I127: 0.24814755
A128: 6 | B128: 0.12160156 | C128: 0.17388153 | D128: 0.13279213 | E128: 0.14702336 | F128: 0.12160156 | G128: 0.19147104 | H128: 0.18882792 | I128: 0.15085743
A129: 5 | B129: 0 | C129: 0 | D129: 0 | E129: 0 | F129: 0 | G129: 0.043267849 | H129: 0.035017776 | I129: 0.037530072
A130: 4 | B130: 0 | C130: 0 | D130: 0 | E130: 0 | F130: 0 | G130: 0 | H130: 0 | I130: 0
A131: 3 | B131: 0 | C131: 0 | D131: 0 | E131: 0 | F131: 0 | G131: 0 | H131: 0 | I131: 0
...

Sheet Poland (quarter)
B2: Source: Global NPS tracking / Toluna | C2: Q4 - 2025
B4: Rolling NPS Data - Total
B5: ING
B6: NPS - ING (%) | C6: ='Poland (Month)'!#REF! -> #REF!
B7: Rank - ING | C7: =C57 -> #REF!
B8: Promoter - ING (%) | C8: ='Poland (Month)'!#REF! -> #REF!
B9: Passive - ING (%) | C9: ='Poland (Month)'!#REF! -> #REF!
B10: Detractor - ING (%) | C10: ='Poland (Month)'!#REF! -> #REF!
B12: Key competitors
B13: Velo bank (previously Getin Bank)
B14: NPS - Velo bank (previously Getin Bank) (%) | C14: ='Poland (Month)'!#REF! -> #REF!
B15: Rank - Velo bank (previously Getin Bank) | C15: =C58 -> #REF!
B16: Promoter - Velo bank (previously Getin Bank)(%) | C16: ='Poland (Month)'!#REF! -> #REF!
B17: Passive - Velo bank (previously Getin Bank) (%) | C17: ='Poland (Month)'!#REF! -> #REF!
B18: Detractor - Velo bank (previously Getin Bank) (%) | C18: ='Poland (Month)'!#REF! -> #REF!
B20: mBank
B21: NPS - mBank (%) | C21: ='Poland (Month)'!#REF! -> #REF!
B22: Rank - mBank | C22: =C59 -> #REF!
B23: Promoter - mBank (%) | C23: ='Poland (Month)'!#REF! -> #REF!
B24: Passive - mBank (%) | C24: ='Poland (Month)'!#REF! -> #REF!
B25: Detractor - mBank (%) | C25: ='Poland (Month)'!#REF! -> #REF!
B27: Pekao S.A.
B28: NPS - Pekao S.A. (%) | C28: ='Poland (Month)'!#REF! -> #REF!
B29: Rank - Pekao S.A. | C29: =C60 -> #REF!
B30: Promoter - Pekao S.A. (%) | C30: ='Poland (Month)'!#REF! -> #REF!
B31: Passive - Pekao S.A. (%) | C31: ='Poland (Month)'!#REF! -> #REF!
B32: Detractor - Pekao S.A. (%) | C32: ='Poland (Month)'!#REF! -> #REF!
B34: PKO BP
B35: NPS - PKO BP (%) | C35: ='Poland (Month)'!#REF! -> #REF!
B36: Rank - PKO BP | C36: =C61 -> #REF!
B37: Promoter - PKO BP (%) | C37: ='Poland (Month)'!#REF! -> #REF!
B38: Passive - PKO BP (%) | C38: ='Poland (Month)'!#REF! -> #REF!
B39: Detractor - PKO BP (%) | C39: ='Poland (Month)'!#REF! -> #REF!
B41: Santander
B42: NPS - Santander (%) | C42: ='Poland (Month)'!#REF! -> #REF!
B43: Rank - Santander | C43: =C62 -> #REF!
B44: Promoter - Santander (%) | C44: ='Poland (Month)'!#REF! -> #REF!
B45: Passive - Santander (%) | C45: ='Poland (Month)'!#REF! -> #REF!
B46: Detractor - Santander (%) | C46: ='Poland (Month)'!#REF! -> #REF!
B48: NPS - ING & Key competitors (For ranking)
B49: ING | C49: =C6 -> #REF!
B50: Velo bank (previously Getin Bank) | C50: =C14 -> #REF!
B51: mBank | C51: =C21 -> #REF!
B52: Pekao S.A. | C52: =C28 -> #REF!
B53: PKO BP | C53: =C35 -> #REF!
B54: Santander | C54: =C42 -> #REF!
B56: Ranking formule
B57: ING | C57: =RANK(C49,C$49:C$54,0) -> #REF!
B58: Velo bank (previously Getin Bank) | C58: =RANK(C50,C$49:C$54,0) -> #REF!
B59: mBank | C59: =RANK(C51,C$49:C$54,0) -> #REF!
B60: Pekao S.A. | C60: =RANK(C52,C$49:C$54,0) -> #REF!
B61: PKO BP | C61: =RANK(C53,C$49:C$54,0) -> #REF!
B62: Santander | C62: =RANK(C54,C$49:C$54,0) -> #REF!
B64: Base Size - NPS
B65: ING | C65: ='Poland (Month)'!#REF! -> #REF!
B66: Velo bank (previously Getin Bank) | C66: ='Poland (Month)'!#REF! -> #REF!
B67: mBank | C67: ='Poland (Month)'!#REF! -> #REF!
B68: Pekao S.A. | C68: ='Poland (Month)'!#REF! -> #REF!
B69: PKO BP | C69: ='Poland (Month)'!#REF! -> #REF!
B70: Santander | C70: ='Poland (Month)'!#REF! -> #REF!

Sheet Poland (Month)
B2: Source: Global NPS tracking / Toluna | C2: January - 2026 (6 months rolling) | D2: February - 2026 (6 months rolling) | E2: March - 2026 (6 months rolling)
B4: NPS total
B5: ING | C5: NPS | D5: NPS | E5: NPS
C6: ='Poland Crunch Output'!G21 -> 37.738385 | D6: ='Poland Crunch Output'!H21 -> 35.603056 | E6: ='Poland Crunch Output'!I21 -> 33.415363
B7: Promoter | C7: ='Poland Crunch Output'!G7 -> 0.49538712 | D7: ='Poland Crunch Output'!H7 -> 0.47932465 | E7: ='Poland Crunch Output'!I7 -> 0.44955854
B8: Passive | C8: ='Poland Crunch Output'!G8 -> 0.38660961 | D8: ='Poland Crunch Output'!H8 -> 0.39738126 | E8: ='Poland Crunch Output'!I8 -> 0.43503655
B9: Detractor | C9: ='Poland Crunch Output'!G9 -> 0.11800327 | D9: ='Poland Crunch Output'!H9 -> 0.12329409 | E9: ='Poland Crunch Output'!I9 -> 0.11540491
B10: Extremely likely | C10: ='Poland Crunch Output'!G10 -> 0.36285319 | D10: ='Poland Crunch Output'!H10 -> 0.32371577 | E10: ='Poland Crunch Output'!I10 -> 0.30167373
B11: 9 | C11: ='Poland Crunch Output'!G11 -> 0.13253393 | D11: ='Poland Crunch Output'!H11 -> 0.15560889 | E11: ='Poland Crunch Output'!I11 -> 0.14788481
B12: 8 | C12: ='Poland Crunch Output'!G12 -> 0.27830204 | D12: ='Poland Crunch Output'!H12 -> 0.27776395 | E12: ='Poland Crunch Output'!I12 -> 0.32027814
B13: 7 | C13: ='Poland Crunch Output'!G13 -> 0.10830758 | D13: ='Poland Crunch Output'!H13 -> 0.1196173 | E13: ='Poland Crunch Output'!I13 -> 0.11475841
B14: 6 | C14: ='Poland Crunch Output'!G14 -> 0.057307143 | D14: ='Poland Crunch Output'!H14 -> 0.06108891 | E14: ='Poland Crunch Output'!I14 -> 0.06925107
B15: 5 | C15: ='Poland Crunch Output'!G15 -> 0.049555588 | D15: ='Poland Crunch Output'!H15 -> 0.046580275 | E15: ='Poland Crunch Output'!I15 -> 0.034572076
B16: 4 | C16: ='Poland Crunch Output'!G16 -> 0 | D16: ='Poland Crunch Output'!H16 -> 0 | E16: ='Poland Crunch Output'!I16 -> 0
B17: 3 | C17: ='Poland Crunch Output'!G17 -> 0 | D17: ='Poland Crunch Output'!H17 -> 0.0063905527 | E17: ='Poland Crunch Output'!I17 -> 0.0061587941
B18: 2 | C18: ='Poland Crunch Output'!G18 -> 0 | D18: ='Poland Crunch Output'!H18 -> 0 | E18: ='Poland Crunch Output'!I18 -> 0
B19: 1 | C19: ='Poland Crunch Output'!G19 -> 0 | D19: ='Poland Crunch Output'!H19 -> 0 | E19: ='Poland Crunch Output'!I19 -> 0
B20: Extremely Unlikely | C20: ='Poland Crunch Output'!G20 -> 0.011140539 | D20: ='Poland Crunch Output'!H20 -> 0.0092343549 | E20: ='Poland Crunch Output'!I20 -> 0.0054229687
B21: n | C21: ='Poland Crunch Output'!G6 -> 133 | D21: ='Poland Crunch Output'!H6 -> 160 | E21: ='Poland Crunch Output'!I6 -> 163
B23: Velo bank (previously Getin Bank) | C23: NPS | D23: NPS | E23: NPS
C24: Low N | D24: Low N | E24: Low N
B25: Promoter | C25: Low N | D25: Low N | E25: Low N
B26: Passive | C26: Low N | D26: Low N | E26: Low N
B27: Detractor | C27: Low N | D27: Low N | E27: Low N
B28: Extremely likely | C28: Low N | D28: Low N | E28: Low N
B29: 9 | C29: Low N | D29: Low N | E29: Low N
B30: 8 | C30: Low N | D30: Low N | E30: Low N
B31: 7 | C31: Low N | D31: Low N | E31: Low N
B32: 6 | C32: Low N | D32: Low N | E32: Low N
B33: 5 | C33: Low N | D33: Low N | E33: Low N
B34: 4 | C34: Low N | D34: Low N | E34: Low N
B35: 3 | C35: Low N | D35: Low N | E35: Low N
